Workbook

Sheet Balance Sheet
A1: Consolidated statements of financial position (In millions of Canadian dollars)
A2: Field Name | B2: 2024 | C2: 2023 | D2: 2022 | E2: 2021 | F2: 2020 | G2: 2019 | H2: 2018 | I2: 2017 | J2: 2016 | K2: 2015
A3: Cash and cash equivalents | B3: 865 | C3: 1423 | D3: 307 | E3: 387 | F3: 367 | G3: 248 | H3: 182 | I3: 52 | J3: 98 | K3: 80
A4: Cash on deposit | C4: 1415 | D4: 297 | E4: 218 | F4: 67 | G4: 100 | I4: 29 | J4: 20
A5: Restricted Accounts - | B5: 83
A6: Cash and cash equivalents - Balancing value | B6: 782
A7: Cash equivalents | C7: 8 | D7: 10 | E7: 169 | F7: 300 | G7: 148 | I7: 23 | J7: 78
A8: Trade and other receivables | B8: 604 | C8: 747 | D8: 949 | E8: 474 | F8: 499 | G8: 334 | H8: 438 | I8: 278 | J8: 223 | K8: 190
A9: Accrued revenues | B9: 292 | C9: 281 | D9: 765 | E9: 308 | F9: 330 | G9: 199 | I9: 99 | J9: 106
A10: Trade receivables | B10: 109 | C10: 281 | D10: 70 | E10: 62 | F10: 50 | G10: 36
A11: Accounts receivable | C11: 283 | D11: 72 | E11: 63 | F11: 51 | G11: 36 | I11: 79 | J11: 33
A12: Allowance for doubtful accounts | C12: -2 | D12: -2 | E12: -1 | F12: -1 | G12: 0 | I12: 0 | J12: 0
A13: Income taxes recoverable | B13: 97 | C13: 78 | D13: 11 | E13: 7 | F13: 29 | G13: 5 | I13: 1 | J13: 1
A14: Finance lease receivable | B14: 12 | C14: 9 | D14: 7 | I14: 23 | J14: 22
A15: Prepayments | B15: 36 | C15: 40 | D15: 39 | E15: 42 | F15: 36 | G15: 41 | I15: 25 | J15: 9
A16: Government grant receivable | B16: 58 | C16: 58 | D16: 57 | E16: 55 | F16: 54 | G16: 53 | I16: 51 | J16: 52
A17: Inventories | B17: 235 | C17: 309 | D17: 242 | E17: 217 | F17: 220 | G17: 203 | H17: 200 | I17: 120 | J17: 118 | K17: 99
A18: Parts and other consumables | B18: 117 | C18: 106 | D18: 125 | E18: 144 | F18: 157 | G18: 120 | I18: 86 | J18: 74
A19: Coal | B19: 4 | C19: 23 | D19: 24 | E19: 22 | F19: 13 | G19: 16 | I19: 13 | J19: 15
A20: Emission credits | B20: 114 | C20: 180 | D20: 93 | E20: 51 | F20: 50 | G20: 67 | I20: 21 | J20: 29
A21: Derivative financial instruments assets | B21: 244 | C21: 153 | D21: 188 | E21: 108 | F21: 71 | G21: 46 | H21: 77 | I21: 92 | J21: 115 | K21: 93
A22: Current Assets | B22: 1948 | C22: 2632 | D22: 1686 | E22: 1186 | F22: 1157 | G22: 831 | H22: 897 | I22: 542 | J22: 554 | K22: 462
A23: Property, plant and equipmen, Gross | F23: 8137 | G23: 7763 | J23: 4754 | K23: 4523
A24: Plant and equipment - Accumulated Depreciation | F24: -2039 | G24: -1674 | J24: -990 | K24: -846
A25: Property, plant and equipment | B25: 8061 | C25: 6557 | D25: 6360 | E25: 6203 | F25: 6098 | G25: 6089 | H25: 5356 | I25: 4378 | J25: 3764 | K25: 3679
A26: Construction work in progress | B26: 863 | C26: 1206 | D26: 719 | E26: 396 | F26: 168 | G26: 350 | H26: 136 | I26: 64 | J26: 253 | K26: 27
A27: Land | B27: 166 | C27: 147 | D27: 147 | E27: 147 | F27: 150 | G27: 151 | H27: 122 | I27: 118 | J27: 116 | K27: 116
A28: Plant and equipment - Gross | B28: 9483 | C28: 8182 | D28: 8007 | E28: 7846 | F28: 7819 | G28: 7262 | H28: 6730 | I28: 5369 | J28: 4385 | K28: 4380
A29: Plant and equipment - Accumulated Depreciation | B29: -2451 | C29: -2978 | D29: -2513 | E29: -2186 | F29: -2039 | G29: -1674 | H29: -1632 | I29: -1173 | J29: -990 | K29: -846
A30: Plant and equipment - Net - Balancing value | K30: 2
A31: Intangible Assets - Gross - Total | F31: 980 | G31: 922
A32: Intangible Assets - Accumulated Amortization & Impairment - Total | F32: -207 | G32: -127
A33: Intangible assets and goodwill | B33: 744 | C33: 775 | D33: 817 | E33: 784 | F33: 773 | G33: 795
A34: Intangible work in progress - Gross | B34: 10 | C34: 111 | D34: 41 | E34: 3 | F34: 20 | G34: 21 | H34: 57 | I34: 29 | J34: 29 | K34: 27
A35: PPAs - Gross | B35: 688 | C35: 583 | D35: 605 | E35: 599 | F35: 599 | G35: 604 | H35: 164 | I35: 55 | J35: 11 | K35: 140
A36: PPAs - Accumulated Amortisation | B36: -351 | C36: -270 | D36: -264 | E36: -192 | F36: -126 | G36: -58 | H36: -21 | I36: -12 | J36: -7 | K36: -79
A37: Contract rights - Gross | B37: 93 | C37: 88 | D37: 87 | E37: 82 | F37: 66 | G37: 60 | H37: 50 | I37: 49 | J37: 41 | K37: 37
A38: Contract rights - Accumulated Amortisation | B38: -36 | C38: -31 | D38: -27 | E38: -23 | F38: -19 | G38: -16 | H38: -14 | I38: -11 | J38: -9 | K38: -7
A39: Other rights - Gross | B39: 287 | C39: 167 | D39: 170 | E39: 158 | F39: 137 | G39: 124 | H39: 206 | I39: 165 | J39: 164 | K39: 155
A40: Other rights - Accumulated Amortisation | B40: -45 | C40: -36 | D40: -32 | E40: -27 | F40: -22 | G40: -18 | H40: -34 | I40: -26 | J40: -18 | K40: -13
A41: Emission credits - Gross | B41: 45 | C41: 109 | D41: 182 | E41: 127 | F41: 67 | G41: 25 | H41: 47 | I41: 129 | J41: 61 | K41: 46
A42: Software - Gross | B42: 62 | C42: 58 | D42: 55 | E42: 67 | F42: 56 | G42: 53 | H42: 55 | I42: 55 | J42: 53 | K42: 51
A43: Software - Accumulated Amortisation | B43: -44 | C43: -39 | D43: -35 | E43: -45 | F43: -40 | G43: -35 | H43: -37 | I43: -32 | J43: -26 | K43: -21
A44: Goodwill - Gross | B44: 35 | C44: 35 | D44: 35 | E44: 35 | F44: 35 | G44: 35
A45: Derivative financial instruments assets | B45: 412 | C45: 199 | D45: 295 | E45: 222 | F45: 177 | G45: 140 | H45: 82 | I45: 79 | J45: 154 | K45: 127
A46: Finance lease receivables | I46: 644 | J46: 667 | K46: 689
A47: Deferred tax assets | B47: 26 | C47: 16 | D47: 20 | E47: 17 | F47: 19 | G47: 24 | H47: 59 | I47: 74 | J47: 16 | K47: 18
A48: Intangible assets | H48: 473 | I48: 401 | J48: 299 | K48: 341
A49: Intangible assets - Balancing value | K49: 5
A50: Total Intangible Assets , Gross | J50: 359 | K50: 456
A51: Acc Amort/Imp Total Intangible Assets | J51: -60 | K51: -120
A52: Goodwill | H52: 35 | I52: 35 | J52: 23 | K52: 30
A53: Other assets | B53: 132 | C53: 110 | D53: 49 | E53: 47 | F53: 37 | G53: 53 | H53: 66 | I53: 68 | J53: 20 | K53: 24
A54: Equity-accounted investments | B54: 1096 | C54: 455 | D54: 437 | E54: 145 | F54: 134 | G54: 132 | H54: 142 | I54: 184 | J54: 18 | K54: 10
A55: Other financial assets | J55: 5 | K55: 13
A56: Government grants receivable | B56: 380 | C56: 269 | D56: 310 | E56: 349 | F56: 387 | G56: 423 | H56: 459 | I56: 493 | J56: 542
A57: Right-of-use assets | B57: 118 | C57: 118 | D57: 127 | E57: 120 | F57: 129 | G57: 95 | H57: 0
A58: Finance lease receivable | B58: 13 | C58: 25 | D58: 34
A59: Total Non-current Assets | B59: 10982 | C59: 8524 | D59: 8449 | E59: 7887 | F59: 7754 | G59: 7751 | H59: 6672 | I59: 6356 | J59: 5508 | K59: 4931
A60: Total Assets | B60: 12930 | C60: 11156 | D60: 10135 | E60: 9073 | F60: 8911 | G60: 8582 | H60: 7569 | I60: 6898 | J60: 6062 | K60: 5393
A61: Trade and other payables | B61: 751 | C61: 717 | D61: 1249 | E61: 624 | F61: 470 | G61: 301 | H61: 244 | I61: 216 | J61: 217 | K61: 181
A62: Trade payables | B62: 163 | C62: 183 | D62: 117 | E62: 69 | F62: 78 | G62: 63 | I62: 38 | J62: 70
A63: Operating accruals | B63: 427 | C63: 420 | D63: 1025 | E63: 436 | F63: 308 | G63: 137 | I63: 103 | J63: 90
A64: Dividends payable | B64: 91 | C64: 72 | D64: 68 | E64: 64 | F64: 54 | G64: 50 | I64: 44 | J64: 37
A65: Taxes payable | B65: 0 | C65: 1 | D65: 5 | E65: 31 | F65: 7 | G65: 32 | I65: 11 | J65: 6
A66: Accrued interest | B66: 70 | C66: 41 | D66: 34 | E66: 24 | F66: 23 | G66: 19 | I66: 19 | J66: 13
A67: Deferred revenue and other liabilities | B67: 213 | C67: 96 | D67: 158 | E67: 153 | F67: 135 | G67: 60 | H67: 62 | I67: 58 | J67: 57 | K67: 2
A68: Deferred government grant revenue | C68: 0 | D68: 117 | E68: 117 | F68: 117 | G68: 42
A69: Lease liabilities | C69: 7 | D69: 7 | E69: 6 | F69: 6 | G69: 6 | I69: 1 | J69: 1
A70: Contract Liabilities | B70: 4 | C70: 5 | D70: 7 | E70: 6 | F70: 4 | G70: 4
A71: Deferred payments on capital project costs | B71: 178 | C71: 66 | D71: 11
A72: Other deferred revenue and liabilities | B72: 31 | C72: 18 | D72: 16 | E72: 24 | F72: 8 | G72: 8
A73: Derivative financial instruments liabilities | B73: 147 | C73: 178 | D73: 600 | E73: 252 | F73: 91 | G73: 143 | H73: 90 | I73: 86 | J73: 48 | K73: 27
A74: Provisions | B74: 85 | C74: 67 | D74: 72 | E74: 50 | F74: 37 | G74: 41 | H74: 54 | I74: 37 | J74: 26 | K74: 22
A75: Loans and borrowings | B75: 157 | C75: 590 | D75: 133 | E75: 126 | F75: 417 | G75: 857 | H75: 456 | I75: 239 | J75: 200 | K75: 339
A76: Subscription receipts | B76: 0 | C76: 399
A77: Total Current Liabilities | B77: 1353 | C77: 2047 | D77: 2212 | E77: 1205 | F77: 1150 | G77: 1402 | H77: 906 | I77: 636 | J77: 548 | K77: 571
A78: Derivative financial instruments liabilities | B78: 494 | C78: 422 | D78: 624 | E78: 352 | F78: 212 | G78: 107 | H78: 114 | I78: 56 | J78: 44 | K78: 26
A79: Loans and borrowings | B79: 4819 | C79: 4126 | D79: 3593 | E79: 3234 | F79: 3135 | G79: 2556 | H79: 2191 | I79: 1907 | J79: 1308 | K79: 1276
A80: Deferred revenue and other liabilities | B80: 323 | C80: 206 | D80: 245 | E80: 291 | F80: 277 | G80: 383 | H80: 587 | I80: 581 | J80: 632 | K80: 97
A81: Deferred government grant revenue | F81: 192 | G81: 299
A82: Contract Liabilities | B82: 29 | C82: 8 | D82: 34 | E82: 36 | F82: 44 | G82: 43
A83: Deferred revenue and other liabilities - Balancing value | B83: 294 | C83: 198 | D83: 211 | E83: 255
A84: Other deferred revenue and liabilities | F84: 41 | G84: 41
A85: Provisions | B85: 373 | C85: 352 | D85: 325 | E85: 411 | F85: 464 | G85: 416 | H85: 291 | I85: 265 | J85: 231 | K85: 210
A86: Lease liabilities | B86: 134 | C86: 140 | D86: 146 | E86: 137 | F86: 143 | G86: 105 | H86: 17 | I86: 17 | J86: 19 | K86: 21
A87: Deferred tax liabilities | B87: 863 | C87: 677 | D87: 530 | E87: 584 | F87: 601 | G87: 512 | H87: 410 | I87: 374 | J87: 379 | K87: 376
A88: Equity attributable to shareholders of the Company | B88: 7006 | C88: 5923 | D88: 5463 | E88: 5009 | F88: 4832 | G88: 4079 | H88: 3610 | I88: 3200 | J88: 2613 | K88: 2006
A89: Total liabilities | B89: 8359 | C89: 7970 | D89: 7675 | E89: 6214 | F89: 5982 | G89: 5481 | H89: 4516 | I89: 3836 | J89: 3161 | K89: 2577
A90: Share capital | B90: 4301 | C90: 3524 | D90: 3498 | E90: 3631 | F90: 3465 | G90: 3441 | H90: 3200 | I90: 3262 | J90: 2918 | K90: 2744
A91: Common Stock - Issued & Paid | B91: 3848 | C91: 2921 | D91: 2895 | E91: 2878 | F91: 2512 | G91: 2488 | H91: 2393 | I91: 2455 | J91: 2258
A92: Other Preferred Stock | B92: 453 | C92: 603 | D92: 603 | E92: 753 | F92: 953 | G92: 953 | H92: 807 | I92: 807 | J92: 660
A93: Other reserves | B93: 349 | C93: 70 | D93: -209 | E93: -119 | F93: -91 | G93: -30 | H93: 32 | I93: -67 | J93: 49 | K93: 74
A94: Cash Flow Hedges | B94: 108 | C94: 48 | D94: -264 | E94: -84 | F94: -48 | G94: -10 | H94: 7 | I94: -39 | J94: 22
A95: Translation Reserve | B95: 240 | C95: 22 | D95: 53 | E95: -28 | F95: -34 | G95: -16 | H95: 23 | I95: -27 | J95: 26
A96: Defined Benefit Plan, Acturial Gains/Los | B96: -9 | C96: -10 | D96: -8 | E96: -17 | F96: -20 | G96: -15 | H96: -9 | I96: -11 | J96: -10
A97: Employee Benefits | B97: 10 | C97: 10 | D97: 10 | E97: 10 | F97: 11 | G97: 11 | H97: 11 | I97: 10 | J97: 11
A98: Deficit | B98: -74 | C98: -404 | D98: -835 | E98: -671 | F98: -474 | G98: -347 | H98: -222 | I98: -181 | J98: -124 | K98: -70
A99: Deficit and other reserves | B99: 4576 | C99: 3190 | D99: 2454 | E99: 2841 | F99: 2900 | G99: 3064 | H99: 3010 | I99: 3014 | J99: 2843 | K99: 2748
A100: Non-controlling interests | B100: -5 | C100: -4 | D100: 6 | E100: 18 | F100: 29 | G100: 37 | H100: 43 | I100: 48 | J100: 58 | K100: 68
...

Sheet Cash Flow
A1: Consolidated statements of cash flows (In millions of Canadian dollars)
A2: Field Name | B2: 2024 | C2: 2023 | D2: 2022 | E2: 2021 | F2: 2020 | G2: 2019 | H2: 2018 | I2: 2017 | J2: 2016 | K2: 2015
A3: Net income | B3: 701 | C3: 737 | D3: 128 | E3: 87 | F3: 130 | G3: 119 | H3: 258 | I3: 134 | J3: 102 | K3: 86
A4: Depreciation and amortization | B4: 503 | C4: 574 | D4: 553 | E4: 539 | F4: 478 | G4: 473 | H4: 335 | I4: 271 | J4: 216 | K4: 215
A5: Gain on acquisition transaction | G5: -24 | H5: -159
A6: Impairments | F6: 26 | G6: 401 | I6: 83 | J6: 6
A7: Net finance expense | B7: 221 | C7: 166 | D7: 156 | E7: 174 | F7: 197 | G7: 156 | H7: 123 | I7: 108 | J7: 86 | K7: 94
A8: Fair value changes on commodity derivative instruments and emission credits held for trading | B8: -238 | C8: -321 | D8: 429 | E8: 220 | F8: 15 | G8: -118 | H8: 67 | I8: 41 | J8: -12 | K8: 1
A9: Foreign exchange gain | J9: -4 | K9: 17
A10: Other items | B10: 44 | C10: 13 | D10: 39 | E10: 9 | F10: 13 | G10: 21 | H10: 6 | I10: -21 | J10: -13 | K10: -17
A11: Reduction in finance lease receivables | I11: 22 | J11: 21 | K11: 19
A12: Interest paid | B12: -163 | C12: -111 | D12: -89 | E12: -111 | F12: -132 | G12: -110 | H12: -96 | I12: -81 | J12: -73 | K12: -80
A13: Income taxes recovered (paid) | B13: -38 | C13: -214 | D13: -37 | E13: 7 | F13: -41 | K13: -1
A14: Realized losses on settlement of interest rate derivatives | F14: -24
A15: Miscellaneous financing fees paid | F15: -5
A16: Reclamation costs | F16: -3
A17: Other | F17: -13
A18: Other cash items | B18: 15 | C18: -29 | D18: -13 | E18: -30 | F18: -45 | G18: -67 | H18: -22 | I18: -16 | J18: -25 | K18: -5
A19: Income tax (recovery) expense | B19: 198 | C19: 204 | D19: 13 | E19: 60 | F19: 82 | G19: -6 | H19: 90 | I19: -41 | J19: 30 | K19: 66
A20: Change in non-cash operating working capital | B20: 173 | C20: -226 | D20: 179 | E20: 100 | F20: 26 | G20: 69 | H20: -43 | I20: -40 | J20: 20 | K20: 11
A21: Change in fair value of derivative instruments reflected as cash settlement | B21: 13 | C21: 249 | D21: -213 | E21: -43 | F21: -14 | G21: 29 | H21: 21 | I21: -5 | J21: -31 | K21: 8
A22: Trade and other receivables | B22: 194 | F22: -23 | I22: -26 | J22: 17 | K22: 11
A23: Inventories | B23: 77 | F23: -31 | I23: 4 | J23: 5 | K23: 13
A24: Trade and other payables | B24: -58 | F24: 89 | I24: -14 | J24: -7
A25: Deferred revenue and other liabilities | B25: -5 | F25: -5 | K25: -1
A26: Provisions | B26: -35 | F26: -4 | I26: -4 | J26: 5 | K26: -7
A27: Distributions received from equity-accounted investments | B27: 120 | C27: 36 | D27: 16 | E27: 11 | F27: 11 | G27: 12 | H27: 30 | I27: 27 | J27: 24
A28: Income from equity-accounted investments | B28: -76 | C28: -65 | D28: -32 | E28: -9 | F28: 3 | G28: -2 | H28: -19 | I28: -31 | J28: -25
A29: Loss on de-recognition of power purchase arrangement | J29: 53
A30: Recognition of government grant deferred revenue | C30: -126 | D30: -126 | E30: -126 | F30: -50 | G30: -181 | H30: -51 | I30: -51
A31: Foreign exchange (gains) losses | B31: 29 | C31: 6 | D31: 15 | E31: 9 | G31: 5 | H31: -10 | I31: -28
A32: Tax-equity attributes | B32: -76 | C32: -71 | D32: -83 | E32: -88 | F32: -88 | G32: -57 | H32: -80
A33: Impairment reversal | E33: 58
A34: Impairment | B34: 27
A35: Gain on divestiture | B35: -309
A36: Net cash flows from operating activities | B36: 1144 | C36: 822 | D36: 935 | E36: 867 | F36: 611 | G36: 720 | H36: 450 | I36: 372 | J36: 375 | K36: 419
A37: Purchase of Property, plant and equipment and other assets | B37: -1070 | C37: -723 | D37: -682 | E37: -622 | F37: -306 | G37: -635 | H37: -355 | I37: -218 | J37: -313 | K37: -140
A38: Proceeds on disposal of joint venture | G38: 90 | H38: 126
A39: Other cash flows from investing activities | B39: -5 | D39: -5 | E39: 7 | F39: -2 | G39: 19 | I39: 17 | J39: 21 | K39: 18
A40: Change in non-cash investing working capital | F40: -12 | G40: 2 | H40: 24 | I40: -54 | J40: 39 | K40: -14
A41: Government grant received | D41: 50 | E41: 50 | F41: 50 | G41: 50 | H41: 50 | I41: 50
A42: Genesee Coal Mine prepayment | I42: -70
A43: Business acquisitions, net of acquired cash | B43: -908 | C43: -134 | F43: -79 | G43: -392 | H43: -399 | I43: -839
A44: Government grant received | B44: 50 | C44: 50
A45: Acquisition of equity-accounted investment | B45: -316 | D45: -273
A46: Divestiture | B46: 333
A47: Net cash flows used in investing activities | B47: -1916 | C47: -807 | D47: -910 | E47: -565 | F47: -349 | G47: -866 | H47: -554 | I47: -1114 | J47: -253 | K47: -136
A48: Proceeds from issue of loans and borrowings | B48: 1050 | C48: 1200 | D48: 447 | E48: 236 | F48: 578 | G48: 900 | H48: 705 | I48: 1098 | J48: 164 | K48: 220
A49: Repayment of loans and borrowings | B49: -781 | C49: -145 | D49: -71 | E49: -341 | F49: -444 | G49: -633 | H49: -195 | I49: -507 | J49: -260 | K49: -267
A50: Issue costs on loans and borrowings | B50: -9 | C50: -6 | D50: -4 | E50: -8 | F50: -9 | G50: -7 | H50: -6 | I50: -10 | K50: -1
A51: Proceeds from exercise of share options | B51: 26 | C51: 8 | D51: 16 | E51: 21 | F51: 18 | G51: 23 | H51: 14 | I51: 17 | K51: 2
A52: Issue of shares | G52: 300 | I52: 150 | J52: 200
A53: Share issue costs | B53: -27 | E53: -12 | G53: -12 | I53: -11 | J53: -6
A54: Distributions to non-controlling interests | B54: -3 | C54: -3 | D54: -2 | K54: -13
A55: Dividends - Common - Cash Paid | F55: -194 | G55: -190
A56: Preferred share dividends paid | F56: -48 | G56: -48 | I56: -35 | J56: -23 | K56: -22
A57: Dividends paid | B57: -280 | C57: -290 | D57: -296 | E57: -219 | F57: -242 | G57: -238 | H57: -217 | I57: -159 | J57: -143 | K57: -106
A58: Capitalized interest paid | B58: -56 | C58: -41 | D58: -21 | E58: -10 | F58: -5 | G58: -13 | H58: -5 | I58: -6 | J58: -3 | K58: -9
A59: Income taxes paid on preferred share dividends | B59: -13 | C59: -13 | D59: -15 | E59: -21 | F59: -22 | G59: -19 | H59: -19 | I59: -10 | J59: -8 | K59: -9
A60: Common shares purchased | F60: -10 | G60: -74 | H60: -76 | J60: -22 | K60: -121
A61: Issue of share capital | B61: 460 | E61: 288 | I61: 183
A62: Other cash items | B62: -8 | E62: -3 | F62: -2 | G62: -9 | H62: -1 | I62: -1 | J62: -1
A63: Proceeds on sale and leaseback of generating facility | K63: 46
A64: Realized gains (losses) on settlement of foreign exchange derivatives | I64: -12
A65: Realized gains on settlement of foreign exchange derivatives | H65: 33
A66: Repayment of lease liabilities | B66: -7 | C66: -6 | D66: -6 | E66: -6 | F66: -6
A67: Distributions to non-controlling interests | F67: -2
A68: Redemption of preferred shares | B68: -150 | D68: -150 | E68: -200
A69: Net proceeds from issuance of subscription receipts2 | C69: 399
A70: Net cash flows from financing activities | B70: 202 | C70: 1103 | D70: -102 | E70: -275 | F70: -146 | G70: 218 | H70: 233 | I70: 697 | J70: -102 | K70: -280
A71: Foreign exchange loss on cash held in a foreign currency | B71: 17 | C71: -2 | D71: -3 | E71: -7 | F71: 3 | G71: -6 | H71: 1 | I71: -1 | J71: -2 | K71: 6
A72: Cash derecognized on loss of control of subsidiaries | B72: -5
A73: Cash and cash equivalents at beginning of period | B73: 1423 | C73: 307 | D73: 387 | E73: 367 | F73: 248 | G73: 182 | H73: 52 | I73: 98 | J73: 80 | K73: 71
A74: Cash and cash equivalents at end of period | B74: 865 | C74: 1423 | D74: 307 | E74: 387 | F74: 367 | G74: 248 | H74: 182 | I74: 52 | J74: 98 | K74: 80
A75: Net decrease in cash and cash equivalents | B75: -558 | C75: 1116 | D75: -80 | E75: 20 | F75: 119 | G75: 66 | H75: 130 | I75: -46 | J75: 18 | K75: 9

Sheet Income sheet
A1: Consolidated statements of Income (In millions of Canadian dollars)
A2: Field Name | B2: 2024 | C2: 2023 | D2: 2022 | E2: 2021 | F2: 2020 | G2: 2019 | H2: 2018 | I2: 2017 | J2: 2016 | K2: 2015
A3: Revenues | B3: 3677 | C3: 4068 | D3: 2712 | E3: 1757 | F3: 1791 | G3: 1713 | H3: 1272 | I3: 1046 | J3: 1214 | K3: 1241
A4: Other income | B4: 99 | C4: 214 | D4: 217 | E4: 233 | F4: 146 | G4: 250 | H4: 145 | I4: 100
A5: Revenues and other income | B5: 3776 | C5: 4282 | D5: 2929 | E5: 1990 | F5: 1937 | G5: 1963 | H5: 1417 | I5: 1146 | J5: 1214 | K5: 1241
A6: Energy purchases and fuel | B6: 1787 | C6: 2166 | D6: 1578 | E6: 667 | F6: 584 | G6: 418 | H6: 434 | I6: 318 | J6: 420 | K6: 479
A7: Gross margin | B7: 1989 | C7: 2116 | D7: 1351 | E7: 1323 | F7: 1353 | G7: 1545 | H7: 983 | I7: 828 | J7: 794 | K7: 762
A8: Other raw materials and operating charges | B8: 209 | C8: 159 | D8: 154 | E8: 151 | F8: 160 | G8: 140 | H8: 124 | I8: 114 | J8: 102 | K8: 96
A9: Share-based payments | B9: 41 | C9: 12 | D9: 25 | E9: 16 | F9: 9 | G9: 16 | H9: 14 | I9: 11 | J9: 11 | K9: -1
A10: Staff costs and employee benefits expense - Balancing value | B10: 213 | C10: 167 | D10: 159 | E10: 160 | F10: 162 | G10: 151 | H10: 131 | I10: 118 | J10: 113 | K10: 121
A11: Staff costs and employee benefits expense | B11: 254 | C11: 179 | D11: 184 | E11: 176 | F11: 171 | G11: 167 | H11: 145 | I11: 129 | J11: 124 | K11: 120
A12: Losses on termination of power purchase arrangement | J12: 73
A13: Impairments | F13: 26 | G13: 401 | I13: 83 | J13: 6
A14: Depreciation of property plant and equipment | B14: 400 | C14: 489 | D14: 462 | E14: 445 | F14: 383 | G14: 356 | H14: 309 | I14: 249 | J14: 198 | K14: 186
A15: Amortisation of Contract rights and Other rights | B15: 4 | C15: 4 | D15: 9 | E15: 4 | F15: 7 | G15: 101 | H15: 19 | I15: 10 | J15: 7 | K15: 6
A16: Amortisation of Computer Software | B16: 5 | C16: 4 | D16: 6 | E16: 5 | F16: 5 | G16: 4 | H16: 5 | I16: 6 | J16: 5 | K16: 6
A17: Amortization of intangible assets - Balancing value | B17: 84 | C17: 66 | D17: 67 | E17: 71 | F17: 69
A18: Amortization of intangible assets | B18: 93 | C18: 74 | D18: 82 | E18: 80 | F18: 81 | G18: 105 | H18: 24 | I18: 5 | J18: 4 | K18: 12
A19: Depreciation of Financial Lease Right-of-Use Assets | B19: 10 | C19: 10 | D19: 9 | E19: 9 | F19: 9 | G19: 8
A20: Depreciation and amortization | B20: 503 | C20: 574 | D20: 553 | E20: 539 | F20: 478 | G20: 473 | H20: 335 | I20: 271 | J20: 216 | K20: 215
A21: Losses on retirement of property plant and equipment | J21: 1 | K21: 2
A22: Other | C22: 1 | E22: 5 | F22: 5 | G22: 4 | H22: 2 | I22: 1 | J22: 1 | K22: 3
A23: Operating lease payment | I23: 8 | J23: 8 | K23: 8
A24: Other administrative expense - Balancing value | I24: 81 | J24: 78 | K24: 77
A25: Other administrative expense | B25: 201 | C25: 153 | D25: 143 | E25: 114 | F25: 106 | G25: 116 | H25: 96 | I25: 89 | J25: 86 | K25: 85
A26: Foreign exchange gain (loss) | B26: 29 | C26: 6 | D26: 15 | E26: 9 | G26: 5 | H26: -10 | I26: -28 | J26: -6 | K26: 15
A27: Impairment reversal | E27: 58
A28: Impairment | B28: 27
A29: Reported Operating Expense | B29: 1223 | C29: 1071 | D29: 1049 | E29: 1047 | F29: 941 | G29: 1302 | H29: 690 | I29: 658 | J29: 601 | K29: 531
A30: Operating (loss) income | B30: 766 | C30: 1045 | D30: 302 | E30: 276 | F30: 412 | G30: 243 | H30: 293 | I30: 170 | J30: 193 | K30: 231
A31: Gain on divestiture | B31: 309
A32: Inventory write-downs - Gain/Loss | C32: -1 | D32: -18
A33: Net (losses) gains related to decommissioning of facilitie | B33: -11 | D33: -6
A34: Termination fees | B34: -18 | D34: -13
A35: Insurance recoveries, net of related expenses | C35: 3
A36: Other losses on disposal | B36: -2 | C36: -5
A37: Losses on disposals and other transactions | B37: -31 | C37: -3 | D37: -37
A38: (Loss) gain on disposals and other transactions | E38: 36 | G38: 24 | H38: 159
A39: Interest on long-term debt | B39: -270 | C39: -195 | D39: -153 | E39: -142 | F39: -165 | G39: -146 | H39: -115 | I39: -105 | J39: -77 | K39: -89
A40: Capitalized interest | B40: 56 | C40: 41 | D40: 21 | E40: 10 | F40: 5 | G40: 13 | H40: 5 | I40: 6 | J40: 3 | K40: 9
A41: Realized losses on settlement of interest rate derivatives | B41: 14 | C41: 34 | D41: 10
A42: Unrealized losses representing changes in the fair value of interest rate derivatives | C42: -14 | D42: 5
A43: Termination of interest rate non-hedges | J43: -11
A44: Other - Balancing value | B44: -9 | C44: -14 | D44: -13
A45: Gain on interest rate non hedges | J45: 8 | K45: -2
A46: Interest on lease liabilities | B46: -9 | C46: -9 | D46: -8 | E46: -5 | F46: -6 | G46: -5 | H46: -1
A47: Charge on early debt extinguishment | K47: -1
A48: Accretion on decommissioning provisions | B48: -12 | C48: -11 | D48: -7 | E48: -8 | F48: -5 | G48: -6 | H48: -5 | I48: -4 | J48: -3 | K48: -4
A49: Contributions and grants | B49: 5 | C49: 6 | D49: 2 | E49: -36 | F49: -23 | G49: -10 | H49: -7 | I49: -5 | J49: -6 | K49: -7
A50: Accretion on deferred government grant revenue | C50: -9 | D50: -23 | E50: 13 | F50: -17 | G50: 17 | H50: 16 | I50: 17 | J50: -2
A51: Interest on long-term government grant receivable | B51: 9 | C51: 11 | D51: 12 | E51: -6 | F51: 14 | G51: -15 | H51: -16 | I51: -17 | J51: 2
A52: Net finance expense - Balancing value | G52: -4
A53: Net finance expense | B53: -221 | C53: -166 | D53: -156 | E53: -174 | F53: -197 | G53: -156 | H53: -123 | I53: -108 | J53: -86 | K53: -94
A54: Income from equity-accounted investments | B54: 76 | C54: 65 | D54: 32 | E54: 9 | F54: -3 | G54: 2 | H54: 19 | I54: 31 | J54: 25 | K54: 15
A55: Non-operating Income/(Expense), Net | B55: 133 | C55: -104 | D55: -161 | E55: -129 | F55: -200 | G55: -130 | H55: 55 | I55: -77 | J55: -61 | K55: -79
A56: (Loss) income before tax | B56: 899 | C56: 941 | D56: 141 | E56: 147 | F56: 212 | G56: 113 | H56: 348 | I56: 93 | J56: 132 | K56: 152
A57: Income tax recovery (expense) | B57: 198 | C57: 204 | D57: 13 | E57: 60 | F57: 82 | G57: -6 | H57: 90 | I57: -41 | J57: 30 | K57: 66
A58: Total current income tax expense | B58: 31 | C58: 155 | D58: 20 | E58: 60 | F58: 18 | G58: 54 | H58: 18 | I58: 16 | J58: 15 | K58: 10 | L58: =B57/B56 -> 0.22024472 | M58: =C57/C56 -> 0.21679065 | N58: =D57/D56 -> 0.092198582 | O58: =E57/E56 -> 0.40816327 | P58: =F57/F56 -> 0.38679245 | Q58: =G57/G56 -> -0.053097345 | R58: =H57/H56 -> 0.25862069 | S58: =I57/I56 -> -0.44086022 | ... U58: =K57/K56 -> 0.43421053 | V58: =SUM(L58:U58)/10 -> 0.1750336
A59: Relating To Origination And Reversal Of temporary differences | B59: 176 | C59: 57 | D59: -6 | E59: 23 | F59: 64 | G59: -6 | H59: 77 | I59: 4 | J59: 43 | K59: 37
A60: Post-employment defined benefit plan expense | D60: 3 | E60: -2 | F60: 2 | H60: 4 | I60: -3 | J60: 9 | K60: 5 | S60: =POWER((L58-V58),0.1)-1 -> -0.26628986
A61: Relating to prior periods | K61: 1
A62: Post-employment defined contribution plan expense | B62: -9 | C62: -8 | D62: -4 | E62: -21 | F62: -2 | G62: -3 | H62: -9 | I62: -89 | J62: -37 | K62: -6
A63: Changes in US Tax rate | G63: -51 | I63: 31
A64: Change in statutory tax rate | K64: 19
A65: Income Taxes - Total | B65: 198 | C65: 204 | D65: 13 | E65: 60 | F65: 82 | G65: -6 | H65: 90 | I65: -41 | J65: 30 | K65: 66
A66: Net income | B66: 701 | C66: 737 | D66: 128 | E66: 87 | F66: 130 | G66: 119 | H66: 258 | I66: 134 | J66: 102 | K66: 86
A67: Income for the period attributable to shareholders | B67: 701 | C67: 737 | D67: 128 | E67: 87 | F67: 130 | G67: 119 | H67: 258 | I67: 134 | J67: 102 | K67: 86
A68: Non-controlling interests | B68: 2 | C68: -7 | D68: -10 | E68: -11 | F68: -6 | G68: -6 | H68: -7 | I68: -10 | J68: -9 | K68: -4
A69: Minority Interests | B69: 2 | C69: -7 | D69: -10 | E69: -11 | F69: -6 | G69: -6 | H69: -7 | I69: -10 | J69: -9 | K69: -4
A70: Income for the period attributable to shareholders | B70: 699 | C70: 744 | D70: 138 | E70: 98 | F70: 136 | G70: 125 | H70: 265 | I70: 144 | J70: 111 | K70: 90
A71: Preferred share dividends of the Company | B71: -34 | C71: -34 | D71: -39 | E71: -54 | F71: -54 | G71: -49 | H71: -42 | I71: -36 | J71: -23 | K71: -23
A72: Preferred Dividends and Similar | B72: -34 | C72: -34 | D72: -39 | E72: -54 | F72: -54 | G72: -49 | H72: -42 | I72: -36 | J72: -23 | K72: -23
A73: As Rep. Net Inc. Attrib. to Common S/H. | B73: 665 | C73: 710 | D73: 99 | E73: 44 | F73: 82 | G73: 76 | H73: 223 | I73: 108 | J73: 88 | K73: 67
A74: SubTotal | B74: 665 | C74: 710 | D74: 99 | E74: 44 | F74: 82 | G74: 76 | H74: 223 | I74: 108 | J74: 88 | K74: 67
A75: Income for the period attributable to shareholders | B75: 701 | C75: 737 | D75: 128 | E75: 87 | F75: 130 | G75: 119 | H75: 258 | I75: 134
A76: Actuarial gains | B76: 1 | C76: -2 | D76: 9 | E76: 3 | F76: -5 | I76: -1
A77: Unrealized (losses) gains on derivative instruments | B77: 81 | C77: 155 | D77: -508 | E77: -194 | F77: -12 | G77: -26 | H77: 15 | I77: -4
A78: Unrealized gains (losses) on derivative instruments – joint ventures | H78: 3 | I78: 3
A79: Reclassification of (gains) losses on derivative instruments to income for the year | B79: -25 | C79: 160 | D79: 328 | E79: 158 | F79: -26 | G79: 9 | H79: 14 | I79: -63
A80: Unrealized (losses) gains | B80: 218 | C80: -31 | D80: 81 | E80: 6 | F80: -18 | G80: -39 | H80: 50 | I80: -53
A81: Losses realized in net income on disposal of joint ventu | H81: 12
A82: Reclassification of losses on derivative instruments to income for the period joint venture | H82: 2 | I82: 3
A83: Equity-accounted investments | B83: 4 | C83: -3
A84: Other Comprehensive Income - Net of Tax - Total | B84: 279 | C84: 279 | D84: -90 | E84: -27 | F84: -61 | G84: -56 | H84: 96 | I84: -115
A85: Total comprehensive (loss) income | B85: 978 | C85: 1023 | D85: 48 | E85: 71 | F85: 75 | G85: 63 | H85: 363 | I85: 29
A86: Non-controlling interests | B86: 2 | C86: -7 | D86: -10 | E86: -11 | F86: -6 | G86: -6 | H86: -7 | I86: -10
A87: Total comprehensive income | B87: 980 | C87: 1016 | D87: 38 | E87: 60 | F87: 69 | G87: 63 | H87: 354 | I87: 19
A88: Basic earnings per share | B88: 5.16 | C88: 6.07 | D88: 0.85 | E88: 0.39 | F88: 0.78 | G88: 0.73 | H88: 2.17 | I88: 1.07 | J88: 0.91 | K88: 0.7
A89: Basic EPS Excluding ExtraOrdinary Items | B89: 5.16 | C89: 6.07 | D89: 0.85 | E89: 0.39 | F89: 0.78 | G89: 0.73 | H89: 2.17 | I89: 1.07 | J89: 0.91 | K89: 0.7
A90: As Reported Net Income-Fully Diluted | B90: 665 | C90: 710 | D90: 99 | E90: 44 | F90: 82 | G90: 76 | H90: 223 | I90: 108 | J90: 88 | K90: 67
A91: Weighted average number of common shares | B91: 128.9 | C91: 117.06 | D91: 116.54 | E91: 112.05 | F91: 105.3 | G91: 104.3 | H91: 102.98 | I91: 100.75 | J91: 96.21 | K91: 96.39
A92: Diluted weighted average number of common shares | B92: 129.23 | C92: 117.46 | D92: 117.22 | E92: 112.81 | F92: 105.85 | G92: 105.01 | H92: 103.33 | I92: 101.09 | J92: 96.21 | K92: 96.39
A93: Diluted earnings per share | B93: 5.15 | C93: 6.04 | D93: 0.84 | E93: 0.39 | F93: 0.77 | G93: 0.72 | H93: 2.16 | I93: 1.07 | J93: 0.91 | K93: 0.7
A94: Diluted EPS Excluding ExtraOrd Items | B94: 5.15 | C94: 6.04 | D94: 0.84 | E94: 0.39 | F94: 0.77 | G94: 0.72 | H94: 2.16 | I94: 1.07 | J94: 0.91 | K94: 0.7
A95: Diluted Net Income excluding Extra Items applicable to Common - (Company Level) | B95: 665 | C95: 710 | D95: 99 | E95: 44 | F95: 82 | G95: 76 | H95: 223 | I95: 108 | J95: 88 | K95: 67
A96: Revenue - Realized Derivative Gains/Losses (incl Reclassified from OCI) | B96: 826 | C96: 279 | D96: -1573 | E96: -840 | F96: 38 | G96: 71 | H96: 55 | I96: 131 | J96: 393 | K96: 234
A97: Energy purchases and fuel - Derivatives | B97: -379 | C97: -272 | D97: 500 | E97: 421 | F97: 28 | G97: 92 | H97: -76 | I97: -18 | J97: -136 | K97: -102
A98: Foreign exchange (loss) gain - Derivatives | B98: -5 | D98: -1 | E98: -2 | F98: 1 | G98: -3 | H98: 13 | I98: -37 | J98: -5 | K98: 49
A99: Finance expense - Derivatives | B99: 14 | C99: 20 | D99: 15 | E99: 3 | F99: -14 | J99: -3 | K99: -2
A100: Audit Fees | B100: 2.1 | C100: 1.5 | D100: 1.5 | E100: 0.9 | F100: 1 | G100: 1.1 | I100: 1.4 | J100: 1 | K100: 1
...

Sheet Financial Analysis
A1: Solvency
A2: Ratios | B2: 2024 | C2: 2023 | D2: 2022 | E2: 2021 | F2: 2020 | G2: 2019 | H2: 2018 | I2: 2017 | J2: 2016 | K2: 2015
A3: Debt to Equity | B3: =('Balance Sheet'!B69 + 'Balance Sheet'!B75 +'Balance Sheet'!B79 + 'Balance Sheet'!B86)/('Balance Sheet'!B102) -> 1.1179173 | C3: =('Balance Sheet'!C69 + 'Balance Sheet'!C75 +'Balance Sheet'!C79 + 'Balance Sheet'!C86)/('Balance Sheet'!C102) -> 1.5263653 | D3: =('Balance Sheet'!D69 + 'Balance Sheet'!D75 +'Balance Sheet'!D79 + 'Balance Sheet'!D86)/('Balance Sheet'!D102) -> 1.5768293 | E3: =('Balance Sheet'!E69 + 'Balance Sheet'!E75 +'Balance Sheet'!E79 + 'Balance Sheet'!E86)/('Balance Sheet'!E102) -> 1.2252536 | F3: =('Balance Sheet'!F69 + 'Balance Sheet'!F75 +'Balance Sheet'!F79 + 'Balance Sheet'!F86)/('Balance Sheet'!F102) -> 1.2635712 | G3: =('Balance Sheet'!G69 + 'Balance Sheet'!G75 +'Balance Sheet'!G79 + 'Balance Sheet'!G86)/('Balance Sheet'!G102) -> 1.1364076 | H3: =('Balance Sheet'!H69 + 'Balance Sheet'!H75 +'Balance Sheet'!H79 + 'Balance Sheet'!H86)/('Balance Sheet'!H102) -> 0.87258434 | I3: =('Balance Sheet'!I69 + 'Balance Sheet'!I75 +'Balance Sheet'!I79 + 'Balance Sheet'!I86)/('Balance Sheet'!I102) -> 0.70672763 | ... K3: =('Balance Sheet'!K69 + 'Balance Sheet'!K75 +'Balance Sheet'!K79 + 'Balance Sheet'!K86)/('Balance Sheet'!K102) -> 0.58096591
A4: Debt to Asset | B4: =('Balance Sheet'!B70 + 'Balance Sheet'!B76 +'Balance Sheet'!B80 + 'Balance Sheet'!B87)/('Balance Sheet'!B60) -> 0.092034029 | C4: =('Balance Sheet'!C70 + 'Balance Sheet'!C76 +'Balance Sheet'!C80 + 'Balance Sheet'!C87)/('Balance Sheet'!C60) -> 0.11536393 | D4: =('Balance Sheet'!D70 + 'Balance Sheet'!D76 +'Balance Sheet'!D80 + 'Balance Sheet'!D87)/('Balance Sheet'!D60) -> 0.077158362 | E4: =('Balance Sheet'!E70 + 'Balance Sheet'!E76 +'Balance Sheet'!E80 + 'Balance Sheet'!E87)/('Balance Sheet'!E60) -> 0.09710129 | F4: =('Balance Sheet'!F70 + 'Balance Sheet'!F76 +'Balance Sheet'!F80 + 'Balance Sheet'!F87)/('Balance Sheet'!F60) -> 0.09897879 | G4: =('Balance Sheet'!G70 + 'Balance Sheet'!G76 +'Balance Sheet'!G80 + 'Balance Sheet'!G87)/('Balance Sheet'!G60) -> 0.10475414 | H4: =('Balance Sheet'!H70 + 'Balance Sheet'!H76 +'Balance Sheet'!H80 + 'Balance Sheet'!H87)/('Balance Sheet'!H60) -> 0.1317215 | I4: =('Balance Sheet'!I70 + 'Balance Sheet'!I76 +'Balance Sheet'!I80 + 'Balance Sheet'!I87)/('Balance Sheet'!I60) -> 0.13844593 | ... K4: =('Balance Sheet'!K70 + 'Balance Sheet'!K76 +'Balance Sheet'!K80 + 'Balance Sheet'!K87)/('Balance Sheet'!K60) -> 0.087706286
A5: Interest Coverage | B5: ='Income sheet'!B30/-'Cash Flow'!B12 -> 4.6993865 | C5: ='Income sheet'!C30/-'Cash Flow'!C12 -> 9.4144144 | D5: ='Income sheet'!D30/-'Cash Flow'!D12 -> 3.3932584 | E5: ='Income sheet'!E30/-'Cash Flow'!E12 -> 2.4864865 | F5: ='Income sheet'!F30/-'Cash Flow'!F12 -> 3.1212121 | G5: ='Income sheet'!G30/-'Cash Flow'!G12 -> 2.2090909 | H5: ='Income sheet'!H30/-'Cash Flow'!H12 -> 3.0520833 | I5: ='Income sheet'!I30/-'Cash Flow'!I12 -> 2.0987654 | ... K5: ='Income sheet'!K30/-'Cash Flow'!K12 -> 2.8875
A6: Cash Coverage | B6: =('Cash Flow'!B36+'Cash Flow'!B12+'Cash Flow'!B13) /-'Cash Flow'!B12 -> 5.7852761 | C6: =('Cash Flow'!C36+'Cash Flow'!C12+'Cash Flow'!C13) /-'Cash Flow'!C12 -> 4.4774775 | D6: =('Cash Flow'!D36+'Cash Flow'!D12+'Cash Flow'!D13) /-'Cash Flow'!D12 -> 9.0898876 | E6: =('Cash Flow'!E36+'Cash Flow'!E12-'Cash Flow'!E13) /-'Cash Flow'!E12 -> 6.7477477 | F6: =('Cash Flow'!F36+'Cash Flow'!F12+'Cash Flow'!F13) /-'Cash Flow'!F12 -> 3.3181818 | G6: =('Cash Flow'!G36+'Cash Flow'!G12+'Cash Flow'!G13) /-'Cash Flow'!G12 -> 5.5454545 | H6: =('Cash Flow'!H36+'Cash Flow'!H12+'Cash Flow'!H13) /-'Cash Flow'!H12 -> 3.6875 | I6: =('Cash Flow'!I36+'Cash Flow'!I12+'Cash Flow'!I13) /-'Cash Flow'!I12 -> 3.5925926 | J6: =('Cash Flow'!J36+'Cash Flow'!J12+'Cash Flow'!J13) /-'Cash Flow'!J12 -> 4.1369863 | K6: =('Cash Flow'!K36+'Cash Flow'!K12+'Cash Flow'!K13) /-'Cash Flow'!K12 -> 4.225
A7: Times Interest Earned | B7: =('Income sheet'!B87-'Cash Flow'!B12-'Cash Flow'!B13) /-'Cash Flow'!B12 -> 7.2453988 | C7: =('Income sheet'!C87-'Cash Flow'!C12-'Cash Flow'!C13) /-'Cash Flow'!C12 -> 12.081081 | D7: =('Income sheet'!D87-'Cash Flow'!D12-'Cash Flow'!D13) /-'Cash Flow'!D12 -> 1.8426966 | E7: =('Income sheet'!E87-'Cash Flow'!E12+'Cash Flow'!E13) /-'Cash Flow'!E12 -> 1.6036036 | F7: =('Income sheet'!F87-'Cash Flow'!F12-'Cash Flow'!F13) /-'Cash Flow'!F12 -> 1.8333333 | G7: =('Income sheet'!G87-'Cash Flow'!G12-'Cash Flow'!G13) /-'Cash Flow'!G12 -> 1.5727273 | H7: =('Income sheet'!H87-'Cash Flow'!H12-'Cash Flow'!H13) /-'Cash Flow'!H12 -> 4.6875 | I7: =('Income sheet'!I87-'Cash Flow'!I12-'Cash Flow'!I13) /-'Cash Flow'!I12 -> 1.2345679 | J7: =('Income sheet'!J87-'Cash Flow'!J12-'Cash Flow'!J13) /-'Cash Flow'!J12 -> 1 | K7: =('Income sheet'!K87-'Cash Flow'!K12-'Cash Flow'!K13) /-'Cash Flow'!K12 -> 1.0125
A10: Profitability
B11: 2024 | C11: 2023 | D11: 2022 | E11: 2021 | F11: 2020 | G11: 2019 | H11: 2018 | I11: 2017 | J11: 2016 | K11: 2015
A12: Gross Profit Margin | B12: 0.5409 | C12: 0.5202 | D12: 0.4982 | E12: 0.753 | F12: 0.7554 | G12: 0.9019 | H12: 0.7728 | I12: 0.7916 | J12: 0.654 | K12: 0.614
A13: Operating Profit Margin | B13: 0.2083 | C13: 0.2569 | D13: 0.1114 | E13: 0.1571 | F13: 0.23 | G13: 0.1419 | H13: 0.2303 | I13: 0.1625 | J13: 0.159 | K13: 0.1861
A14: Net Profit Margin | B14: 0.1906 | C14: 0.1812 | D14: 0.0472 | E14: 0.0495 | F14: 0.0726 | G14: 0.0695 | H14: 0.2028 | I14: 0.1281 | J14: 0.084 | K14: 0.0693
A15: Average Total Assets | B15: 12930 | C15: 12043 | D15: 10645.5 | E15: 9604 | F15: 8992 | G15: 8746.5 | H15: 8075.5 | I15: 7233.5 | J15: 6480 | K15: 5727.5
A16: Average Equity | B16: 4571 | C16: 3878.5 | D16: 2823 | E16: 2659.5 | F16: 2894 | G16: 3015 | H16: 3077 | I16: 3057.5 | J16: 2981.5 | K16: 2858.5
A17: ROA | B17: 0.0542 | C17: 0.0612 | D17: 0.012 | E17: 0.0091 | F17: 0.0145 | G17: 0.0136 | H17: 0.0319 | I17: 0.0185 | J17: 0.0157 | K17: 0.015
A18: ROE | B18: 0.1534 | C18: 0.19 | D18: 0.0453 | E18: 0.0327 | F18: 0.0449 | G18: 0.0395 | H18: 0.0838 | I18: 0.0438 | J18: 0.0342 | K18: 0.0301
A22: Operating
B23: 2024 | C23: 2023 | D23: 2022 | E23: 2021 | F23: 2020 | G23: 2019 | H23: 2018 | I23: 2017 | J23: 2016 | K23: 2015
A24: Accounts Receivable Turnover | B24: 5.92 | C24: 5.3 | D24: 4.37 | E24: 4.45 | F24: 5.12 | G24: 5.37 | H24: 4.1 | I24: 4.91 | J24: 6.01 | K24: 6.78
A25: Average Receivables Collection Days | B25: 61.79 | C25: 69.11 | D25: 83.85 | E25: 82.3 | F25: 71.42 | G25: 68.15 | H25: 89.24 | I25: 74.57 | J25: 60.9 | K25: 53.97
A26: Payables Turnover | B26: 13.24 | C26: 18.26 | D26: 22.91 | E26: 16.34 | F26: 14.99 | G26: 5.78 | H26: 5.44 | I26: 10.89 | J26: 4.96 | K26: 6.24
A27: Average Payables Payment Days | B27: 27.65 | C27: 20.04 | D27: 15.97 | E27: 22.4 | F27: 24.41 | G27: 63.34 | H27: 67.28 | I27: 33.61 | J27: 73.73 | K27: 58.64
A28: Inventory Turnover | B28: 8.42 | C28: 9.94 | D28: 9.29 | E28: 5.5 | F28: 5 | G28: 4.4 | H28: 4.79 | I28: 4.94 | J28: 5.74 | K28: 6.61
A29: Average Inventory Days | B29: 43.47 | C29: 36.81 | D29: 39.42 | E29: 66.59 | F29: 73.23 | G29: 83.14 | H29: 76.35 | I29: 74.07 | J29: 63.74 | K29: 55.36
A30: Average Net Trade Cycle Days | B30: 77.61 | C30: 85.88 | D30: 107.29 | E30: 126.49 | F30: 120.25 | G30: 87.95 | H30: 98.31 | I30: 115.03 | J30: 50.91 | K30: 50.7
B32: 2024 | C32: 2023 | D32: 2022 | E32: 2021 | F32: 2020 | G32: 2019 | H32: 2018 | I32: 2017 | J32: 2016 | K32: 2015
A33: Average Receivables Collection Days | B33: 61.79 | C33: 69.11 | D33: 83.85 | E33: 82.3 | F33: 71.42 | G33: 68.15 | H33: 89.24 | I33: 74.57 | J33: 60.9 | K33: 53.97
A34: Average Payables Payment Days | B34: 27.65 | C34: 20.04 | D34: 15.97 | E34: 22.4 | F34: 24.41 | G34: 63.34 | H34: 67.28 | I34: 33.61 | J34: 73.73 | K34: 58.64
A35: Average Net Trade Cycle Days | B35: 77.61 | C35: 85.88 | D35: 107.29 | E35: 126.49 | F35: 120.25 | G35: 87.95 | H35: 98.31 | I35: 115.03 | J35: 50.91 | K35: 50.7
A39: Growth Rate
B40: 2024 | C40: 2023 | D40: 2022 | E40: 2021 | F40: 2020 | G40: 2019 | H40: 2018 | I40: 2017 | J40: 2016 | K40: 2015
A41: Revenue from Business Activities - Total | B41: 3776 | C41: 4282 | D41: 2929 | E41: 1990 | F41: 1937 | G41: 1963 | H41: 1417 | I41: 1146 | J41: 1214 | K41: 1241
A42: Revenue Growth Rate | B42: =(B41-C41)/C41 -> -0.11816908 | C42: =(C41-D41)/D41 -> 0.4619324 | D42: =(D41-E41)/E41 -> 0.4718593 | E42: =(E41-F41)/F41 -> 0.0273619 | F42: =(F41-G41)/G41 -> -0.013245033 | G42: =(G41-H41)/H41 -> 0.3853211 | H42: =(H41-I41)/I41 -> 0.23647469 | I42: =(I41-J41)/J41 -> -0.05601318 | ... K42: =(K41-L41)/L41 -> #DIV/0!
A43: EPS - Diluted - excluding Extraordinary Items Applicable to Common - Total | B43: 5.15 | C43: 6.04 | D43: 0.84 | E43: 0.39 | F43: 0.77 | G43: 0.24 | H43: 2.16 | I43: 1.38 | J43: 0.91 | K43: 0.7
A44: Earnings Per Share Growth, EPS Growth | B44: =(B43-C43)/C43 -> -0.14735099 | C44: =(C43-D43)/D43 -> 6.1904762 | D44: =(D43-E43)/E43 -> 1.1538462 | E44: =(E43-F43)/F43 -> -0.49350649 | F44: =(F43-G43)/G43 -> 2.2083333 | G44: =(G43-H43)/H43 -> -0.88888889 | H44: =(H43-I43)/I43 -> 0.56521739 | I44: =(I43-J43)/J43 -> 0.51648352 | ... K44: =(K43-L43)/L43 -> #DIV/0!

Sheet CCA
A1: Identifier (GRID_REPORT.RIC) | B1: Company Name | C1: EBITDA Margin - % (FY0) | D1: Net Debt to EBITDA, TTM (FI0) | E1: Revenue 10 YR Hist Growth | F1: Return on Average Total Equity - %, TTM (FI0) | G1: Credit SmartRatios Net Debt / Equity, NTM | H1: EPS IBES Actual (Last Fisc YR) | I1: Forward Enterprise Value To EBITDA (Time Series Ratio) (FY1) | J1: Relative Valuation P/E, NTM | L1: Company | M1: EBITDA Margin - % (FY0) | N1: Forward Enterprise Value To EBITDA (Time Series Ratio) (FY1) | P1: Company | Q1: Relative Valuation P/E, NTM | R1: Return on Average Total Equity - %, TTM (FI0) | S1: Credit SmartRatios Net Debt / Equity, NTM | T1: Net Debt to EBITDA, TTM (FI0) | U1: EPS IBES Actual (Last Fisc YR)
A2: ACOx.TO | B2: Atco Ltd | C2: 0.407 | D2: 5.38 | E2: 22.48 | F2: 0.085 | G2: 2.58 | H2: 2.96 | I2: 8.66 | J2: 11.24 | L2: CPX.TO | M2: 0.348 | N2: 11.04 | P2: EMA.TO | Q2: 19.17 | R2: 0.074 | S2: 1.77 | T2: 6.12 | U2: 2.08
A3: NPI.TO | B3: Northland Power Inc (Ontario) | C3: 0.648 | D3: 4.92 | E3: 25.86 | F3: 0.004 | G3: 1.64 | H3: 0.72 | I3: 10.54 | J3: 15.55 | L3: EMA.TO | M3: 0.343 | N3: 11.79 | P3: CU.TO | Q3: 15.72 | R3: 0.074 | S3: 1.82 | T3: 6 | U3: 1.22
A4: CU.TO | B4: Canadian Utilities Ltd | C4: 0.453 | D4: 6 | E4: -26.04 | F4: 0.074 | G4: 1.82 | H4: 1.22 | I4: 9.73 | J4: 15.72 | L4: CU.TO | M4: 0.453 | N4: 9.73 | P4: FTS.TO | Q4: 19.77 | R4: 0.077 | S4: 1.45 | T4: 5.95 | U4: 2.31
A5: EMA.TO | B5: Emera Inc | C5: 0.343 | D5: 6.12 | E5: 16.34 | F5: 0.074 | G5: 1.77 | H5: 2.08 | I5: 11.79 | J5: 19.17 | L5: H.TO | M5: 0.339 | N5: 14.59 | P5: ACOx.TO | Q5: 11.24 | R5: 0.085 | S5: 2.58 | T5: 5.38 | U5: 2.96
A6: CPX.TO | B6: Capital Power Corp | C6: 0.348 | D6: 6.16 | E6: -2.27 | F6: 0.1 | G6: 1.25 | H6: 3.59 | I6: 11.04 | J6: 19.28 | L6: FTS.TO | M6: 0.454 | N6: 12.49 | P6: CPX.TO | Q6: 20.07 | R6: 0.1 | S6: 1.25 | T6: 6.16 | U6: 3.59
A7: FTS.TO | B7: Fortis Inc | C7: 0.454 | D7: 5.95 | E7: 15.28 | F7: 0.077 | G7: 1.45 | H7: 2.31 | I7: 12.49 | J7: 19.77 | L7: ACOx.TO | M7: 0.407 | N7: 8.66 | P7: TRP.TO | Q7: 20.1 | R7: 0.128 | S7: 2.25 | T7: 6.98 | U7: 2.63
A8: TRP.TO | B8: TC Energy Corp | C8: 0.604 | D8: 6.98 | E8: 3.88 | F8: 0.128 | G8: 2.25 | H8: 2.63 | I8: 13.71 | J8: 20.1 | L8: Average | M8: =SUM(M3:M7)/5 -> 0.3992 | N8: =SUM(N3:N7)/5 -> 11.452 | P8: Average | Q8: =(Q2+Q3+Q4+Q5+Q7)/5 -> 17.2 | R8: =SUM(R1:R5)/5 -> 0.062 | S8: =SUM(S1:S5)/5 -> 1.524 | T8: =SUM(T1:T5)/5 -> 4.69 | U8: =SUM(U1:U5)/5 -> 1.714
A9: H.TO | B9: Hydro One Ltd | C9: 0.339 | D9: 5.63 | E9: 21.07 | F9: 0.104 | G9: 1.58 | H9: 1.35 | I9: 14.59 | J9: 22.34
A10: BLX.TO | B10: Boralex Inc | C10: 0.619 | D10: 7.1 | E10: 33.73 | F10: 0.01 | G10: 2.03 | H10: 0.48 | I10: 10.73 | J10: 23.99
A11: TA.TO | B11: TransAlta Corp | C11: 0.239 | D11: 7.88 | E11: -20.22 | F11: -0.072 | G11: 6.25 | H11: 0.42 | I11: 9.33 | J11: 70.17
A12: ACOx.TO | B12: Atco Ltd | C12: 0.407 | D12: 5.38 | E12: 22.48 | F12: 0.085 | G12: 2.58 | H12: 2.96 | I12: 8.66 | J12: 11.18 | K12: 9.25
H15: Criterion 1 | I15: Description | J15: Examples
A16: Primary Screening Criteria Basaed on Business model and Strategic alignment. | B16: Included In Comps | H16: Geographic Focus | I16: Publicly traded North American IPPs, operating primarily in Canada and the U.S. | J16: NPI.TO, EMA.TO, FTS.TO
A17: North American Focused IPPs | B17: Capital Power Corp | H17: Business Model | I17: Hybrid structure — exposure to merchant wholesale markets (e.g., Alberta) and long-term Power Purchase Agreements (PPAs). | J17: CPX, NPI, EMA
A18: Hybrid Merchant/Contracted Model: | B18: Northland Power Inc (Ontario) | H18: Asset Mix | I18: Diversified generation portfolio: gas, wind, solar, storage. | J18: EMA, TA, FTS
A19: Diversified Fuel Mix: | B19: Boralex Inc | H19: Strategic Direction | I19: Active transition toward net-zero and decarbonization (renewables, CCS, hydrogen, BESS). | J19: CPX, EMA, ACOx.TO
A20: Secondary Screening Criteria provides broader market context and includes companies that share key financial characteristics or strategic goals, even if their business models aren't identical. | B20: TC Energy Corp
A21: U.S. IPPs with a Decarbonization Focus | B21: Canadian Utilities Ltd
A22: Renewable Energy "Yield cos" | B22: Fortis Inc
A23: Key Customers/Off-takers: | B23: Atco Ltd
B24: Emera Inc
B25: Hydro One Ltd
B26: AltaGas Ltd
A28: Market Multiples/Company | B28: EV/EBITDA FY1 | D28: EV/EBITDA Valuation | I28: P/E Valuation
A29: CPX.TO | B29: 11.04 | D29: CPX EV | E29: =B35*Caculation!C15 -> 15036.476 | I29: EPS | J29: ='Income sheet'!B114 -> 5.15
A30: EMA.TO | B30: 11.79 | D30: less：Net Debt | E30: ='Balance Sheet'!B75+'Balance Sheet'!B79-'Balance Sheet'!B3 -> 4111 | I30: Price | J30: =J29*B44 -> 88.58
A31: CU.TO | B31: 9.73 | D31: Less:Minority Interest | E31: ='Income sheet'!B69 -> 2
A32: H.TO | B32: 14.59 | D32: Equity Value | E32: =E29-E30-E31 -> 10923.476
A33: FTS.TO | B33: 12.49 | D33: Share outstanding | E33: =139 -> 139 | I33: =(E34+J30)/2 -> 83.583079
A34: ACOx.TO | B34: 8.66 | D34: Stock Price | E34: =E32/E33 -> 78.586158
A35: Average | B35: =SUM(B30:B34)/5 -> 11.452
A37: Market Multiples/Company | B37: P/E FY1
A38: CPX.TO | B38: 19.28
A39: EMA.TO | B39: 19.17
A40: FTS.TO | B40: 19.77
A41: CU.TO | B41: 15.72
A42: TRP.TO | B42: 20.1 | I42: Metric | J42: Peer Average Multiple | K42: Implied Value (CAD/share)
A43: ACOx.TO | B43: 11.24 | I43: EV/EBITDA | J43: =B35 -> 11.452 | K43: =E34 -> 78.586158
A44: Average | B44: =SUM(B39:B43)/5 -> 17.2 | I44: P/E | J44: =B44 -> 17.2 | K44: =J30 -> 88.58
A50: Market Multiples/Company | B50: EV/EBITDA FY1
A51: ACOx.TO | B51: 8.66
A52: CU.TO | B52: 9.73
A53: CPX.TO | B53: 11.04
A54: EMA.TO | B54: 11.79
A55: FTS.TO | B55: 12.49
A56: H.TO | B56: 14.59
A57: Average | B57: =SUM(B49:B53)/5 -> 5.886

Sheet Caculation
C1: 2024 | D1: 2023 | E1: 2022 | F1: 2021 | G1: 2020 | H1: 2019 | I1: 2018 | J1: 2017 | K1: 2016 | L1: 2015
B2: Revenue from bussiness | C2: ='Income sheet'!B3 -> 3677 | D2: ='Income sheet'!C3 -> 4068 | E2: ='Income sheet'!D3 -> 2712 | F2: ='Income sheet'!E3 -> 1757 | G2: ='Income sheet'!F3 -> 1791 | H2: ='Income sheet'!G3 -> 1713 | I2: ='Income sheet'!H3 -> 1272 | J2: ='Income sheet'!I3 -> 1046 | ... L2: ='Income sheet'!K3 -> 1241
B3: other revenue | C3: ='Income sheet'!B4 -> 99 | D3: ='Income sheet'!C4 -> 214 | E3: ='Income sheet'!D4 -> 217 | F3: ='Income sheet'!E4 -> 233 | G3: ='Income sheet'!F4 -> 146 | H3: ='Income sheet'!G4 -> 250 | I3: ='Income sheet'!H4 -> 145 | J3: ='Income sheet'!I4 -> 100 | ... L3: ='Income sheet'!K4 -> 0
B4: Total Revenue | C4: =C3+C2 -> 3776 | D4: =D3+D2 -> 4282 | E4: =E3+E2 -> 2929 | F4: =F3+F2 -> 1990 | G4: =G3+G2 -> 1937 | H4: =H3+H2 -> 1963 | I4: =I3+I2 -> 1417 | J4: =J3+J2 -> 1146 | ... L4: =L3+L2 -> 1241
B5: Energy purchases and fuel | C5: ='Income sheet'!B6 -> 1787 | D5: ='Income sheet'!C6 -> 2166 | E5: ='Income sheet'!D6 -> 1578 | F5: ='Income sheet'!E6 -> 667 | G5: ='Income sheet'!F6 -> 584 | H5: ='Income sheet'!G6 -> 418 | I5: ='Income sheet'!H6 -> 434 | J5: ='Income sheet'!I6 -> 318 | ... L5: ='Income sheet'!K6 -> 479
B6: Staff costs and employee benefits expense | C6: ='Income sheet'!B11 -> 254 | D6: ='Income sheet'!C11 -> 179 | E6: ='Income sheet'!D11 -> 184 | F6: ='Income sheet'!E11 -> 176 | G6: ='Income sheet'!F11 -> 171 | H6: ='Income sheet'!G11 -> 167 | I6: ='Income sheet'!H11 -> 145 | J6: ='Income sheet'!I11 -> 129 | ... L6: ='Income sheet'!K11 -> 120
B7: Other administrative expense | C7: ='Income sheet'!B25 -> 201 | D7: ='Income sheet'!C25 -> 153 | E7: ='Income sheet'!D25 -> 143 | F7: ='Income sheet'!E25 -> 114 | G7: ='Income sheet'!F25 -> 106 | H7: ='Income sheet'!G25 -> 116 | I7: ='Income sheet'!H25 -> 96 | J7: ='Income sheet'!I25 -> 89 | ... L7: ='Income sheet'!K25 -> 85
A8: Other raw materials and operating charges+Accretion on decommissioning provisions | B8: other operaring expense | C8: ='Income sheet'!B8-'Income sheet'!B48 -> 221 | D8: ='Income sheet'!C8-'Income sheet'!C48 -> 170 | E8: ='Income sheet'!D8-'Income sheet'!D48 -> 161 | F8: ='Income sheet'!E8-'Income sheet'!E48 -> 159 | G8: ='Income sheet'!F8-'Income sheet'!F48 -> 165 | H8: ='Income sheet'!G8-'Income sheet'!G48 -> 146 | I8: ='Income sheet'!H8-'Income sheet'!H48 -> 129 | J8: ='Income sheet'!I8-'Income sheet'!I48 -> 118 | ... L8: ='Income sheet'!K8-'Income sheet'!K48 -> 100
A9: Staff costs and employee benefits expense + Other administrative expense | B9: Selling，General& Administrative Expenses | C9: =C6+C7 -> 455 | D9: =D6+D7 -> 332 | E9: =E6+E7 -> 327 | F9: =F6+F7 -> 290 | G9: =G6+G7 -> 277 | H9: =H6+H7 -> 283 | I9: =I6+I7 -> 241 | J9: =J6+J7 -> 218 | ... L9: =L6+L7 -> 205
B10: Cost of Operating Revenue | C10: =C5 -> 1787 | D10: =D5 -> 2166 | E10: =E5 -> 1578 | F10: =F5 -> 667 | G10: =G5 -> 584 | H10: =H5 -> 418 | I10: =I5 -> 434 | J10: =J5 -> 318 | ... L10: =L5 -> 479
B11: Gross profit | C11: =C2-C5 -> 1890 | D11: =D2-D5 -> 1902 | E11: =E2-E5 -> 1134 | F11: =F2-F5 -> 1090 | G11: =G2-G5 -> 1207 | H11: =H2-H5 -> 1295 | I11: =I2-I5 -> 838 | J11: =J2-J5 -> 728 | ... L11: =L2-L5 -> 762
B12: Equity Earnings/(Loss) - before Taxes including Non-Recurring | C12: 76 | D12: 65 | E12: 32 | F12: 9 | G12: -3 | H12: 2 | I12: 19 | J12: 31 | K12: 25 | L12: 15
B13: Other Non-Operating Income/(Expense) - Total | C13: 14 | D13: 25 | E13: -14 | F13: -29 | G13: -26 | H13: -8 | I13: -7 | J13: -5 | K13: -6 | L13: -7
B14: EBIT | C14: =C4-C5-C9-C8-C16 -> 810 | D14: =D4-D5-D9-D8-D16 -> 1040 | E14: =E4-E5-E9-E8-E16 -> 310 | F14: =F4-F5-F9-F8-F16 -> 335 | G14: =G4-G5-G9-G8-G16 -> 433 | H14: =H4-H5-H9-H8-H16 -> 643 | I14: =I4-I5-I9-I8-I16 -> 278 | J14: =J4-J5-J9-J8-J16 -> 221 | ... L14: =L4-L5-L9-L8-L16 -> 242
B15: EBITDA | C15: =C14+ C16 -> 1313 | D15: =D14+ D16 -> 1614 | E15: =E14+ E16 -> 863 | F15: =F14+ F16 -> 874 | G15: =G14+ G16 -> 911 | H15: =H14+ H16 -> 1116 | I15: =I14+ I16 -> 613 | J15: =J14+ J16 -> 492 | ... L15: =L14+ L16 -> 457
B16: Depreciation and amortization | C16: ='Income sheet'!B20 -> 503 | D16: ='Income sheet'!C20 -> 574 | E16: ='Income sheet'!D20 -> 553 | F16: ='Income sheet'!E20 -> 539 | G16: ='Income sheet'!F20 -> 478 | H16: ='Income sheet'!G20 -> 473 | I16: ='Income sheet'!H20 -> 335 | J16: ='Income sheet'!I20 -> 271 | ... L16: ='Income sheet'!K20 -> 215
B17: Net income | C17: ='Income sheet'!B66 -> 701 | D17: ='Income sheet'!C66 -> 737 | E17: ='Income sheet'!D66 -> 128 | F17: ='Income sheet'!E66 -> 87 | G17: ='Income sheet'!F66 -> 130 | H17: ='Income sheet'!G66 -> 119 | I17: ='Income sheet'!H66 -> 258 | J17: ='Income sheet'!I66 -> 134 | ... L17: ='Income sheet'!K66 -> 86

Sheet DCF
A2: Revenue Forecast | B2: Historical | O2: Forecast | U2: Cost Forecast | V2: Historical | AH2: Forecast | AP2: Net Working Capital | BH2: CapEx
A3: Year | B3: 2014 | C3: 2015 | D3: 2016 | E3: 2017 | F3: 2018 | G3: 2019 | H3: 2020 | I3: 2021 | J3: 2022 | K3: 2023 | L3: 2024 | N3: Revenue growth by Segement (CAGR) | O3: 2025E | P3: 2026E | Q3: 2027E | R3: 2028E | S3: 2029E | U3: Year | V3: 2014 | W3: 2015 | X3: 2016 | Y3: 2017 | Z3: 2018 | AA3: 2019 | AB3: 2020 | AC3: 2021 | AD3: 2022 | AE3: 2023 | AF3: 2024 | AG3: Cost growth (CAGR) | AH3: 2025E | AI3: 2026E | AJ3: 2027E | AK3: 2028E | AL3: 2029E | AQ3: Historical | BB3: Forecast | BH3: CapEx | BI3: Historical | BT3: Forecast
A4: Revenue Segment | U4: Cost Items | AP4: Year | AQ4: 2015 | AR4: 2016 | AS4: 2017 | AT4: 2018 | AU4: 2019 | AV4: 2020 | AW4: 2021 | AX4: 2022 | AY4: 2023 | AZ4: 2024 | BA4: Average | BB4: 2025E | BC4: 2026E | BD4: 2027E | BE4: 2028E | BF4: 2029E | BH4: Year | BI4: 2015 | BJ4: 2016 | BK4: 2017 | BL4: 2018 | BM4: 2019 | BN4: 2020 | BO4: 2021 | BP4: 2022 | BQ4: 2023 | BR4: 2024 | BS4: Cost growth (CAGR) | BT4: 2025E | BU4: 2026E | BV4: 2027E | BW4: 2028E | BX4: 2029E
A5: Alberta commercial facilities and portfolio optimization | B5: 626 | C5: 782 | D5: 689 | E5: 657 | F5: 587 | G5: 725 | H5: 772 | I5: 1350 | J5: 2108 | K5: 2571 | L5: 1886 | N5: =POWER((L5/C5),0.1)-1 -> 0.092027295 | O5: =L5*(1+$N$5) -> 2059.5635 | P5: =O5*(1+$N$5) -> 2249.0995 | Q5: =P5*(1+$N$5) -> 2456.0781 | R5: =Q5*(1+$N$5) -> 2682.1043 | S5: =R5*(1+$N$5) -> 2928.9311 | U5: Energy purchases and fuel | V5: 511 | W5: ='Income sheet'!K6 -> 479 | X5: ='Income sheet'!J6 -> 420 | Y5: ='Income sheet'!I6 -> 318 | Z5: ='Income sheet'!H6 -> 434 | AA5: ='Income sheet'!G6 -> 418 | AB5: ='Income sheet'!F6 -> 584 | AC5: ='Income sheet'!E6 -> 667 | AD5: ='Income sheet'!D6 -> 1578 | AE5: ='Income sheet'!C6 -> 2166 | AF5: ='Income sheet'!B6 -> 1787 | AG5: =POWER(AF5/W5,0.1)-1 -> 0.1407196 | AH5: =AF5*(1+$AG$5) -> 2038.4659 | AI5: =AH5*(1+$AG$5) -> 2325.318 | AJ5: =AI5*(1+$AG$5) -> 2652.5359 | AK5: =AJ5*(1+$AG$5) -> 3025.7996 | AL5: =AK5*(1+$AG$5) -> 3451.589 | AP5: Inventory | AQ5: ='Balance Sheet'!K17 -'Balance Sheet'!K20 -> 99 | AR5: ='Balance Sheet'!J17 -'Balance Sheet'!J20 -> 89 | AS5: ='Balance Sheet'!I17 -'Balance Sheet'!I20 -> 99 | AT5: ='Balance Sheet'!H17 -'Balance Sheet'!H20 -> 200 | AU5: ='Balance Sheet'!G17 -'Balance Sheet'!G20 -> 136 | AV5: ='Balance Sheet'!F17 -'Balance Sheet'!F20 -> 170 | AW5: ='Balance Sheet'!E17 -'Balance Sheet'!E20 -> 166 | AX5: ='Balance Sheet'!D17 -'Balance Sheet'!D20 -> 149 | AY5: ='Balance Sheet'!C17 -'Balance Sheet'!C20 -> 129 | AZ5: ='Balance Sheet'!B17 -'Balance Sheet'!B20 -> 121 | BB5: =AH5 * $BA$6 -> 464.31305 | BC5: =AI5 * $BA$6 -> 529.651 | BD5: =AJ5 * $BA$6 -> 604.18328 | BE5: =AK5 * $BA$6 -> 689.20371 | BF5: =AL5 * $BA$6 -> 786.18818 | BH5: Purchase of Property, plant and equipment and other assets | BI5: =-'Cash Flow'!K37 -> 140 | BJ5: =-'Cash Flow'!J37 -> 313 | BK5: =-'Cash Flow'!I37 -> 218 | BL5: =-'Cash Flow'!H37 -> 355 | BM5: =-'Cash Flow'!G37 -> 635 | BN5: =-'Cash Flow'!F37 -> 306 | BO5: =-'Cash Flow'!E37 -> 622 | BP5: =-'Cash Flow'!D37 -> 682 | BQ5: =-'Cash Flow'!C37 -> 723 | BR5: =-'Cash Flow'!B37 -> 1070 | BS5: =POWER(BR5/BI5,0.1)-1 -> 0.22553459 | BT5: =BR5*(1+$BS$5) -> 1311.322 | BU5: =BT5*(1+$BS$5) -> 1607.0705 | BV5: =BU5*(1+$BS$5) -> 1969.5205 | BW5: =BV5*(1+$BS$5) -> 2413.7155 | BX5: =BW5*(1+$BS$5) -> 2958.0918
A6: Alberta contracted plants | B6: 266 | C6: 265 | D6: 252 | E6: 241 | F6: 268 | G6: 261 | H6: 301 | I6: N/A | J6: N/A | K6: N/A | L6: N/A | U6: Staff costs and employee benefits expense | V6: 123 | W6: 120 | X6: 124 | Y6: 129 | Z6: 145 | AA6: 167 | AB6: 171 | AC6: 176 | AD6: 184 | AE6: 179 | AF6: 254 | AG6: =POWER(AF6/W6,0.1)-1 -> 0.077867177 | AH6: =AF6*(1+AG6) -> 273.77826 | AI6: =AH6*(1+AG6) -> 295.0966 | AJ6: =AI6*(1+AG6) -> 318.07494 | AK6: =AJ6*(1+AG6) -> 342.84254 | AL6: =AK6*(1+AG6) -> 369.53872 | AP6: INV% | AQ6: =AQ5 / W5 * 100 -> 20.668058 | AR6: =AR5 / X5 * 100 -> 21.190476 | AS6: =AS5 / Y5 * 100 -> 31.132075 | AT6: =AT5 / Z5 * 100 -> 46.082949 | AU6: =AU5 / AA5 * 100 -> 32.535885 | AV6: =AV5 / AB5 * 100 -> 29.109589 | AW6: =AW5 / AC5 * 100 -> 24.887556 | AX6: =AX5 / AD5 * 100 -> 9.4423321 | ... AZ6: =AZ5 / AF5 * 100 -> 6.7711248 | BA6: =AVERAGE(AQ6:AZ6)/100 -> 0.22777573 | BB6: =AH6 * $BA$6 -> 62.360042 | BQ6: =(BR5-BQ5)/BR5 -> 0.32429907 | BT6: =BR5*0.6 -> 642 | BU6: =BT6*(1+0.08) -> 693.36 | BV6: =BU6*(1+0.08) -> 748.8288 | BW6: =BV6*(1+0.08) -> 808.7351 | BX6: =BW6*(1+0.15) -> 930.04537
A7: Western Canada contracted facilities | B7: N/A | C7: N/A | D7: N/A | E7: N/A | F7: N/A | G7: N/A | H7: N/A | I7: 133 | J7: 150 | K7: 152 | L7: 143 | N7: =POWER((L7/I7),0.1)-1 -> 0.0072758918 | O7: =L7*(1+$N$7) -> 144.04045 | P7: =O7*(1+$N$7) -> 145.08848 | Q7: =P7*(1+$N$7) -> 146.14412 | R7: =Q7*(1+$N$7) -> 147.20745 | S7: =R7*(1+$N$7) -> 148.27852 | U7: Other administrative expense | V7: 80 | W7: 85 | X7: 86 | Y7: 89 | Z7: 96 | AA7: 116 | AB7: 106 | AC7: 114 | AD7: 143 | AE7: 153 | AF7: 201 | AG7: =POWER(AF7/W7,0.1)-1 -> 0.089877566 | AH7: =AF7*(1+AG7) -> 219.06539 | AI7: =AH7*(1+AG7) -> 238.75445 | AJ7: =AI7*(1+AG7) -> 260.21312 | AK7: =AJ7*(1+AG7) -> 283.60045 | AL7: =AK7*(1+AG7) -> 309.08976 | AP7: Receivables | AQ7: ='Balance Sheet'!K8 -('Balance Sheet'!K13 + 'Balance Sheet'!K14 + 'Balance Sheet'!K15 + 'Balance Sheet'!K16) -> 190 | AR7: ='Balance Sheet'!J8 -('Balance Sheet'!J13 + 'Balance Sheet'!J14 + 'Balance Sheet'!J15 + 'Balance Sheet'!J16) -> 139 | AS7: ='Balance Sheet'!I8 -('Balance Sheet'!I13 + 'Balance Sheet'!I14 + 'Balance Sheet'!I15 + 'Balance Sheet'!I16) -> 178 | AT7: ='Balance Sheet'!H8 -('Balance Sheet'!H13 + 'Balance Sheet'!H14 + 'Balance Sheet'!H15 + 'Balance Sheet'!H16) -> 438 | AU7: ='Balance Sheet'!G8 -('Balance Sheet'!G13 + 'Balance Sheet'!G14 + 'Balance Sheet'!G15 + 'Balance Sheet'!G16) -> 235 | AV7: ='Balance Sheet'!F8 -('Balance Sheet'!F13 + 'Balance Sheet'!F14 + 'Balance Sheet'!F15 + 'Balance Sheet'!F16) -> 380 | AW7: ='Balance Sheet'!E8 -('Balance Sheet'!E13 + 'Balance Sheet'!E14 + 'Balance Sheet'!E15 + 'Balance Sheet'!E16) -> 370 | AX7: ='Balance Sheet'!D8 -('Balance Sheet'!D13 + 'Balance Sheet'!D14 + 'Balance Sheet'!D15 + 'Balance Sheet'!D16) -> 835 | AY7: ='Balance Sheet'!C8 -('Balance Sheet'!C13 + 'Balance Sheet'!C14 + 'Balance Sheet'!C15 + 'Balance Sheet'!C16) -> 562 | AZ7: ='Balance Sheet'!B8 -('Balance Sheet'!B13 + 'Balance Sheet'!B14 + 'Balance Sheet'!B15 + 'Balance Sheet'!B16) -> 401 | BB7: =O13 * $BA$8 -> 700.91133 | BC7: =P13 * $BA$8 -> 771.02679 | BD7: =Q13 * $BA$8 -> 864.03122 | BE7: =R13 * $BA$8 -> 978.45925 | BF7: =S13 * $BA$8 -> 1115.551 | BP7: =(BP5-BO5)/BO5 -> 0.096463023 | BQ7: =(BQ5-BP5)/BP5 -> 0.060117302 | BR7: =(BQ7+BP7)/2 -> 0.078290162
A8: Ontario contracted facilities | B8: 119 | C8: 124 | D8: 115 | E8: 146 | F8: 180 | G8: 293 | H8: 391 | I8: 316 | J8: 437 | K8: 374 | L8: 378 | N8: =POWER((L8/C8),0.1)-1 -> 0.11791044 | O8: =L8*(1+$N$8) -> 422.57015 | P8: =O8*(1+$N$8) -> 472.39558 | Q8: =P8*(1+$N$8) -> 528.09595 | R8: =Q8*(1+$N$8) -> 590.36397 | S8: =R8*(1+$N$8) -> 659.97405 | U8: other operaring expense | V8: 96 | W8: 100 | X8: 105 | Y8: 118 | Z8: 129 | AA8: 146 | AB8: 165 | AC8: 159 | AD8: 161 | AE8: 170 | AF8: 221 | AG8: =POWER(AF8/W8,0.1)-1 -> 0.082528222 | AH8: =AF8*(1+AG8) -> 239.23874 | AI8: =AH8*(1+AG8) -> 258.98268 | AJ8: =AI8*(1+AG8) -> 280.35607 | AK8: =AJ8*(1+AG8) -> 303.49335 | AL8: =AK8*(1+AG8) -> 328.54012 | AP8: AR% | AQ8: =AQ7/DCF!C13 * 100 -> 15.310234 | AR8: =AR7/DCF!D13 * 100 -> 11.449753 | AS8: =AS7/DCF!E13 * 100 -> 15.532286 | AT8: =AT7/DCF!F13 * 100 -> 30.910374 | AU8: =AU7/DCF!G13 * 100 -> 11.971472 | AV8: =AV7/DCF!H13 * 100 -> 19.617966 | AW8: =AW7/DCF!I13 * 100 -> 18.592965 | AX8: =AX7/DCF!J13 * 100 -> 28.508023 | ... AZ8: =AZ7/DCF!L13 * 100 -> 10.619703 | BA8: =AVERAGE(AQ8:AZ8)/100 -> 0.17563748
A9: U.S. contracted facilities | B9: 83 | C9: 114 | D9: 129 | E9: 201 | F9: 304 | G9: 449 | H9: 463 | I9: 402 | J9: 534 | K9: 491 | L9: 903 | N9: =POWER((L9/C9),0.1)-1 -> 0.22992404 | O9: =L9*(1+$N$9) -> 1110.6214 | P9: =O9*(1+$N$9) -> 1365.98 | Q9: =P9*(1+$N$9) -> 1680.0516 | R9: =Q9*(1+$N$9) -> 2066.3358 | S9: =R9*(1+$N$9) -> 2541.4361 | U9: Total Expenses | V9: =SUM(V5:V8) -> 810 | W9: =SUM(W5:W8) -> 784 | X9: =SUM(X5:X8) -> 735 | Y9: =SUM(Y5:Y8) -> 654 | Z9: =SUM(Z5:Z8) -> 804 | AA9: =SUM(AA5:AA8) -> 847 | AB9: =SUM(AB5:AB8) -> 1026 | AC9: =SUM(AC5:AC8) -> 1116 | ... AF9: =SUM(AF5:AF8) -> 2463 | AG9: =POWER(AF9/W9,0.1)-1 -> 0.12128196 | AH9: =SUM(AH5:AH8) -> 2770.5483 | AI9: =SUM(AI5:AI8) -> 3118.1518 | AJ9: =SUM(AJ5:AJ8) -> 3511.18 | AK9: =SUM(AK5:AK8) -> 3955.736 | AL9: =SUM(AL5:AL8) -> 4458.7576 | AP9: Payables | AQ9: ='Balance Sheet'!K61-('Balance Sheet'!K64+'Balance Sheet'!K66) -> 181 | AR9: ='Balance Sheet'!J61-('Balance Sheet'!J64+'Balance Sheet'!J66) -> 167 | AS9: ='Balance Sheet'!I61-('Balance Sheet'!I64+'Balance Sheet'!I66) -> 153 | AT9: ='Balance Sheet'!H61-('Balance Sheet'!H64+'Balance Sheet'!H66) -> 244 | AU9: ='Balance Sheet'!G61-('Balance Sheet'!G64+'Balance Sheet'!G66) -> 232 | AV9: ='Balance Sheet'!F61-('Balance Sheet'!F64+'Balance Sheet'!F66) -> 393 | AW9: ='Balance Sheet'!E61-('Balance Sheet'!E64+'Balance Sheet'!E66) -> 536 | AX9: ='Balance Sheet'!D61-('Balance Sheet'!D64+'Balance Sheet'!D66) -> 1147 | AY9: ='Balance Sheet'!C61-('Balance Sheet'!C64+'Balance Sheet'!C66) -> 604 | AZ9: ='Balance Sheet'!B61-('Balance Sheet'!B64+'Balance Sheet'!B66) -> 590 | BB9: =AH5 * $BA$10 -> 1057.2071 | BC9: =AI5 * $BA$10 -> 1205.9768 | BD9: =AJ5 * $BA$10 -> 1375.6814 | BE9: =AK5 * $BA$10 -> 1569.2668 | BF9: =AL5 * $BA$10 -> 1790.0934
A10: U.S. commercial facilities | B10: N/A | C10: N/A | D10: N/A | E10: N/A | F10: N/A | G10: N/A | H10: N/A | I10: N/A | J10: N/A | K10: N/A | L10: N/A | U10: Growth Rate | V10: 2014 | W10: 2015 | X10: 2016 | Y10: 2017 | Z10: 2018 | AA10: 2019 | AB10: 2020 | AC10: 2021 | AD10: 2022 | AE10: 2023 | AF10: 2024 | AG10: Average | AP10: AP% | AQ10: =AQ9/W5 * 100 -> 37.787056 | AR10: =AR9/X5 * 100 -> 39.761905 | AS10: =AS9/Y5 * 100 -> 48.113208 | AT10: =AT9/Z5 * 100 -> 56.221198 | AU10: =AU9/AA5 * 100 -> 55.502392 | AV10: =AV9/AB5 * 100 -> 67.294521 | AW10: =AW9/AC5 * 100 -> 80.35982 | AX10: =AX9/AD5 * 100 -> 72.686946 | ... AZ10: =AZ9/AF5 * 100 -> 33.016228 | BA10: =AVERAGE(AQ10:AZ10)/100 -> 0.51862878 | BB10: =AH6 * $BA$10 -> 141.98929 | BH10: Based on Revenue | BN10: =BN5/H13 -> 0.15797625 | BO10: =BO5/I13 -> 0.31256281 | BP10: =BP5/J13 -> 0.23284397 | BQ10: =BQ5/K13 -> 0.16884633 | BR10: =BR5/L13 -> 0.28336864 | BS10: =AVERAGE(BN10:BR10) -> 0.2311196 | BT10: =$BS$10*O13 -> 922.32218 | BU10: =$BS$10*P13 -> 1014.5864 | BV10: =$BS$10*Q13 -> 1136.97 | BW10: =$BS$10*R13 -> 1287.5447 | BX10: =$BS$10*S13 -> 1467.9423
A11: Unrealized changes in fair value of commodity derivatives and emission credits | B11: 121 | C11: -52 | D11: 13 | E11: -162 | F11: 20 | G11: 47 | H11: -45 | I11: -337 | J11: -431 | K11: 564 | L11: 447 | O11: =L11+0.5*(O14-L11) -> 253.875 | P11: =O11+0.5*(O14-O11) -> 157.3125 | Q11: =P11+0.5*(O14-P11) -> 109.03125 | R11: =Q11+0.5*(O14-Q11) -> 84.890625 | S11: =R11+0.5*(O14-R11) -> 72.820312 | U11: Energy purchases and fuel | W11: =(W5-V5)/V5 -> -0.062622309 | X11: =(X5-W5)/W5 -> -0.12317328 | Y11: =(Y5-X5)/X5 -> -0.24285714 | Z11: =(Z5-Y5)/Y5 -> 0.36477987 | AA11: =(AA5-Z5)/Z5 -> -0.036866359 | AB11: =(AB5-AA5)/AA5 -> 0.39712919 | AC11: =(AC5-AB5)/AB5 -> 0.14212329 | AD11: =(AD5-AC5)/AC5 -> 1.3658171 | ... AF11: =(AF5-AE5)/AE5 -> -0.17497692 | AG11: =SUM(W11:AF11)/10 -> 0.2001977 | BA11: NWC | BB11: =BB5 + BB7 -BB9 -> 108.01729 | BC11: =BC5 + BC7 -BC9 -> 94.70094 | BD11: =BD5 + BD7 -BD9 -> 92.533067 | BE11: =BE5 + BE7 -BE9 -> 98.396187 | BF11: =BF5 + BF7 -BF9 -> 111.64578
A12: Corporate | B12: 13 | C12: 8 | D12: 16 | E12: 63 | F12: 58 | G12: 188 | H12: 55 | I12: 126 | J12: 131 | K12: 130 | L12: 19 | U12: Total Expenses | W12: =(W9-V9)/V9 -> -0.032098765 | X12: =(X9-W9)/W9 -> -0.0625 | Y12: =(Y9-X9)/X9 -> -0.11020408 | Z12: =(Z9-Y9)/Y9 -> 0.2293578 | AA12: =(AA9-Z9)/Z9 -> 0.053482587 | AB12: =(AB9-AA9)/AA9 -> 0.21133412 | AC12: =(AC9-AB9)/AB9 -> 0.087719298 | AD12: =(AD9-AC9)/AC9 -> 0.85125448 | ... AF12: =(AF9-AE9)/AE9 -> -0.076836582 | AG12: =SUM(W12:AF12)/10 -> 0.14428932
A13: Total Revenue | B13: =SUM(B5:B12) -> 1228 | C13: =SUM(C5:C12) -> 1241 | D13: =SUM(D5:D12) -> 1214 | E13: =SUM(E5:E12) -> 1146 | F13: =SUM(F5:F12) -> 1417 | G13: =SUM(G5:G12) -> 1963 | H13: =SUM(H5:H12) -> 1937 | I13: =SUM(I5:I12) -> 1990 | ... L13: =SUM(L5:L12) -> 3776 | N13: =POWER((L13/C13),0.1)-1 -> 0.11770198 | O13: =SUM(O5:O11) -> 3990.6705 | P13: =SUM(P5:P11) -> 4389.8761 | Q13: =SUM(Q5:Q11) -> 4919.401 | R13: =SUM(R5:R11) -> 5570.9022 | S13: =SUM(S5:S11) -> 6351.4401 | U13: Depreciation and amortization | V13: Historical | AH13: Forecast
A14: Revenue Forecast | B14: As % of Revenue | O14: =AVERAGE(I11:L11) -> 60.75 | U14: Year | V14: 2014 | W14: 2015 | X14: 2016 | Y14: 2017 | Z14: 2018 | AA14: 2019 | AB14: 2020 | AC14: 2021 | AD14: 2022 | AE14: 2023 | AF14: 2024 | AG14: Cost growth (CAGR) | AH14: 2025E | AI14: 2026E | AJ14: 2027E | AK14: 2028E | AL14: 2029E
A15: Percentage of Total Revenue | B15: 2014 | C15: 2015 | D15: 2016 | E15: 2017 | F15: 2018 | G15: 2019 | H15: 2020 | I15: 2021 | J15: 2022 | K15: 2023 | L15: 2024 | N15: Average | O15: =(P13-O13)/O13 -> 0.10003471 | P15: =(Q13-P13)/P13 -> 0.12062412 | Q15: =(R13-Q13)/Q13 -> 0.13243507 | R15: =(S13-R13)/R13 -> 0.14010979 | S15: =(T13-S13)/S13 -> -1 | U15: Depreciation of property plant and equipment | W15: 186 | X15: 198 | Y15: 249 | Z15: 309 | AA15: 356 | AB15: 383 | AC15: 445 | AD15: 462 | AE15: 489 | AF15: 400 | AG15: =POWER(AF15/W15,0.1)-1 -> 0.079579688
A16: Alberta commercial facilities and portfolio optimization | B16: =B5/B$13 -> 0.50977199 | C16: =C5/C$13 -> 0.63013699 | D16: =D5/D$13 -> 0.5675453 | E16: =E5/E$13 -> 0.57329843 | F16: =F5/F$13 -> 0.41425547 | G16: =G5/G$13 -> 0.36933265 | H16: =H5/H$13 -> 0.39855447 | I16: =I5/I$13 -> 0.67839196 | ... L16: =L5/L$13 -> 0.49947034 | N16: =SUM(B16:L16)/10 -> 0.59608775 | U16: Amortisation of Contract rights and Other rights | W16: 6 | X16: 7 | Y16: 10 | Z16: 19 | AA16: 101 | AB16: 7 | AC16: 4 | AD16: 9 | AE16: 4 | AF16: 4 | AG16: =POWER(AF16/W16,0.1)-1 -> -0.039735499
A17: Alberta contracted plants | B17: =B6/B$13 -> 0.21661238 | C17: =C6/C$13 -> 0.21353747 | D17: =D6/D$13 -> 0.20757825 | E17: =E6/E$13 -> 0.21029668 | F17: =F6/F$13 -> 0.18913197 | G17: =G6/G$13 -> 0.13295976 | H17: =H6/H$13 -> 0.15539494 | I17: N/A | J17: N/A | K17: N/A | L17: N/A | O17: =POWER(S13/O13,0.2)-1 -> 0.097400788 | U17: Amortisation of Computer Software | W17: 6 | X17: 5 | Y17: 6 | Z17: 5 | AA17: 4 | AB17: 5 | AC17: 5 | AD17: 6 | AE17: 4 | AF17: 5 | AG17: =POWER(AF17/W17,0.1)-1 -> -0.018066955
A18: Western Canada contracted facilities | B18: N/A | C18: N/A | D18: N/A | E18: N/A | F18: N/A | G18: N/A | H18: N/A | I18: =I7/I$13 -> 0.066834171 | J18: =J7/J$13 -> 0.051212018 | K18: =K7/K$13 -> 0.035497431 | L18: =L7/L$13 -> 0.037870763 | N18: =SUM(I18:L18)/4 -> 0.047853596 | U18: Amortization of intangible assets - Balancing value | AB18: 69 | AC18: 71 | AD18: 67 | AE18: 66 | AF18: 84
A19: Ontario contracted facilities | B19: =B8/B$13 -> 0.096905537 | C19: =C8/C$13 -> 0.09991942 | D19: =D8/D$13 -> 0.094728171 | E19: =E8/E$13 -> 0.12739965 | F19: =F8/F$13 -> 0.12702893 | G19: =G8/G$13 -> 0.14926133 | H19: =H8/H$13 -> 0.20185854 | I19: =I8/I$13 -> 0.15879397 | ... L19: =L8/L$13 -> 0.10010593 | N19: =SUM(B19:L19)/10 -> 0.13925415 | U19: Amortization of intangible assets | W19: 12 | X19: 4 | Y19: 5 | Z19: 24 | AA19: 105 | AB19: 81 | AC19: 80 | AD19: 82 | AE19: 74 | AF19: 93 | AG19: =POWER(AF19/W19,0.1)-1 -> 0.22724189 | AQ19: WACC
A20: U.S. contracted facilities | B20: =B9/B$13 -> 0.067589577 | C20: =C9/C$13 -> 0.091861402 | D20: =D9/D$13 -> 0.1062603 | E20: =E9/E$13 -> 0.17539267 | F20: =F9/F$13 -> 0.21453776 | G20: =G9/G$13 -> 0.22873153 | H20: =H9/H$13 -> 0.23902943 | I20: =I9/I$13 -> 0.20201005 | ... L20: =L9/L$13 -> 0.23914195 | N20: =SUM(B20:L20)/10 -> 0.18615355 | U20: Depreciation of Financial Lease Right-of-Use Assets | AA20: 8 | AB20: 9 | AC20: 9 | AD20: 9 | AE20: 10 | AF20: 10 | AR20: Total Value of Equity | AU20: Total Value of Preference Shares | AX20: Total Value of Debt
A21: U.S. commercial facilities | B21: N/A | C21: N/A | D21: N/A | E21: N/A | F21: N/A | G21: N/A | H21: N/A | I21: N/A | J21: N/A | K21: N/A | L21: N/A | U21: Depreciation and amortization | V21: 160 | W21: 215 | X21: 216 | Y21: 271 | Z21: 335 | AA21: 473 | AB21: 478 | AC21: 539 | AD21: 553 | AE21: 574 | AF21: 503 | AG21: =POWER(AF21/W21,0.1)-1 -> 0.088711856 | AH21: =AF21*(1+AG21) -> 547.62206 | AI21: =AH21*(1+AG21) -> 596.20263 | AJ21: =AI21*(1+AG21) -> 649.09288 | AK21: =AJ21*(1+AG21) -> 706.67511 | AL21: =AK21*(1+AG21) -> 769.36557 | AQ21: Share Price | AR21: 71.25 | AU21: 23.13 | AX21: 7100
A22: Unrealized changes in fair value of commodity derivatives and emission credits | B22: =B11/B$13 -> 0.098534202 | C22: =C11/C$13 -> -0.041901692 | D22: =D11/D$13 -> 0.010708402 | E22: =E11/E$13 -> -0.14136126 | F22: =F11/F$13 -> 0.014114326 | G22: =G11/G$13 -> 0.023942944 | H22: =H11/H$13 -> -0.023231802 | I22: =I11/I$13 -> -0.16934673 | ... L22: =L11/L$13 -> 0.11837924 | N22: =SUM(B22:L22)/10 -> -0.012559742 | U22: Growth Rate | V22: 2014 | W22: 2015 | X22: 2016 | Y22: 2017 | Z22: 2018 | AA22: 2019 | AB22: 2020 | AC22: 2021 | AD22: 2022 | AE22: 2023 | AF22: 2024 | AG22: Average | AQ22: Outstanding Shares | AR22: 155.47 | AU22: 5
A23: Corporate | B23: =B12/B$13 -> 0.010586319 | C23: =C12/C$13 -> 0.0064464142 | D23: =D12/D$13 -> 0.013179572 | E23: =E12/E$13 -> 0.054973822 | F23: =F12/F$13 -> 0.040931546 | G23: =G12/G$13 -> 0.095771778 | H23: =H12/H$13 -> 0.028394424 | I23: =I12/I$13 -> 0.063316583 | ... L23: =L12/L$13 -> 0.0050317797 | N23: =SUM(B23:L23)/10 -> 0.039371704 | U23: Energy purchases and fuel | W23: =(W21-V21)/V21 -> 0.34375 | X23: =(X21-W21)/W21 -> 0.0046511628 | Y23: =(Y21-X21)/X21 -> 0.25462963 | Z23: =(Z21-Y21)/Y21 -> 0.23616236 | AA23: =(AA21-Z21)/Z21 -> 0.4119403 | AB23: =(AB21-AA21)/AA21 -> 0.010570825 | AC23: =(AC21-AB21)/AB21 -> 0.12761506 | AD23: =(AD21-AC21)/AC21 -> 0.025974026 | ... AF23: =(AF21-AE21)/AE21 -> -0.12369338 | AG23: =SUM(W23:AF23)/10 -> 0.13295747 | AQ23: TVE | AR23: =AR21*AR22 -> 11077.237 | AT23: TVP | AU23: =AU21*AU22 -> 115.65 | AW23: TVD | AX23: =AX21 -> 7100 | BD23: Equity | BE23: =AR23/$AS$24 -> 0.60940159 | BF23: =AR23/$AS$24 -> 0.60940159
A24: Total Revenue | B24: =SUM(B16:B23) -> 1 | C24: =SUM(C16:C23) -> 1 | D24: =SUM(D16:D23) -> 1 | E24: =SUM(E16:E23) -> 1 | F24: =SUM(F16:F23) -> 1 | G24: =SUM(G16:G23) -> 1 | H24: =SUM(H16:H23) -> 1 | I24: =SUM(I16:I23) -> 1 | ... L24: =SUM(L16:L23) -> 1 | AQ24: Total Market Value | AS24: =AR23+AX23 -> 18177.237 | BD24: Preference Shares | BE24: =AU23/$AS$24 -> 0.0063623529 | BF24: =BE24/$AS$24 -> 3.5001759e-07
A25: Revenue Forecast | B25: Revenue growth by Segement | AQ25: Cost of Equity | AS25: =7.58/100 -> 0.0758 | BD25: Debt | BE25: =AX23/$AS$24 -> 0.39059841 | BF25: =BE25/$AS$24 -> 2.1488326e-05
A26: Growth Rate | B26: 2014 | C26: 2015 | D26: 2016 | E26: 2017 | F26: 2018 | G26: 2019 | H26: 2020 | I26: 2021 | J26: 2022 | K26: 2023 | L26: 2024 | N26: Average | V26: Forecast | AQ26: Cost of Debt | AS26: =AS27/AS28*(1-AS29) -> 0.029652666 | BE26: =SUM(BE23:BE25) -> 1.0063624
A27: Alberta commercial facilities and portfolio optimization | C27: =(C5-B5)/B5 -> 0.24920128 | D27: =(D5-C5)/C5 -> -0.11892583 | E27: =(E5-D5)/D5 -> -0.046444122 | F27: =(F5-E5)/E5 -> -0.1065449 | G27: =(G5-F5)/F5 -> 0.2350937 | H27: =(H5-G5)/G5 -> 0.064827586 | I27: =(I5-H5)/H5 -> 0.74870466 | J27: =(J5-I5)/I5 -> 0.56148148 | ... L27: =(L5-K5)/K5 -> -0.26643329 | N27: =SUM(C27:L27)/10 -> 0.15406 | V27: 2025E | W27: 2026E | X27: 2027E | Y27: 2028E | Z27: 2029E | AQ27: Interest Expenses | AS27: =-'Income sheet'!B39 -> 270
A28: Alberta contracted plants | C28: =(C6-B6)/B6 -> -0.0037593985 | D28: =(D6-C6)/C6 -> -0.049056604 | E28: =(E6-D6)/D6 -> -0.043650794 | F28: =(F6-E6)/E6 -> 0.1120332 | G28: =(G6-F6)/F6 -> -0.026119403 | H28: =(H6-G6)/G6 -> 0.1532567 | I28: N/A | J28: N/A | K28: N/A | L28: N/A | U28: Total Revenue | V28: =O13 -> 3990.6705 | W28: =P13 -> 4389.8761 | X28: =Q13 -> 4919.401 | Y28: =R13 -> 5570.9022 | Z28: =S13 -> 6351.4401 | AQ28: Value of Debt | AS28: =AX23 -> 7100
A29: Western Canada contracted facilities | C29: N/A | D29: N/A | E29: N/A | F29: N/A | G29: N/A | H29: N/A | I29: N/A | J29: =(J7-I7)/I7 -> 0.12781955 | K29: =(K7-J7)/J7 -> 0.013333333 | L29: =(L7-K7)/K7 -> -0.059210526 | N29: =SUM(C29:L29)/3 -> 0.027314119 | U29: Revenue groeth | V29: =(V28-L13)/L13 -> 0.056851293 | W29: =(W28-V28)/V28 -> 0.10003471 | X29: =(X28-W28)/W28 -> 0.12062412 | Y29: =(Y28-X28)/X28 -> 0.13243507 | Z29: =(Z28-Y28)/Y28 -> 0.14010979 | AQ29: Effective Tax Rate | AS29: =AS30/AS31 -> 0.22024472
A30: Ontario contracted facilities | C30: =(C8-B8)/B8 -> 0.042016807 | D30: =(D8-C8)/C8 -> -0.072580645 | E30: =(E8-D8)/D8 -> 0.26956522 | F30: =(F8-E8)/E8 -> 0.23287671 | G30: =(G8-F8)/F8 -> 0.62777778 | H30: =(H8-G8)/G8 -> 0.33447099 | I30: =(I8-H8)/H8 -> -0.19181586 | J30: =(J8-I8)/I8 -> 0.38291139 | ... L30: =(L8-K8)/K8 -> 0.010695187 | N30: =SUM(C30:L30)/10 -> 0.14917528 | U30: Total Expenses of Operating | V30: =AH9 -> 2770.5483 | W30: =AI9 -> 3118.1518 | X30: =AJ9 -> 3511.18 | Y30: =AK9 -> 3955.736 | Z30: =AL9 -> 4458.7576 | AQ30: Tax Expense | AS30: ='Income sheet'!B65 -> 198
A31: U.S. contracted facilities | C31: =(C9-B9)/B9 -> 0.37349398 | D31: =(D9-C9)/C9 -> 0.13157895 | E31: =(E9-D9)/D9 -> 0.55813953 | F31: =(F9-E9)/E9 -> 0.51243781 | G31: =(G9-F9)/F9 -> 0.47697368 | H31: =(H9-G9)/G9 -> 0.031180401 | I31: =(I9-H9)/H9 -> -0.13174946 | J31: =(J9-I9)/I9 -> 0.32835821 | ... L31: =(L9-K9)/K9 -> 0.83910387 | N31: =SUM(C31:L31)/10 -> 0.30389926 | U31: Depreciation and amortization | V31: =AH21 -> 547.62206 | W31: =AI21 -> 596.20263 | X31: =AJ21 -> 649.09288 | Y31: =AK21 -> 706.67511 | Z31: =AL21 -> 769.36557 | AQ31: Pre-Tax Income | AS31: ='Income sheet'!B56 -> 899
A32: U.S. commercial facilities | C32: N/A | D32: N/A | E32: N/A | F32: N/A | G32: N/A | H32: N/A | I32: N/A | J32: N/A | K32: N/A | L32: N/A | U32: EBITDA | V32: =V34+V31 -> 1220.1222 | W32: =W34+W31 -> 1271.7243 | X32: =X34+X31 -> 1408.221 | Y32: =Y34+Y31 -> 1615.1662 | Z32: =Z34+Z31 -> 1892.6825 | AQ32: Cost of Preference Shares | AS32: =AS33/AU21 -> 0.0283
A33: Unrealized changes in fair value of commodity derivatives and emission credits | C33: =(C11-B11)/B11 -> -1.4297521 | D33: =(D11-C11)/C11 -> -1.25 | E33: =(E11-D11)/D11 -> -13.461538 | F33: =(F11-E11)/E11 -> -1.1234568 | G33: =(G11-F11)/F11 -> 1.35 | H33: =(H11-G11)/G11 -> -1.9574468 | I33: =(I11-H11)/H11 -> 6.4888889 | J33: =(J11-I11)/I11 -> 0.27893175 | ... L33: =(L11-K11)/K11 -> -0.20744681 | N33: =SUM(C33:L33)/10 -> -1.3620405 | U33: EBITDA Margin | V33: =V32/V28 -> 0.30574365 | W33: =W32/W28 -> 0.2896948 | X33: =X32/X28 -> 0.28625863 | Y33: =Y32/Y28 -> 0.28992902 | Z33: =Z32/Z28 -> 0.29799266 | AQ33: DPS for PS | AS33: 0.654579
A34: Corporate | C34: =(C12-B12)/B12 -> -0.38461538 | D34: =(D12-C12)/C12 -> 1 | E34: =(E12-D12)/D12 -> 2.9375 | F34: =(F12-E12)/E12 -> -0.079365079 | G34: =(G12-F12)/F12 -> 2.2413793 | H34: =(H12-G12)/G12 -> -0.70744681 | I34: =(I12-H12)/H12 -> 1.2909091 | J34: =(J12-I12)/I12 -> 0.03968254 | ... L34: =(L12-K12)/K12 -> -0.85384615 | N34: =SUM(C34:L34)/10 -> 0.54765639 | U34: EBIT | V34: =V28-V30-V31 -> 672.5001 | W34: =W28-W30-W31 -> 675.52164 | X34: =X28-X30-X31 -> 759.12813 | Y34: =Y28-Y30-Y31 -> 908.4911 | Z34: =Z28-Z30-Z31 -> 1123.317
A35: Total Revenue | C35: =(C13-B13)/B13 -> 0.010586319 | D35: =(D13-C13)/C13 -> -0.021756648 | E35: =(E13-D13)/D13 -> -0.05601318 | F35: =(F13-E13)/E13 -> 0.23647469 | G35: =(G13-F13)/F13 -> 0.3853211 | H35: =(H13-G13)/G13 -> -0.013245033 | I35: =(I13-H13)/H13 -> 0.0273619 | J35: =(J13-I13)/I13 -> 0.4718593 | ... L35: =(L13-K13)/K13 -> -0.11816908 | N35: =SUM(C35:L35)/10 -> 0.13843518 | U35: EBIT Margin | V35: =V34/V28 -> 0.16851807 | W35: =W34/W28 -> 0.15388171 | X35: =X34/X28 -> 0.15431312 | Y35: =Y34/Y28 -> 0.16307791 | Z35: =Z34/Z28 -> 0.1768602
U36: Effective Tax Rate | V36: =AS29 -> 0.22024472 | W36: =AS29 -> 0.22024472 | X36: =AS29 -> 0.22024472 | Y36: =AS29 -> 0.22024472 | Z36: =AS29 -> 0.22024472 | AQ36: WACC | AR36: =(AR23/AS24 * AS25) + (AU23/AS24 * AS32) + (AX23/AS24 * AS26) -> 0.057954979
U37: EBIT*(1-Tax Rate) | V37: =V34*(1-V36) -> 524.38551 | W37: =W34*(1-W36) -> 526.74157 | X37: =X34*(1-X36) -> 591.93417 | Y37: =Y34*(1-Y36) -> 708.40073 | Z37: =Z34*(1-Z36) -> 875.91234
U38: (Plus)D&A | V38: =AH21 -> 547.62206 | W38: =AI21 -> 596.20263 | X38: =AJ21 -> 649.09288 | Y38: =AK21 -> 706.67511 | Z38: =AL21 -> 769.36557
U39: (less)changes in working capital | V39: =BB11 -> 108.01729 | W39: =BC11 -> 94.70094 | X39: =BD11 -> 92.533067 | Y39: =BE11 -> 98.396187 | Z39: =BF11 -> 111.64578 | AQ39: Pre-tax Cost of Debt
U40: (less)Capex | V40: =BT6 -> 642 | W40: =BU6 -> 693.36 | X40: =BV6 -> 748.8288 | Y40: =BW6 -> 808.7351 | Z40: =BX6 -> 930.04537
U41: Unlevered Free cash flow of firm | V41: =V37+V38-V39-V40 -> 321.99028 | W41: =W37+W38-W39-W40 -> 334.88326 | X41: =X37+X38-X39-X40 -> 399.66518 | Y41: =Y37+Y38-Y39-Y40 -> 507.94455 | Z41: =Z37+Z38-Z39-Z40 -> 603.58676 | AQ41: Tax Rate | AR41: =AS29 -> 0.22024472
A42: Capacity (MW) | AA42: 2025 | AB42: 2026 | AC42: 2027 | AD42: 2028 | AE42: 2029 | AO42: Risk-free rate | AQ42: After-tax cost of debt | AR42: =AS26 -> 0.029652666
A43: Year | B43: 2014 | C43: 2015 | D43: 2016 | E43: 2017 | F43: 2018 | G43: 2019 | H43: 2020 | I43: 2021 | J43: 2022 | K43: 2023 | L43: 2024 | Z43: PVs | AA43: =V41/(1+$V$44)^1 -> 304.35159 | AB43: =W41/(1+$V$44)^2 -> 299.19826 | AC43: =X41/(1+$V$44)^3 -> 337.5163 | AD43: =Y41/(1+$V$44)^4 -> 405.45957 | AE43: =Z41/(1+$V$44)^5 -> 455.41127 | AO43: Market risk premium | AQ43: Cost of Equity | AR43: =AS25 -> 0.0758
A44: Alberta commercial facilities and portfolio optimization | B44: 7279 | C44: 8769 | D44: 7504 | E44: 7372 | F44: 8502 | G44: 9049 | H44: 8763 | I44: 12877 | J44: 15171 | K44: 15311 | L44: 13204 | U44: Current WACC | V44: =AR36 -> 0.057954979 | AA44: =SUM(AA43:AE43) -> 1801.937 | AO44: Levered beta | AQ44: Net debt | AR44: =AS28 -> 7100 | AW44: 78.41 | AX44: 70.82
A45: Alberta contracted plants | B45: 6235 | C45: 6508 | D45: 6470 | E45: 6435 | F45: 6227 | G45: 6288 | H45: 6763 | I45: - | J45: - | K45: - | L45: - | U45: Present value (5-year CF) | V45: =V41/(1+V44)+W41/(1+V44)^2+X41/(1+V44)^3+Y41/(1+V44)^4+Z41/(1+V44)^5 -> 1801.937 | AQ45: Value of Preference Shares | AR45: =AU23 -> 115.65
A46: Western Canada contracted facilities | B46: - | C46: - | D46: - | E46: - | F46: - | G46: - | H46: - | I46: 1923 | J46: 1917 | K46: 1851 | L46: 2211 | AQ46: Market value of equity | AR46: =AR23 -> 11077.237 | AW46: =(AW44-AX44)/AX44 -> 0.10717311
A47: Ontario contracted facilities | C47: 1054 | D47: 1012 | E47: 1018 | F47: 1070 | G47: 2061 | H47: 1938 | I47: 1923 | J47: 2668 | K47: 2698 | L47: 3178 | AQ47: Enterprise value | AR47: =AS24 -> 18177.237
A48: U.S. contracted facilities | B48: 740 | C48: 897 | D48: 997 | E48: 2369 | F48: 4430 | G48: 7129 | H48: 6342 | I48: 6382 | J48: 8817 | K48: 12627 | L48: 19228 | AQ48: WACC | AR48: =AR36 -> 0.057954979
A49: U.S. commercial facilities | B49: - | C49: - | D49: - | E49: - | F49: - | G49: - | H49: - | I49: - | J49: - | K49: - | L49: - | U49: Share price calculation | AA49: Sensitive Analysis
A50: Year | B50: 2014 | C50: 2015 | D50: 2016 | E50: 2017 | F50: 2018 | G50: 2019 | H50: 2020 | I50: 2021 | J50: 2022 | K50: 2023 | L50: 2024 | U50: Perpetual growth rate | V50: 0.03 | AA50: =V62 -> 79.401462 | AB50: =0.056 -> 0.056 | AC50: 0.057 | AD50: =0.058 -> 0.058 | AE50: =0.059 -> 0.059 | AF50: =0.06 -> 0.06 | AG50: WACC
A51: Alberta spot price( per MWh) | B51: 49 | C51: 33 | D51: 18 | E51: 22 | F51: 50 | G51: 55 | H51: 47 | I51: 102 | J51: 162 | K51: 134 | L51: 63 | U51: Terminal Value | V51: =Z41*(1+V50)/(V44-V50) -> 22239.128 | AA51: 0.01 | AB51: 36.456412 | AC51: 34.739717 | AD51: 33.094893 | AE51: 31.517539 | AF51: 30.003606
A52: Alberta commercial facilities and portfolio optimization | U52: Implied EV/EBITDA | V52: =V51/Z32 -> 11.750057 | AA52: 0.015 | AB52: 44.733275 | AC52: 42.617717 | AD52: 40.600931 | AE52: 38.676179 | AF52: 36.837325
A53: Alberta commercial facilities Revenue | B53: =B44*B51/1000 -> 356.671 | C53: =C44*C51/1000 -> 289.377 | D53: =D44*D51/1000 -> 135.072 | E53: =E44*E51/1000 -> 162.184 | F53: =F44*F51/1000 -> 425.1 | G53: =G44*G51/1000 -> 497.695 | H53: =H44*H51/1000 -> 411.861 | I53: =I44*I51/1000 -> 1313.454 | ... L53: =L44*L51/1000 -> 831.852 | U53: Present value of terminal value | V53: =V51/(1+V44)^5 -> 16779.608 | Z53: Perpetual growth rate | AA53: 0.02 | AB53: 55.309266 | AC53: 52.624907 | AD53: 50.082242 | AE53: 47.670368 | AF53: 45.379474
A54: other income | B54: =B5-B55-B53 -> 54.329 | C54: =C5-C55-C53 -> 58.623 | D54: =D5-D55-D53 -> 85.928 | E54: =E5-E55-E53 -> 78.816 | F54: =F5-F55-F53 -> 44.9 | G54: =G5-G55-G53 -> 24.305 | H54: =H5-H55-H53 -> 54.139 | I54: =I5-I55-I53 -> 51.546 | ... L54: =L5-L55-L53 -> 79.148 | U54: Present value (5-year CF) | V54: =V45 -> 1801.937 | AA54: 0.025 | AB54: 69.296867 | AC54: 65.759344 | AD54: 62.436677 | AE54: 59.309906 | AF54: 56.362237
A55: Portfolio optimization | B55: 215 | C55: 434 | D55: 468 | E55: 416 | F55: 117 | G55: 203 | H55: 306 | I55: -15 | J55: -277 | K55: 574 | L55: 975 | U55: Enterprise Value | V55: =V54+V53 -> 18581.545 | AA55: 0.03 | AB55: 88.664315 | AC55: 83.758388 | AD55: 79.203411 | AE55: 74.963078 | AF55: 71.005921
A56: Total | B56: =SUM(B53:B55) -> 626 | C56: =SUM(C53:C55) -> 782 | D56: =SUM(D53:D55) -> 689 | E56: =SUM(E53:E55) -> 657 | F56: =SUM(F53:F55) -> 587 | G56: =SUM(G53:G55) -> 725 | H56: =SUM(H53:H55) -> 772 | I56: =SUM(I53:I55) -> 1350 | ... L56: =SUM(L53:L55) -> 1886 | U56: Total debt | V56: =AX23 -> 7100 | AA56: 0.035 | AB56: 117.25436 | AC56: 109.93881 | AD56: 103.26003 | AE56: 97.138405 | AF56: 91.507079
U57: Cash | V57: ='Balance Sheet'!B3 -> 865
A58: Alberta capacity(MW) | B58: 7279 | C58: 8769 | D58: 7504 | E58: 7372 | F58: 8502 | G58: 9049 | H58: 8763 | I58: 12877 | J58: 15171 | K58: 15311 | L58: 13204 | U58: Net Debt/ Net Cash | V58: =V56-V57 -> 6235
A59: Alberta capacity(MW) Growth | J59: =(J58-I58)/I58 -> 0.17814708 | K59: =(K58-J58)/J58 -> 0.0092281326 | L59: =(L58-K58)/K58 -> -0.13761348 | N59: =AVERAGE(K60:L60) -> -0.35134513 | O59: =AVERAGE(J60:L60) -> -0.038151653 | U59: Minority interest | V59: 2
A60: Alberta spot price growth | C60: =(C51-B51)/B51 -> -0.32653061 | D60: =(D51-C51)/C51 -> -0.45454545 | E60: =(E51-D51)/D51 -> 0.22222222 | F60: =(F51-E51)/E51 -> 1.2727273 | G60: =(G51-F51)/F51 -> 0.1 | H60: =(H51-G51)/G51 -> -0.14545455 | I60: =(I51-H51)/H51 -> 1.1702128 | J60: =(J51-I51)/I51 -> 0.58823529 | ... L60: =(L51-K51)/K51 -> -0.52985075 | N60: =AVERAGE(K61:L61) -> -1.1867979 | O60: =AVERAGE(J61:L61) -> 5.0310236 | U60: Equity Value | V60: =V55-V58-V59 -> 12344.545
A61: Portfolio optimization growth | C61: =(C55-B55)/B55 -> 1.0186047 | D61: =(D55-C55)/C55 -> 0.078341014 | E61: =(E55-D55)/D55 -> -0.11111111 | F61: =(F55-E55)/E55 -> -0.71875 | G61: =(G55-F55)/F55 -> 0.73504274 | H61: =(H55-G55)/G55 -> 0.50738916 | I61: =(I55-H55)/H55 -> -1.0490196 | J61: =(J55-I55)/I55 -> 17.466667 | ... L61: =(L55-K55)/K55 -> 0.69860627 | N61: =N60/N59 -> 3.3778694 | O61: =O60/O59 -> -131.86909 | U61: Number of share outstanding | V61: =AR22 -> 155.47 | Y61: Net Debt | Z61: Equity Value
A62: Portfolio optimization growth/spot price growth (β) | C62: =C61/C60 -> -3.1194767 | D62: =D61/D60 -> -0.17235023 | E62: =E61/E60 -> -0.5 | F62: =F61/F60 -> -0.56473214 | G62: =G61/G60 -> 7.3504274 | H62: =H61/H60 -> -3.4883005 | I62: =I61/I60 -> -0.89643494 | J62: =J61/J60 -> 29.693333 | ... L62: =L61/L60 -> -1.3184963 | U62: indicated per share price (CAD) | V62: =V60/V61 -> 79.401462 | X62: 18581.545 | Y62: 6235 | Z62: 12344.545 | AA62: 2
A63: Average β (3 years) | L63: =AVERAGE(J62:L62) -> 15.38324
O64: WACC
M65: =V62 -> 79.401462 | N65: 0.038 | O65: 0.048 | P65: 0.058 | Q65: 0.068 | R65: 0.078
M66: 0.02
M67: 0.025
L68: Terminal Growth | M68: 0.03
M69: 0.035
M70: 0.04

Sheet Sheet1

Sheet DDM_2-Stage
A1: Year | B1: Total Dividends | C1: Growth Rate | F1: Growth Rate | I1: Dividend at end of 2025 | J1: =B3*(1+G2) -> 2.7066305 | N1: sensitive analyse
A2: 2025(Est) | B2: =J1 -> 2.7066305 | C2: =AVERAGE(C3:C12) -> 0.06821 | F2: Stage 1 growth rate (2025–2029) | G2: =C2 -> 0.06821 | I2: Dividend at end of 2026 | J2: =J1*(1+G2) -> 2.8912498 | N2: =J8 -> 73.304749 | O2: 0.0622 | P2: 0.0672 | Q2: 0.0721575 | R2: 0.0772 | S2: 0.0822
A3: 2024 | B3: 2.5338 | C3: 0.0602 | F3: Stage 2 growth rate (beyond 2029) | G3: 0.03 | I3: Dividend at end of 2027 | J3: =J2*(1+G2) -> 3.0884619 | N3: 0.02 | O3: 75.8815 | P3: 67.720459 | Q3: 61.175622 | R3: 55.68424 | S3: 51.119935
A4: 2023 | B4: 2.39 | C4: 0.0599 | I4: Dividend at end of 2028 | J4: =J3*(1+G2) -> 3.2991259 | N4: 0.025 | O4: 84.698989 | P4: 74.540513 | Q4: 66.597174 | R4: 60.067262 | S4: 54.730781
A5: 2022 | B5: 2.26 | C5: 0.0637 | F5: Risk-free Rate | I5: Dividend at end of 2029 | J5: =J4*(1+G2) -> 3.5241593 | N5: 0.03 | O5: 96.25483 | P5: 83.193915 | Q5: 73.304749 | R5: 65.37889 | S5: 59.03336
A6: 2021 | B6: 2.12 | C6: 0.068 | F6: 10 YEAR CAD BOND | G6: 0.0336 | I6: Terminal Value (TV) at Year 2028 | K6: present value | N6: 0.035 | O6: 112.05914 | P6: 94.534709 | Q6: 81.817499 | R6: 71.949198 | S6: 64.247503
A7: 2020 | B7: 1.99 | C7: 0.0701 | I7: D2029/(Re-g2) | J7: =J5/(G17-G3) -> 83.595073 | K7: =NPV(G17,J1,J2,J3,J4,) -> 10.042253 | N7: 0.04 | O7: 134.98251 | P7: 110.04491 | Q7: 92.977453 | R7: 80.285717 | S7: 70.697225
A8: 2019 | B8: 1.86 | C8: 0.0723 | F8: Market Return : Rm | I8: Price 2025 | J8: =NPV(G17,J1,J2,J3,J4+J7) -> 73.304749 | K8: =NPV(G17,0,0,0,J7) -> 63.262497
A9: 2018 | B9: 1.73 | C9: 0.0712 | F9: 30 Year Annualized S&P 500 Return (Dividends Reinvested) | G9: 0.1092 | K9: =K8+K7 -> 73.304749
A10: 2017 | B10: 1.62 | C10: 0.0695 | F10: 20 Year Annualized S&P 500 Return (Dividends Reinvested) | G10: 0.1035 | R10: Stage 1 growth rate (2025–2030) | S10: 0.06821
A11: 2016 | B11: 1.51 | C11: 0.0709 | F11: Rm average | G11: =AVERAGE(G9:G10) -> 0.10635 | K11: 2025E | L11: 2026E | M11: 2027E | N11: 2028E | O11: 2029E | R11: Stage 2 growth rate (beyond 2030) | S11: 0.03
A12: 2015 | B12: 1.41 | C12: 0.0763 | K12: =J1 -> 2.7066305 | L12: =J2 -> 2.8912498 | M12: =J3 -> 3.0884619 | N12: =J4 -> 3.2991259 | O12: =J5 -> 3.5241593
A13: 2014 | B13: 1.31 | C13: 0.0397 | F13: Beta | R13: Risk-free Rate
A14: 2013 | B14: 1.26 | D14: =AVERAGE(C3:C12) -> 0.06821 | F14: 0.53 | R14: 10 YEAR CAD BOND | S14: 0.0336
F16: Discount Raate | R16: Market Return : Rm
F17: CAPM : Re = Rf + B (Rm-Rf) | G17: =G6+F14*(G11-G6) -> 0.0721575 | R17: 30 Year Annualized S&P 500 Return (Dividends Reinvested) | S17: 0.1092
R18: 20 Year Annualized S&P 500 Return (Dividends Reinvested) | S18: 0.1035
R19: Rm average | S19: 0.10635
Q24: Stage 1 growth rate (2025–2029) | R24: 0.0682
Q25: Stage 2 growth rate (beyond 2029) | R25: 0.03
Q26: Risk-free Rate | R26: 0.0336
Q27: Market Return : Rm | R27: 0.1064
Q28: Beta | R28: 0.53
Q29: Terminal Value (TV) at Year 2028 | R29: 83.6
Q30: Current Price | R30: 73.3
K37: Metric | L37: 2022 | M37: 2023 | N37: 2024
K38: Net Profit Margin | L38: 0.047 | M38: 0.122 | N38: 0.191
K39: ROE | L39: 0.045 | M39: 0.182 | N39: 0.153
K40: Debt-to-Equity | L40: 1.58 | M40: 1.26 | N40: 1.12
K41: Dividend Yield | L41: 0.0378 | M41: 0.0378 | N41: 0.0378

Sheet Figure table 
A1: Revenues and other income by fuel type | E1: Challenges and Risks (negative) | F1: Opportunities (positive) | R1: Company Data | U1: Valuation Results | X1: Financial Data
A2: Renewables | B2: 0.11 | E2: 🌦 Climate risks for hydropower | F2: ☀️ Growth in renewables & electrification | R2: Last Close | S2: 71.28 | U2: DCF –Terminal Growth | V2: =DCF!V50 -> 0.03 | Y2: 24E | Z2: 25E | AA2: 26E | AB2: 27E
A3: Flexible generation | B3: 0.81 | E3: 💰 Capital & financing pressure | F3: 💵 Government support & green incentives | R3: Market Cap | S3: 11.00B | U3: DCF –Exit Multiple | V3: =DCF!V62 -> 79.401462 | X3: Rev. ($M)
A4: Natural gas/coal dual-fuel | B4: 0.08 | E4: ⚖️ Policy & regulatory uncertainty | F4: ⚡ Technological innovation (storage, smart grid) | R4: Shares Outstanding | S4: 155.47M | U4: DDM –Terminal Growth | V4: =V2 -> 0.03 | X4: Rev. Growth
E5: 📈 Cost inflation & fuel price volatility | F5: 🌍 Cross-border trade with U.S. | R5: 52-Week High | S5: 73.05 | U5: DDM–Exit Multiple | V5: ='DDM_2-Stage'!J8 -> 73.304749 | X5: Adj. EBITDA ($M)
R6: 52-Week Low | S6: 43.9 | U6: CCA –Exit Multiple | V6: =CCA!I33 -> 83.583079 | X6: Adj. EBITDA Margin
U7: Target Price | V7: =0.5*V3+0.3*V5+0.2*V6 -> 78.408772
U8: Implied Return | V8: =(V7-S2)/S2 -> 0.10001083
A19: Revenues and other income by facility geography
A20: Alberta | B20: 0.59 | L20: 2020 | M20: 2021 | N20: 2022 | O20: 2023 | P20: 2024 | R20: 2020 | S20: 2021 | T20: 2022 | U20: 2023 | V20: 2024
A21: U.S. | B21: 0.27 | L21: 0.4 | M21: 0.39 | N21: 0.3 | O21: 0.35 | P21: 0.4 | R21: 3.5 | S21: 2.8 | T21: 2.6 | U21: 2.6 | V21: 3.2
A22: Rest of Canada | B22: 0.14
L46: Perpetual growth rate | M46: WACC
M47: 0.056 | N47: 0.057 | O47: 0.058 | P47: 0.059 | Q47: 0.06
L48: 0.01 | M48: 36.456412 | N48: 34.739717 | O48: 33.094893 | P48: 31.517539 | Q48: 30.003606
L49: 0.015 | M49: 44.733275 | N49: 42.617717 | O49: 40.600931 | P49: 38.676179 | Q49: 36.837325
L50: 0.02 | M50: 55.309266 | N50: 52.624907 | O50: 50.082242 | P50: 47.670368 | Q50: 45.379474
L51: 0.025 | M51: 69.296867 | N51: 65.759344 | O51: 62.436677 | P51: 59.309906 | Q51: 56.362237
L52: 0.03 | M52: 88.664315 | N52: 83.758388 | O52: 79.203411 | P52: 74.963078 | Q52: 71.005921
L53: 0.035 | M53: 117.25436 | N53: 109.93881 | O53: 103.26003 | P53: 97.138405 | Q53: 91.507079
L57: Perpetual growth rate | M57: Dicount Rate
L58: rate | M58: 0.0622 | N58: 0.0672 | O58: 0.0721575 | P58: 0.0772 | Q58: 0.0822
L59: 0.02 | M59: 75.8815 | N59: 67.720459 | O59: 61.175622 | P59: 55.68424 | Q59: 51.119935
L60: 0.025 | M60: 84.698989 | N60: 74.540513 | O60: 66.597174 | P60: 60.067262 | Q60: 54.730781
L61: 0.03 | M61: 96.25483 | N61: 83.193915 | O61: 73.304749 | P61: 65.37889 | Q61: 59.03336
L62: 0.035 | M62: 112.05914 | N62: 94.534709 | O62: 81.817499 | P62: 71.949198 | Q62: 64.247503
L63: 0.04 | M63: 134.98251 | N63: 110.04491 | O63: 92.977453 | P63: 80.285717 | Q63: 70.697225
L67: Scenario | M67: Economic Conditions | N67: Key Assumptions | O67: Fair Value (CAD/share)
F68: 2023 | G68: 2024 | L68: Bull Case | M68: Economic expansion, higher demand, supportive carbon policy, low interest rates | N68: GDP ↑,WACC 5.6%, g 3.5%,price +48% | O68: 117 | P68: =(O68-O69)/O69 -> 0.48101266
E69: Alberta | F69: 780 | G69: 550 | L69: Base Case | M69: Stable growth, neutral policy, balanced inflation | N69: WACC 5.8%, g 3.0%, | O69: 79
E70: U.S. | F70: 369 | G70: 656 | L70: Bear Case | M70: Slower growth, policy uncertainty, high interest rates | N70: GDP ↓, WACC 6.0%, g 2.0%,price-43% | O70: 45 | P70: =(O70-O69)/O69 -> -0.43037975
E71: Rest of Canada | F71: 342 | G71: 333
U78: Revenue Forecast
W81: Forecast
U82: Year | V82: 2025E | W82: 2026E | X82: 2027E | Y82: 2028E | Z82: 2029E
U83: Revenue Segment
U84: Alberta commercial facilities and portfolio optimization | V84: 2059.5635 | W84: 2249.0995 | X84: 2456.0781 | Y84: 2682.1043 | Z84: 2928.9311
U85: Western Canada contracted facilities | V85: 144.04045 | W85: 145.08848 | X85: 146.14412 | Y85: 147.20745 | Z85: 148.27852
U86: Ontario contracted facilities | V86: 422.57015 | W86: 472.39558 | X86: 528.09595 | Y86: 590.36397 | Z86: 659.97405
U87: U.S. contracted facilities | V87: 1110.6214 | W87: 1365.98 | X87: 1680.0516 | Y87: 2066.3358 | Z87: 2541.4361
U88: Unrealized changes in fair value of commodity derivatives and emission credits | V88: 253.875 | W88: 157.3125 | X88: 109.03125 | Y88: 84.890625 | Z88: 72.820312
U89: Total Revenue | V89: 3990.6705 | W89: 4389.8761 | X89: 4919.401 | Y89: 5570.9022 | Z89: 6351.4401
O104: Risk | P104: Likelihood (1–3) | Q104: Impact (1–3)
O105: R1 | P105: 3 | Q105: 3
O106: R2 | P106: 2 | Q106: 3
O107: R3 | P107: 2 | Q107: 2
O108: R4 | P108: 3 | Q108: 2
E116: 2013 | F116: 2023
D117: Coal/Dual Fuel Exposure (%Capacity) | E117: 0.53 | F117: 0.09
E119: 2013 | F119: 2023
D120: Adjusted EBITDA Growth | E120: 509 | F120: 1455
E122: 2013 | F122: 2023
D123: U.S. Exposure(%Capacity) | E123: 0.05 | F123: 0.5
E125: 2013 | F125: 2023
D126: Dividend Pre Share Growth(%Capacity) | E126: 1.26 | F126: 2.6
D139: =(C141-C140)/2+C140 -> #VALUE!
B140: 52week range | C140: 42.66 (low)
C141: 73.55 (high)
B142: DCF(50%) | C142: =79.4 -> 79.4
B143: DDM(30%) | C143: ='DDM_2-Stage'!J8 -> 73.304749
B144: CCA(20%) | C144: =CCA!I33 -> 83.583079
B145: Current price | C145: Trager price
C146: =0.5*C142+0.3*C143+0.2*C144 -> 78.408041 | M146: 2025E | N146: 2026E | O146: 2027E | P146: 2028E | Q146: 2029E
L147: EBITDA | M147: 1220.1222 | N147: 1271.7243 | O147: 1408.221 | P147: 1615.1662 | Q147: 1892.6825
D148: Alberta commercial facilities and portfolio optimization | E148: 2059.5635 | F148: 2249.0995 | G148: 2456.0781 | H148: 2682.1043 | I148: 2928.9311 | L148: EBITDA Margin | M148: 0.30574365 | N148: 0.2896948 | O148: 0.28625863 | P148: 0.28992902 | Q148: 0.29799266
D149: Western Canada contracted facilities | E149: 144.04045 | F149: 145.08848 | G149: 146.14412 | H149: 147.20745 | I149: 148.27852
D150: Ontario contracted facilities | E150: 422.57015 | F150: 472.39558 | G150: 528.09595 | H150: 590.36397 | I150: 659.97405
D151: U.S. contracted facilities | E151: 1110.6214 | F151: 1365.98 | G151: 1680.0516 | H151: 2066.3358 | I151: 2541.4361
D152: Unrealized changes in fair value of commodity derivatives and emission credits | E152: 253.875 | F152: 157.3125 | G152: 109.03125 | H152: 84.890625 | I152: 72.820312
E161: 2025E | F161: 2026E | G161: 2027E | H161: 2028E | I161: 2029E
D162: Total Revenue(CAD M) | E162: 3990.6705 | F162: 4389.8761 | G162: 4919.401 | H162: 5570.9022 | I162: 6351.4401
D163: Revenue Growth | E163: =(E162-DCF!L13)/DCF!L13 -> 0.056851293 | F163: =(F162-E162)/E162 -> 0.10003471 | G163: =(G162-F162)/F162 -> 0.12062412 | H163: =(H162-G162)/G162 -> 0.13243507 | I163: =(I162-H162)/H162 -> 0.14010979
D164: EBITDA(CAD M) | E164: 1220.1222 | F164: 1271.7243 | G164: 1408.221 | H164: 1615.1662 | I164: 1892.6825
D165: EBITDA Margin | E165: 0.30574365 | F165: 0.2896948 | G165: 0.28625863 | H165: 0.28992902 | I165: 0.29799266
A195: others | B195: Suncor Energy | C195: ENMAX Corporation | D195: Heartland Generation | E195: CPX | F195: TransAlta Corporation
A196: 0.367 | B196: 0.076 | C196: 0.094 | D196: 0.113 | E196: 0.133 | F196: 0.217
A215: Year | B215: Total Dividends | C215: Growth Rate | E215: Growth Rate | H215: Dividend at end of 2025 | I215: =B216*(1+F216) -> 2.7066052
A216: 2024 | B216: 2.5338 | C216: 0.0602 | E216: Stage 1 growth rate (2025–2029) | F216: 0.0682 | H216: Dividend at end of 2026 | I216: =I215*(1+F216)^2 -> 3.0883752
A217: 2023 | B217: 2.39 | C217: 0.0599 | E217: Stage 2 growth rate (beyond 2029) | F217: 0.03 | H217: Dividend at end of 2027 | I217: =I216*(1+F216) -> 3.2990024
A218: 2022 | B218: 2.26 | C218: 0.0637 | E218: Risk-free Rate | H218: Dividend at end of 2028 | I218: =I217*(1+F216) -> 3.5239943
A219: 2021 | B219: 2.12 | C219: 0.068 | E219: 10 YEAR CAD BOND | F219: 0.0336 | H219: Dividend at end of 2029 | I219: =I218*(1+F216) -> 3.7643307
A220: 2020 | B220: 1.99 | C220: 0.0701 | E220: 10 YEAR CAD BOND | F220: 0.0336 | H220: Terminal Value (TV) at Year 2028
A221: 2019 | B221: 1.86 | C221: 0.0723 | H221: D2029/(Re-g2) | I221: =I219/(F231-F217) -> 89.292077
A222: 2018 | B222: 1.73 | C222: 0.0712 | E222: Market Return : Rm | H222: Price 2025 | I222: =NPV(F231,I215,I216,I217,I218+I221) -> 78.128552
A223: 2017 | B223: 1.62 | C223: 0.0695 | E223: 30 Year Annualized S&P 500 Return (Dividends Reinvested) | F223: 0.1092
A224: 2016 | B224: 1.51 | C224: 0.0709 | E224: 20 Year Annualized S&P 500 Return (Dividends Reinvested) | F224: 0.1035
A225: 2015 | B225: 1.41 | C225: 0.0763 | E225: Rm average | F225: =AVERAGE(F223:F224) -> 0.10635
A226: 2014 | B226: 1.31 | C226: 0.0397 | G226: Average 10 year Average Growth (stage 1 growth rate)
E227: Beta | G227: Stage 2 growth rate
E228: 0.53 | G228: Risk-free Rate
C229: =SUM(C216:C225)/10 -> 0.06821 | G229: Rerurn of Market
E230: Discount Raate | G230: Beta
E231: CAPM : Re = Rf + B (Rm-Rf) | F231: =F220+E228*(F225-F220) -> 0.0721575 | H231: 2025E | I231: 2026E | J231: 2027E | K231: 2028E | L231: 2029E
G232: Dividend Forecast
G242: Share price calculation
G243: Average 10 year Average Growth (stage 1 growth rate) | H243: 0.0682
G244: Perpetual growth rate (stage 2 growth rate) | H244: 0.03
G245: Terminal Value | H245: 83.6
G246: Present value of terminal value | H246: 63.26
G247: Present value (5-year CF) | H247: 10.04
...

Sheet Sheet2
