Workbook

Sheet Financial Summary
A2: Company Name | B2: FirstEnergy Corp (FE.N)
A3: Country of Exchange | B3: United States of America
A4: Country of Headquarters | B4: United States of America
A5: TRBC Industry Group | B5: Electric Utilities & IPPs
A6: CF Template | B6: IND
A7: Consolidation Basis | B7: Consolidated
A8: Scaling | B8: Millions
A9: Period | B9: Annual
A10: Export Date | B10: 45975.878
A11: Statement Data | B11: 2024 | C11: 2023 | D11: 2022 | E11: 2021 | F11: 2020 | G11: 2019 | H11: 2018 | I11: 2017 | J11: 2016 | K11: 2015
A12: Period End Date | B12: 45657 | C12: 45291 | D12: 44926 | E12: 44561 | F12: 44196 | G12: 43830 | H12: 43465 | I12: 43100 | J12: 42735 | K12: 42369
A13: Statement Date | B13: 45656 | C13: 45290 | D13: 44925 | E13: 44560 | F13: 44195 | G13: 43829 | H13: 43464 | I13: 43464 | J13: 43464 | K13: 42368
A14: Standardized Currency | B14: USD | C14: USD | D14: USD | E14: USD | F14: USD | G14: USD | H14: USD | I14: USD | J14: USD | K14: USD
A15: Template Type | B15: Industrial - Operating | C15: Industrial - Operating | D15: Industrial - Operating | E15: Industrial - Operating | F15: Industrial - Operating | G15: Industrial - Operating | H15: Industrial - Operating | I15: Industrial - Operating | J15: Industrial - Operating | K15: Industrial - Operating
A16: Period End FX Rate | B16: 1.438 | C16: 1.3245 | D16: 1.3549 | E16: 1.2634 | F16: 1.273 | G16: 1.2986 | H16: 1.3637 | I16: 1.2577 | J16: 1.343 | K16: 1.3839
A17: Avg. FX Rate | B17: 1.370032 | C17: 1.3493112 | D17: 1.3016236 | E17: 1.2534562 | F17: 1.3408481 | G17: 1.3264151 | H17: 1.2960156 | I17: 1.2975704 | J17: 1.3248434 | K17: 1.278554
A19: Financial Summary - Standardized (Currency: Canadian Dollar)
A20: Field Name | B20: 30-12-2024 | C20: 30-12-2023 | D20: 30-12-2022 | E20: 30-12-2021 | F20: 30-12-2020 | G20: 30-12-2019 | H20: 30-12-2018 | I20: 30-12-2017 | J20: 30-12-2016 | K20: 30-12-2015
A21: Selected Per Share Data
A22: Dividend Yield - Common Stock - Gross - Issue Specific - % | B22: 4.27 | C22: 4.36 | D22: 3.72 | E22: 3.75 | F22: 5.1 | G22: 3.15 | H22: 4.85 | I22: 4.7 | J22: 4.65 | K22: 4.54
A23: Dividend Yield - Common Stock - Net - Issue Specific - % | B23: 4.27 | C23: 4.36 | D23: 3.72 | E23: 3.75 | F23: 5.1 | G23: 3.15 | H23: 4.85 | I23: 4.7 | J23: 4.65 | K23: 4.54
A24: Shares used to calculate Diluted EPS - Total | B24: 577 | C24: 574 | D24: 572 | E24: 546 | F24: 543 | G24: 542 | H24: 494 | I24: 444 | J24: 426 | K24: 424
A25: Profitability / Return
A26: Gross Profit Margin - % | B26: 55.78 | C26: 52.55 | D26: 52.1 | E26: 57.36 | F26: 59.74 | G26: 57.92 | H26: 57.53 | I26: 59.28 | J26: 55.01 | K26: 50.39
A27: EBITDA Margin - % | B27: 29.42 | C27: 28.96 | D27: 26.37 | E27: 28.91 | F27: 31.84 | G27: 33.8 | H27: 32.38 | I27: 31.99 | J27: 28.32 | K27: 29.81
A28: Operating Margin - % | B28: 17.63 | C28: 17.61 | D28: 15.33 | E28: 14.53 | F28: 20.04 | G28: 22.75 | H28: 22.22 | I28: 22.59 | J28: 19.6 | K28: 16.66
A29: Income before Tax Margin - % | B29: 11.16 | C29: 11.38 | D29: 11.55 | E29: 14 | F29: 10.46 | G29: 10.12 | H29: 13.43 | I29: 13.05 | J29: 10.07 | K29: 5.94
A30: Income Tax Rate - % | B30: 25.07 | C30: 18.24 | D30: 69.49 | E30: 20.53 | F30: 11.16 | G30: 19.07 | H30: 30.82 | I30: 36.61 | J30: 48.89 | K30: 35.27
A31: Net Margin - % | B31: 8.37 | C31: 9.3 | D31: 3.52 | E31: 11.13 | F31: 9.3 | G31: 8.19 | H31: 9.29 | I31: 8.27 | J31: 5.15 | K31: 3.85
A32: Return on Average Common Equity - % (Income available to Common excluding Extraordinary Items) | B32: 8.54 | C32: 10.9 | D32: 4.31 | E32: 15.57 | F32: 14.11 | G32: 13.12 | H32: 12.73 | I32: 17.78 | J32: 5.91 | K32: 4.65
A33: Return on Average Total Assets - % (Income before Discontinued Operations & Extraordinary Items) | B33: 2.24 | C33: 2.52 | D33: 0.96 | E33: 2.76 | F33: 2.31 | G33: 2.2 | H33: 2.54 | I33: 2.12 | J33: 1.16 | K33: 1.11
A34: Return on Invested Capital - % | B34: 4.72 | C34: 5.7 | D34: 2.15 | E34: 6.63 | F34: 6.56 | G34: 6.23 | H34: 8.34 | I34: -4.29 | J34: -18.07 | K34: 3.6
A35: Growth
A36: Common Shares - Outstanding - Total | B36: 576.61 | C36: 574.34 | D36: 572.13 | E36: 570.26 | F36: 543.12 | G36: 540.65 | H36: 511.92 | I36: 445.33 | J36: 442.34 | K36: 423.56
A37: Financial Strength / Leverage
A38: Total Debt Percentage of Total Assets | B38: 46.16 | C38: 51.08 | D38: 46.96 | E38: 52.5 | F38: 55.05 | G38: 49.64 | H38: 48.68 | I38: 46.25 | J38: 52.27 | K38: 42.18
A39: Total Debt Percentage of Total Capital | B39: 63.65 | C39: 69.53 | D39: 67.05 | E39: 73.33 | F39: 77.18 | G39: 75.07 | H39: 74.11 | I39: 83.28 | J39: 78.32 | K39: 63.88
A40: Total Debt Percentage of Total Equity | B40: 175.09 | C40: 228.2 | D40: 203.46 | E40: 274.97 | F40: 338.22 | G40: 301.05 | H40: 286.23 | I40: 497.96 | J40: 361.35 | K40: 176.89
A41: Debt Service Percentage of Normalized after Tax Profit | B41: 223.91 | C41: 172.77 | D41: 368.68 | E41: 354.96 | F41: 192.64 | G41: 160.23 | H41: 198.03 | I41: 340.21 | J41: 651.58 | K41: 326.11
A42: Interest Coverage Ratio | B42: 2.35 | C42: 2.21 | D42: 2 | E42: 1.52 | F42: 2.19 | G42: 2.61 | H42: 2.38 | I42: 2.59 | J42: 2.28 | K42: 2.47
A43: Dividend Coverage - % | B43: 99.9 | C43: 122.46 | D43: 45.52 | E43: 144.24 | F43: 118.56 | G43: 110.57 | H43: 95.5 | I43: 141.47 | J43: 90.18 | K43: 95.22
A44: Earnings Retention Rate | B44: 0 | C44: 0.18 | D44: -1.2 | E44: 0.31 | F44: 0.16 | G44: 0.1 | H44: -0.05 | I44: 0.29 | J44: -0.11 | K44: -0.05
A45: Dividend Payout Ratio - % | B45: 100.1 | C45: 81.66 | D45: 219.7 | E45: 69.33 | F45: 84.35 | G45: 90.44 | H45: 104.71 | I45: 70.69 | J45: 110.89 | K45: 105.02
A46: Dupont / Earning Power
A47: Asset Turnover | B47: 0.27 | C47: 0.27 | D47: 0.27 | E47: 0.25 | F47: 0.25 | G47: 0.27 | H47: 0.27 | I47: 0.26 | J47: 0.22 | K47: 0.29
A48: Income before Tax Margin - % | B48: 11.16 | C48: 11.38 | D48: 11.55 | E48: 14 | F48: 10.46 | G48: 10.12 | H48: 13.43 | I48: 13.05 | J48: 10.07 | K48: 5.94
A49: Pretax ROA - % | B49: 2.98 | C49: 3.09 | D49: 3.14 | E49: 3.47 | F49: 2.6 | G49: 2.71 | H49: 3.67 | I49: 3.34 | J49: 2.26 | K49: 1.72
A50: Total Assets to Total Shareholders Equity - including Minority Interest & Hybrid Debt | B50: 4.09 | C50: 4.4 | D50: 4.74 | E50: 5.65 | F50: 6.11 | G50: 5.97 | H50: 7.67 | I50: 8.4 | J50: 5.1 | K50: 4.18
A51: Pretax ROE - % | B51: 12.21 | C51: 13.58 | D51: 14.9 | E51: 19.6 | F51: 15.89 | G51: 16.2 | H51: 28.16 | I51: 28.05 | J51: 11.55 | K51: 7.19
A52: Tax Complement | B52: 0.75 | C52: 0.82 | D52: 0.31 | E52: 0.79 | F52: 0.89 | G52: 0.81 | H52: 0.69 | I52: 0.63 | J52: 0.51 | K52: 0.65
A53: Return on Average Common Equity - % (Income available to Common excluding Extraordinary Items) | B53: 8.54 | C53: 10.9 | D53: 4.31 | E53: 15.57 | F53: 14.11 | G53: 13.12 | H53: 12.73 | I53: 17.78 | J53: 5.91 | K53: 4.65
A54: Earnings Retention Rate | B54: 0 | C54: 0.18 | D54: -1.2 | E54: 0.31 | F54: 0.16 | G54: 0.1 | H54: -0.05 | I54: 0.29 | J54: -0.11 | K54: -0.05
A55: Reinvestment Rate - % | B55: -0.01 | C55: 2 | D55: -5.16 | E55: 4.78 | F55: 2.21 | G55: 1.25 | H55: -0.6 | I55: 5.21 | J55: -0.64 | K55: -0.23
A56: Liquidity
A57: Current Ratio | B57: 0.56 | C57: 0.48 | D57: 0.61 | E57: 0.73 | F57: 0.74 | G57: 0.5 | H57: 0.52 | I57: 0.76 | J57: 0.41 | K57: 0.54
A58: Quick Ratio | B58: 0.45 | C58: 0.38 | D58: 0.5 | E58: 0.67 | F58: 0.68 | G58: 0.44 | H58: 0.46 | I58: 0.7 | J58: 0.33 | K58: 0.4
A59: Working Capital to Total Assets | B59: -0.04 | C59: -0.06 | D59: -0.03 | E59: -0.03 | F59: -0.03 | G59: -0.06 | H59: -0.06 | I59: -0.02 | J59: -0.1 | K59: -0.05
A60: Operating
A61: Accounts Receivable Turnover | B61: 7.89 | C61: 8.16 | D61: 8.74 | E61: 8.19 | F61: 7.9 | G61: 7.87 | H61: 7.6 | I61: 7.13 | J61: 6.67 | K61: 8.91
A62: Average Receivables Collection Days | B62: 46.42 | C62: 44.86 | D62: 41.86 | E62: 44.68 | F62: 46.35 | G62: 46.52 | H62: 48.15 | I62: 51.36 | J62: 54.9 | K62: 41.09
A63: Payables Turnover | B63: 4.06 | C63: 4.26 | D63: 4.88 | E63: 5.36 | F63: 4.74 | G63: 4.71 | H63: 5.34 | I63: 4.76 | J63: 4.55 | K63: 6.33
A64: Average Payables Payment Days | B64: 90.23 | C64: 85.85 | D64: 75 | E64: 68.23 | F64: 77.18 | G64: 77.63 | H64: 68.56 | I64: 76.9 | J64: 80.51 | K64: 57.78
A65: Inventory Turnover | B65: 11.23 | C65: 13.09 | D65: 17.53 | E65: 16.45 | F65: 14.53 | G65: 17.43 | H65: 19.6 | I65: 11.13 | J65: 7.14 | K65: 9.31
A66: Average Inventory Days | B66: 32.59 | C66: 27.96 | D66: 20.88 | E66: 22.24 | F66: 25.19 | G66: 21 | H66: 18.67 | I66: 32.9 | J66: 51.28 | K66: 39.32
A67: Average Net Trade Cycle Days | B67: -11.22 | C67: -13.03 | D67: -12.26 | E67: -1.31 | F67: -5.63 | G67: -10.11 | H67: -1.74 | I67: 7.36 | J67: 25.67 | K67: 22.63

Sheet Income Statement
A1: Company Fundamentals - Income Statement
A2: Company Name | B2: FirstEnergy Corp (FE.N)
A3: Country of Exchange | B3: United States of America
A4: Country of Headquarters | B4: United States of America
A5: TRBC Industry Group | B5: Electric Utilities & IPPs
A6: CF Template | B6: IND
A7: Consolidation Basis | B7: Consolidated
A8: Scaling | B8: Millions
A9: Period | B9: Annual
A10: Export Date | B10: 45975.878
A11: Statement Data | B11: 2024 | C11: 2023 | D11: 2022 | E11: 2021 | F11: 2020 | G11: 2019 | H11: 2018 | I11: 2017 | J11: 2016 | K11: 2015
A12: Period End Date | B12: 45657 | C12: 45291 | D12: 44926 | E12: 44561 | F12: 44196 | G12: 43830 | H12: 43465 | I12: 43100 | J12: 42735 | K12: 42369
A13: Statement Date | B13: 45656 | C13: 45290 | D13: 44925 | E13: 44560 | F13: 44195 | G13: 43829 | H13: 43464 | I13: 43464 | J13: 43464 | K13: 42368
A14: Standardized Currency | B14: USD | C14: USD | D14: USD | E14: USD | F14: USD | G14: USD | H14: USD | I14: USD | J14: USD | K14: USD
A15: Template Type | B15: Industrial - Operating | C15: Industrial - Operating | D15: Industrial - Operating | E15: Industrial - Operating | F15: Industrial - Operating | G15: Industrial - Operating | H15: Industrial - Operating | I15: Industrial - Operating | J15: Industrial - Operating | K15: Industrial - Operating
A16: Period End FX Rate | B16: 1.438 | C16: 1.3245 | D16: 1.3549 | E16: 1.2634 | F16: 1.273 | G16: 1.2986 | H16: 1.3637 | I16: 1.2577 | J16: 1.343 | K16: 1.3839
A17: Avg. FX Rate | B17: 1.370032 | C17: 1.3493112 | D17: 1.3016236 | E17: 1.2534562 | F17: 1.3408481 | G17: 1.3264151 | H17: 1.2960156 | I17: 1.2975704 | J17: 1.3248434 | K17: 1.278554
A19: Income Statement - Standardized (Currency: Canadian Dollar)
A20: Field Name | B20: 30-12-2024 | C20: 30-12-2023 | D20: 30-12-2022 | E20: 30-12-2021 | F20: 30-12-2020 | G20: 30-12-2019 | H20: 30-12-2018 | I20: 30-12-2017 | J20: 30-12-2016 | K20: 30-12-2015
A21: Revenues
A22: Revenue from Goods & Services | B22: 18457.07 | C22: 17365.64 | D22: 16216.93 | E22: 13953.47 | F22: 14467.75 | G22: 14636.99 | H22: 14594.43 | I22: 14179.85 | J22: 14175.82 | K22: 19211.55
A23: Utility Revenue - Total | B23: 18457.07 | C23: 17365.64 | D23: 16216.93 | E23: 13953.47 | F23: 14467.75 | G23: 14636.99 | H23: 14594.43 | I23: 14179.85 | J23: 14175.82 | K23: 19211.55
A24: Utility Revenue - Electric Operations | B24: 17980.3 | C24: 16804.32 | D24: 15331.82 | E24: 13307.94 | F24: 13812.08 | G24: 13569.23 | H24: 13312.67 | I24: 12965.32 | J24: 12994.06 | K24: 13598.7
A25: Utility Revenue - Non-Utility Operations | B25: 476.77 | C25: 561.31 | D25: 885.1 | E25: 645.53 | F25: 655.67 | G25: 1067.76 | H25: 1281.76 | I25: 1214.53 | J25: 1181.76 | K25: 5612.85
A26: Revenue from Business Activities - Total | B26: 18457.07 | C26: 17365.64 | D26: 16216.93 | E26: 13953.47 | F26: 14467.75 | G26: 14636.99 | H26: 14594.43 | I26: 14179.85 | J26: 14175.82 | K26: 19211.55
A27: Operating Expenses
A28: Cost of Operating Revenue | B28: 8161.28 | C28: 8240.24 | D28: 7768.09 | E28: 5950.16 | F28: 5824.64 | G28: 6159.87 | H28: 6198.84 | I28: 5774.19 | J28: 6377.8 | K28: 9531.62
A29: Cost of Revenues - Total | B29: 8161.28 | C29: 8240.24 | D29: 7768.09 | E29: 5950.16 | F29: 5824.64 | G29: 6159.87 | H29: 6198.84 | I29: 5774.19 | J29: 6377.8 | K29: 9531.62
A30: Depreciation in Cost of Revenues | B30: 2166.02 | C30: 1971.34 | D30: 1789.73 | E30: 1632 | F30: 1708.24 | G30: 1618.23 | H30: 1472.27 | I30: 1332.6 | J30: 1236.08 | K30: 1639.11
A31: Material Expenses | B31: 5995.26 | C31: 6268.9 | D31: 5978.36 | E31: 4318.16 | F31: 4116.4 | G31: 4541.65 | H31: 4726.57 | I31: 4441.58 | J31: 5141.72 | K31: 7892.51
A32: Utility Cost of Revenue - Fuel Expense | B32: 635.69 | C32: 725.93 | D32: 950.19 | E32: 602.91 | F32: 494.77 | G32: 659.23 | H32: 697.26 | I32: 644.89 | J32: 756.49 | K32: 2371.72
A33: Utility Cost of Revenue - Purchased Power | B33: 5359.57 | C33: 5542.97 | D33: 5028.17 | E33: 3715.24 | F33: 3621.63 | G33: 3882.42 | H33: 4029.31 | I33: 3796.69 | J33: 4385.23 | K33: 5520.8
A34: Gross Profit - Industrials/Property - Total | B34: 10295.79 | C34: 9125.39 | D34: 8448.84 | E34: 8003.32 | F34: 8643.11 | G34: 8477.12 | H34: 8395.59 | I34: 8405.66 | J34: 7798.03 | K34: 9679.93
A35: Selling, General & Administrative Expenses - Total | B35: 1660.48 | C35: 1570.6 | D35: 1469.53 | E35: 1344.96 | F35: 1482.98 | G35: 1402.02 | H35: 1286.94 | I35: 1219.72 | J35: 1209.58 | K35: 1250.43
A36: Selling, General & Administrative Expenses - Other - Total | B36: 1660.48 | C36: 1570.6 | D36: 1469.53 | E36: 1344.96 | F36: 1482.98 | G36: 1402.02 | H36: 1286.94 | I36: 1219.72 | J36: 1209.58 | K36: 1250.43
A37: Property & Other Taxes | B37: 1660.48 | C37: 1570.6 | D37: 1469.53 | E37: 1344.96 | F37: 1402.53 | G37: 1337.03 | H37: 1286.94 | I37: 1219.72 | J37: 1209.58 | K37: 1250.43
A38: Rental Expense | F38: 80.45 | G38: 64.99
A39: Other Operating Expense/(Income) - Net | B39: 5381.49 | C39: 4497.25 | D39: 4493.2 | E39: 4631.52 | F39: 4261.22 | G39: 3745.8 | H39: 3866.01 | I39: 3982.24 | J39: 3810.25 | K39: 5229.29
A40: Other Operating Income - Total | B40: 316.48 | C40: 352.17 | D40: 475.09 | F40: 71.06 | G40: 104.79 | H40: 194.4
A41: Other Operating Expense | B41: 5697.96 | C41: 4849.42 | D41: 4968.3 | E41: 4631.52 | F41: 4332.28 | G41: 3850.58 | H41: 4060.42 | I41: 3982.24 | J41: 3810.25 | K41: 5229.29
A42: Operating Expenses - Total | B42: 15203.24 | C42: 14308.1 | D42: 13730.83 | E42: 11926.64 | F42: 11568.84 | G42: 11307.69 | H42: 11351.8 | I42: 10976.15 | J42: 11397.63 | K42: 16011.33
A43: Operating Profit
A44: Operating Profit before Non-Recurring Income/Expense | B44: 3253.83 | C44: 3057.54 | D44: 2486.1 | E44: 2026.84 | F44: 2898.91 | G44: 3329.3 | H44: 3242.63 | I44: 3203.7 | J44: 2778.2 | K44: 3200.22
A45: Non-Operating Expenses
A46: Financing Income/(Expense) - Net - Total | B46: -1352.22 | C46: -1385.74 | D46: -1243.05 | E46: -1336.18 | F46: -1324.76 | G46: -1276.01 | H46: -1362.11 | I46: -1236.58 | J46: -1216.21 | K46: -1325.86
A47: Interest Expense - Net of (Interest Income) | B47: 1352.22 | C47: 1385.74 | D47: 1243.05 | E47: 1336.18 | F47: 1324.76 | G47: 1276.01 | H47: 1362.11 | I47: 1236.58 | J47: 1216.21 | K47: 1297.73
A48: Interest Income - Non-Bank | B48: 32.88
A49: Interest Expense - Net of Capitalized Interest | B49: 1385.1 | C49: 1385.74 | D49: 1243.05 | E49: 1336.18 | F49: 1324.76 | G49: 1276.01 | H49: 1362.11 | I49: 1236.58 | J49: 1216.21 | K49: 1297.73
A50: Interest Expense on Capital Financing - Gross | B50: 1567.32 | C50: 1516.63 | D50: 1352.39 | E50: 1430.19 | F50: 1428 | G50: 1370.19 | H50: 1446.35 | I50: 1304.06 | J50: 1289.07 | K50: 1447.32
A51: Interest Capitalized | B51: 182.21 | C51: 130.88 | D51: 109.34 | E51: 94.01 | F51: 103.25 | G51: 94.18 | H51: 84.24 | I51: 67.47 | J51: 72.87 | K51: 149.59
A52: Non-Interest Financial Income/(Expense) - Total | K52: -28.13
A53: Non-Interest Financial Income/(Expense) - Other - Net | K53: -28.13
A54: Sale of Tangible & Intangible Fixed Assets - Gain/(Loss) | E54: 136.63
A55: Equity Earnings/(Loss) - before Taxes including Non-Recurring | B55: 79.46 | C55: 236.13 | D55: 218.67
A56: Other Non-Operating Income/(Expense) - Total | B56: 226.06 | C56: 221.29 | D56: 540.17 | E56: 648.04 | F56: 579.25 | G56: 322.32 | H56: 265.68 | I56: 68.77 | J56: 58.29
A57: Normalized Pre-tax Profit | B57: 2207.12 | C57: 2129.21 | D57: 2001.9 | E57: 1475.32 | F57: 2153.4 | G57: 2375.61 | H57: 2146.2 | I57: 2035.89 | J57: 1620.28 | K57: 1874.36
A58: Non-Recurring Income/Expense
A59: Non-Recurring Income/(Expense) - Total | B59: -146.59 | C59: -153.82 | D59: -128.86 | E59: 478.82 | F59: -639.58 | G59: -894 | H59: -186.63 | I59: -185.55 | J59: -192.1 | K59: -732.61
A60: Impairment - Tangible & Intangible Fixed Assets | I60: 53.2 | J60: 56.97 | K60: 53.7
A61: Impairment - Fixed Assets | I61: 53.2 | J61: 56.97 | K61: 53.7
A62: Impairment - Financial Investments | K62: 462.84
A63: Unrealized Adjustments on Derivatives for Hedging | K63: 93.33
A64: Debt Restructuring - Gain/(Loss) | B64: -116.45 | C64: -48.58 | D64: -222.58
A65: Non-Recurring Income/(Expense) - Other - Total | B65: -30.14 | C65: -105.25 | D65: 93.72 | E65: 478.82 | F65: -639.58 | G65: -894 | H65: -186.63 | I65: -132.35 | J65: -135.13 | K65: -309.41
A66: Pre-Tax Income
A67: Income before Taxes | B67: 2060.53 | C67: 1975.39 | D67: 1873.04 | E67: 1954.14 | F67: 1513.82 | G67: 1481.61 | H67: 1959.58 | I67: 1850.34 | J67: 1428.18 | K67: 1141.75
A68: Taxes
A69: Income Taxes | B69: 516.5 | C69: 360.27 | D69: 1301.62 | E69: 401.11 | F69: 168.95 | G69: 282.53 | H69: 603.94 | I69: 677.33 | J69: 698.19 | K69: 402.74
A70: Income Taxes for the Year - Current | B70: 83.57 | C70: 20.24 | D70: 14.32 | E70: 28.83 | F70: 9.39 | G70: 10.61 | H70: 1.3 | I70: 44.12 | J70: 10.6 | K70: 39.64
A71: Income Taxes - Domestic - Current | B71: 83.57 | C71: 20.24 | D71: 14.32 | E71: 28.83 | F71: 9.39 | G71: 10.61 | H71: 1.3 | I71: 44.12 | J71: 10.6 | K71: 39.64
A72: Income Taxes - Deferred | B72: 438.41 | C72: 344.07 | D72: 1292.51 | E72: 377.29 | F72: 178.33 | G72: 278.55 | H72: 610.42 | I72: 641 | J72: 695.54 | K72: 373.34
A73: Income Taxes - Domestic - Deferred | B73: 438.41 | C73: 344.07 | D73: 1292.51 | E73: 377.29 | F73: 178.33 | G73: 278.55 | H73: 610.42 | I73: 641 | J73: 695.54 | K73: 373.34
A74: Income Taxes - Other (by Type) | B74: -5.48 | C74: -4.05 | D74: -5.21 | E74: -5.01 | F74: -18.77 | G74: -6.63 | H74: -7.78 | I74: -7.79 | J74: -7.95 | K74: -10.23
A75: Net Income After Tax
A76: Net Income after Tax | B76: 1544.03 | C76: 1615.13 | D76: 571.41 | E76: 1553.03 | F76: 1344.87 | G76: 1199.08 | H76: 1355.63 | I76: 1173 | J76: 729.99 | K76: 739
A77: After Tax Income/Expense
A78: Income before Discontinued Operations & Extraordinary Items | B78: 1544.03 | C78: 1615.13 | D78: 571.41 | E78: 1553.03 | F78: 1344.87 | G78: 1199.08 | H78: 1355.63 | I78: 1173 | J78: 729.99 | K78: 739
A79: Extraordinary Activities - after Tax - Gain/(Loss) | C79: -28.34 | E79: 55.15 | F79: 101.9 | G79: 10.61 | H79: 391.4 | I79: -3410.02 | J79: -8913.55
A80: Discontinued Operations - Net of Taxes - Total - Income/(Expense) | C80: -28.34 | E80: 55.15 | F80: 101.9 | G80: 10.61 | H80: 422.5 | I80: -1862.01 | J80: -8913.55
A81: Discontinued Operations - Net - Income/(Expense) | E81: 2.51
A82: Sale of Discontinued Operations - Net - Gain/(Loss)
A83: Discontinued Operations before Tax - Total - Income/(Expense) | E83: -5.01 | F83: 22.79 | G83: 3.98 | H83: -1198.81 | I83: -2926.02 | J83: -13659.14
A84: Discontinued Operations before Tax - Income/(Expense) | E84: -5.01 | G84: -5.31 | H84: -62.21 | I84: -2926.02 | J84: -13659.14
A85: Sale of Discontinued Operations before Tax - Gain/(Loss) | F85: 22.79 | G85: 9.28 | H85: -1136.61
A86: Discontinued Operations - Tax Impacts | C86: -28.34 | E86: 57.66 | F86: 79.11 | G86: 6.63 | H86: 1621.32 | I86: 1064.01 | J86: 4745.59
A87: Extraordinary Items | H87: -31.1 | I87: -1548
A88: Net Income before Minority Interest | B88: 1544.03 | C88: 1586.79 | D88: 571.41 | E88: 1608.18 | F88: 1446.78 | G88: 1209.69 | H88: 1747.03 | I88: -2237.01 | J88: -8183.56 | K88: 739
A89: Minority Interest | B89: 204.13 | C89: 99.85 | D89: 42.95
A90: Net Income after Minority Interest | B90: 1339.89 | C90: 1486.94 | D90: 528.46 | E90: 1608.18 | F90: 1446.78 | G90: 1209.69 | H90: 1747.03 | I90: -2237.01 | J90: -8183.56 | K90: 739
A91: Net Income
A92: Distribution for Preferred Shares | G92: 3.98 | H92: 92.02
A93: Earnings Adjustments to Net Income - Other Expense/(Income) | G93: 1.33 | H93: 383.62
A94: Income Available to Common Shares | B94: 1339.89 | C94: 1486.94 | D94: 528.46 | E94: 1608.18 | F94: 1446.78 | G94: 1204.38 | H94: 1271.39 | I94: -2237.01 | J94: -8183.56 | K94: 739
A95: Other Comprehensive Income
A96: Other Comprehensive Income - Starting Line | B96: 1544.03 | C96: 1586.79 | D96: 571.41 | E96: 1608.18 | F96: 1446.78 | G96: 1209.69 | H96: 1747.03 | I96: -2237.01 | J96: -8183.56 | K96: 739
A97: Other Comprehensive Income - Unrealized Investment Gain/(Loss) | H97: -137.38 | I97: 28.55 | J97: 72.87 | K97: -14.06
A98: Other Comprehensive Income - Hedging Gain/(Loss) | B98: 4.11 | C98: 2.7 | D98: 11.71 | E98: 1.25 | F98: 1.34 | G98: 2.65 | H98: 27.22 | I98: 12.98 | J98: 10.6 | K98: 6.39
A99: Other Comprehensive Income - Pension Related | B99: 1.37 | C99: -8.1 | D99: -11.71 | E99: -17.55 | F99: -45.59 | G99: -41.12 | H99: -107.57 | I99: -110.29 | J99: -78.17 | K99: -148.31
A100: Other Comprehensive Income - Income Tax | B100: -1.37 | C100: 1.35 | D100: 1.3 | E100: 3.76 | F100: 10.73 | G100: 10.61 | H100: 86.83 | I100: 27.25 | J100: -1.32 | K100: 60.09
A101: Other Comprehensive Income - Net of Tax - Total | B101: 4.11 | C101: -4.05 | D101: 1.3 | E101: -12.53 | F101: -33.52 | G101: -27.85 | H101: -130.9 | I101: -41.52 | J101: 3.97 | K101: -95.89
...

Sheet Cash Flow
A1: Company Fundamentals - Cash Flow
A2: Company Name | B2: FirstEnergy Corp (FE.N)
A3: Country of Exchange | B3: United States of America
A4: Country of Headquarters | B4: United States of America
A5: TRBC Industry Group | B5: Electric Utilities & IPPs
A6: CF Template | B6: IND
A7: Consolidation Basis | B7: Consolidated
A8: Scaling | B8: Millions
A9: Period | B9: Annual
A10: Export Date | B10: 45975.878
A11: Statement Data | B11: 2024 | C11: 2023 | D11: 2022 | E11: 2021 | F11: 2020 | G11: 2019 | H11: 2018 | I11: 2017 | J11: 2016 | K11: 2015
A12: Period End Date | B12: 45657 | C12: 45291 | D12: 44926 | E12: 44561 | F12: 44196 | G12: 43830 | H12: 43465 | I12: 43100 | J12: 42735 | K12: 42369
A13: Statement Date | B13: 45656 | C13: 45290 | D13: 44925 | E13: 44560 | F13: 44195 | G13: 43829 | H13: 43464 | I13: 43464 | J13: 43464 | K13: 43099
A14: Standardized Currency | B14: USD | C14: USD | D14: USD | E14: USD | F14: USD | G14: USD | H14: USD | I14: USD | J14: USD | K14: USD
A15: Template Type | B15: Industrial - Indirect | C15: Industrial - Indirect | D15: Industrial - Indirect | E15: Industrial - Indirect | F15: Industrial - Indirect | G15: Industrial - Indirect | H15: Industrial - Indirect | I15: Industrial - Indirect | J15: Industrial - Indirect | K15: Industrial - Indirect
A16: Period End FX Rate | B16: 1.438 | C16: 1.3245 | D16: 1.3549 | E16: 1.2634 | F16: 1.273 | G16: 1.2986 | H16: 1.3637 | I16: 1.2577 | J16: 1.343 | K16: 1.3839
A17: Avg. FX Rate | B17: 1.370032 | C17: 1.3493112 | D17: 1.3016236 | E17: 1.2534562 | F17: 1.3408481 | G17: 1.3264151 | H17: 1.2960156 | I17: 1.2975704 | J17: 1.3248434 | K17: 1.278554
A19: Cash Flow - Standardized (Currency: Canadian Dollar)
A20: Field Name | B20: 30-12-2024 | C20: 30-12-2023 | D20: 30-12-2022 | E20: 30-12-2021 | F20: 30-12-2020 | G20: 30-12-2019 | H20: 30-12-2018 | I20: 30-12-2017 | J20: 30-12-2016 | K20: 30-12-2015
A21: Operating Cash Flow - Indirect
A22: Profit/(Loss) - Starting Line - Cash Flow | B22: 1544.03 | C22: 1586.79 | D22: 571.41 | E22: 1608.18 | F22: 1446.78 | G22: 1209.69 | H22: 1747.03 | I22: -2237.01 | J22: -8183.56 | K22: 739
A23: Non-cash Items & Reconciliation Adjustments - Cash Flow | B23: 2957.9 | C23: 817.68 | D23: 2655.31 | E23: 1491.61 | F23: 488.07 | G23: 1887.49 | H23: 451.01 | I23: 7089.92 | J23: 12599.26 | K23: 3481.5
A24: Discontinued Operations - Gain/(Loss) - Net of Tax - Cash Flow - to Reconcile | C24: 28.34 | E24: -58.91 | F24: -101.9 | G24: -78.26 | H24: -563.77
A25: Other Non-Cash Items & Reconciliation Adjustments - Cash Flow - to Reconcile | B25: 349.36 | C25: -1277.8 | D25: -346.23 | E25: -691.91 | F25: -1169.22 | G25: 17.24 | H25: -1389.33 | I25: 659.17 | J25: -33.12 | K25: 852.8
A26: Depreciation, Depletion & Amortization including Impairment - Cash Flow - to Reconcile | B26: 2175.61 | C26: 1727.12 | D26: 1714.24 | E26: 2006.78 | F26: 1607.68 | G26: 1614.25 | H26: 1793.69 | I26: 5318.74 | J26: 16744.7 | K26: 2388.34
A27: Accretion of Asset Retirement Obligations - Cash Flow - to Reconcile | B27: 274.01
A28: Depreciation & Depletion - Property, Plant & Equipment - Cash Flow - to Reconcile | B28: 2175.61 | C28: 1727.12 | D28: 1714.24 | E28: 2006.78 | F28: 1607.68 | G28: 1614.25 | H28: 1793.69 | I28: 2205.87 | J28: 2615.24 | K28: 2334.64
A29: Impairment - Property, Plant & Equipment including Intangible Assets - Cash Flow - to Reconcile | I29: 3112.87 | J29: 14129.46 | K29: 53.7
A30: Deferred Income Taxes & Income Tax Credits - Cash Flow - to Reconcile | B30: 432.93 | C30: 340.03 | D30: 1287.31 | E30: 372.28 | F30: 151.52 | G30: 334.26 | H30: 628.57 | I30: 1088.66 | J30: -4058 | K30: 363.11
A31: Assets Sale - Gain/(Loss) - Cash Flow - to Reconcile | E31: -136.63 | H31: -11.66 | I31: -81.75 | J31: -66.24 | K31: -29.41
A32: Financial Assets - Unrealized Gain/(Loss) - Cash Flow - to Reconcile | H32: -6.48 | I32: 105.1 | J32: 11.92 | K32: -93.33
A33: Cash Flow from Operating Activities before Changes in Working Capital | B33: 4501.93 | C33: 2404.47 | D33: 3226.72 | E33: 3099.8 | F33: 1934.84 | G33: 3097.18 | H33: 2198.04 | I33: 4852.91 | J33: 4415.7 | K33: 4220.51
A34: Working Capital - Increase/(Decrease) - Cash Flow | B34: -541.16 | C34: -532.98 | D34: 265.53 | E34: 423.67 | F34: -26.82 | G34: 175.09 | H34: -370.66 | I34: 88.23 | J34: 66.24 | K34: 203.29
A35: Accounts Receivables - Decrease/(Increase) - Cash Flow | B35: -341.14 | C35: -17.54 | D35: -380.07 | E35: 200.55 | F35: -172.97 | G35: 359.46 | H35: -321.41 | I35: -50.61 | J35: -14.57 | K35: 235.25
A36: Inventories - Decrease/(Increase) - Cash Flow | B36: -50.69 | C36: -122.79 | D36: -209.56 | E36: 71.45 | F36: -42.91 | G36: -49.08 | H36: 31.1 | I36: -7.79 | J36: 54.32 | K36: -19.18
A37: Prepaid Expenses - Decrease/(Increase) - Cash Flow | B37: -45.21 | C37: -58.02 | D37: -36.45 | E37: 22.56 | F37: 8.05 | G37: 13.26 | H37: -79.06 | I37: 38.93 | J37: 35.77 | K37: -12.79
A38: Other Assets - Decrease/(Increase) - Cash Flow | C38: -294.15
A39: Accounts Payable - Increase/(Decrease) - Cash Flow | B39: 169.88 | C39: -190.25 | D39: 728.91 | E39: 146.65 | F39: -185.04 | G39: -64.99 | H39: 141.27 | I39: 93.43 | J39: -49.02 | K39: -310.69
A40: Accrued Expenses - Increase/(Decrease) - Cash Flow | B40: -204.13 | C40: 94.45 | D40: -9.11 | E40: -36.35 | F40: 387.51 | G40: -55.71 | H40: 47.95 | I40: -46.71 | J40: 119.24 | K40: 43.47
A41: Other Liabilities - Increase/(Decrease) -Total - Cash Flow | B41: -69.87 | C41: 55.32 | D41: 171.81 | E41: 18.8 | F41: -21.45 | G41: -27.85 | H41: -190.51 | I41: 60.99 | J41: -79.49 | K41: 267.22
A42: Net Cash Flow from Operating Activities | B42: 3960.76 | C42: 1871.49 | D42: 3492.26 | E42: 3523.47 | F42: 1908.03 | G42: 3272.27 | H42: 1827.38 | I42: 4941.15 | J42: 4481.95 | K42: 4423.8
A43: Investing Cash Flow
A44: Capital Expenditures - Net - Cash Flow | B44: 5521.23 | C44: 4528.29 | D44: 3587.27 | E44: 2870.41 | F44: 3559.95 | G44: 3472.55 | H44: 2916.04 | I44: 3182.94 | J44: 4043.42 | K44: 3674.56
A45: Property, Plant & Equipment - Purchased/(Sold) - Net - Cash Flow | B45: 5521.23 | C45: 4528.29 | D45: 3587.27 | E45: 2870.41 | F45: 3559.95 | G45: 3472.55 | H45: 2916.04 | I45: 3182.94 | J45: 4043.42 | K45: 3674.56
A46: Property, Plant & Equipment - Purchased - Cash Flow | B46: 5521.23 | C46: 4528.29 | D46: 3587.27 | E46: 3064.7 | F46: 3562.63 | G46: 3534.9 | H46: 3466.84 | I46: 3686.4 | J46: 4063.29 | K46: 3700.14
A47: Property, Plant & Equipment Sold - Cash Flow | E47: 194.29 | F47: 2.68 | G47: 62.34 | H47: 550.81 | I47: 503.46 | J47: 19.87 | K47: 25.57
A48: Capital Expenditures - Total | B48: 5521.23 | C48: 4528.29 | D48: 3587.27 | E48: 3064.7 | F48: 3562.63 | G48: 3534.9 | H48: 3466.84 | I48: 3686.4 | J48: 4063.29 | K48: 3700.14
A49: Investments excluding Loans - Decrease/(Increase) - Cash Flow | B49: -17.81 | C49: -16.19 | D49: -14.32 | E49: -13.79 | F49: -29.5 | G49: -50.4 | H49: -69.98 | I49: -127.16 | J49: -147.06 | K49: -145.76
A50: Investment Securities - Unclassified - Sold/(Purchased) - Net - Total - Cash Flow | B50: -17.81 | C50: -16.19 | D50: -14.32 | E50: -13.79 | F50: -29.5 | G50: -50.4 | H50: -69.98 | I50: -127.16 | J50: -147.06 | K50: -145.76
A51: Investment Securities - Sold/Matured - Unclassified - Cash Flow | B51: 165.77 | C51: 51.27 | D51: 62.48 | E51: 60.17 | F51: 249.4 | G51: 2171.34 | H51: 1178.08 | I51: 2815.73 | J51: 2223.09 | K51: 1961.3
A52: Investment Securities - Purchased - Unclassified - Cash Flow | B52: 183.58 | C52: 67.47 | D52: 76.8 | E52: 73.95 | F52: 278.9 | G52: 2221.75 | H52: 1248.06 | I52: 2942.89 | J52: 2370.14 | K52: 2107.06
A53: Other Investing Cash Flow - Decrease/(Increase) | B53: -420.6 | C53: -383.2 | D53: -402.2 | E53: -323.39 | F53: -309.74 | G53: -287.83 | H53: -925.36 | I53: -223.18 | J53: -184.15 | K53: -171.33
A54: Net Cash Flow from Investing Activities | B54: -5959.64 | C54: -4927.68 | D54: -4003.79 | E54: -3207.59 | F54: -3899.19 | G54: -3810.79 | H54: -3911.38 | I54: -3533.28 | J54: -4374.63 | K54: -3991.65
A55: Financing Cash Flow
A56: Dividends Paid - Cash - Total - Cash Flow | B56: 1328.93 | C56: 1222.48 | D56: 1159.75 | E56: 1064.18 | F56: 1133.02 | G56: 1087.66 | H56: 1115.87 | I56: 829.15 | J56: 809.48 | K56: 776.08
A57: Dividends - Common - Cash Paid | B57: 1328.93 | C57: 1222.48 | D57: 1159.75 | E57: 1064.18 | F57: 1133.02 | G57: 1079.7 | H57: 921.47 | I57: 829.15 | J57: 809.48 | K57: 776.08
A58: Dividends - Preferred - Cash Paid | G58: 7.96 | H58: 194.4
A59: Stock - Total - Issuance/(Retirement) - Net - Cash Flow | E59: 1253.46 | H59: 3195.97
A60: Stock - Issuance/(Retirement) - Net - Excluding Options/Warrants - Cash Flow | E60: 1253.46 | H60: 3195.97
A61: Stock - Common - Issuance/(Retirement) - Net - Cash Flow | E61: 1253.46 | H61: 1101.61
A62: Stock - Common - Issued/Sold - Cash Flow | E62: 1253.46 | H62: 1101.61
A63: Stock - Preferred - Issuance/(Retirement) - Net - Cash Flow | H63: 2094.36
A64: Stock - Preferred - Issued/Sold - Cash Flow | H64: 2094.36
A65: Minority Interests & Joint Ventures - Net - Cash Flow | B65: 4677.29 | C65: -97.15 | D65: 3040.59
A66: Debt - Long-Term & Short-Term - Issuance/(Retirement) - Total - Cash Flow | B66: -1212.48 | C66: 4436.54 | D66: -2870.08 | E66: -792.18 | F66: 4707.72 | G66: 2004.21 | H66: -238.47 | I66: 11.68 | J66: 821.4 | K66: 435.99
A67: Debt - Issued/(Reduced) - Short-Term - Total - Cash Flow | B67: -308.26 | C67: 910.79 | D67: 130.16 | E67: -2757.6 | F67: 1609.02 | H67: 1231.21 | I67: -3081.73 | J67: 1291.72 | K67: -116.35
A68: Debt - Issued/(Reduced) - Long-Term - Cash Flow | B68: -904.22 | C68: 3525.75 | D68: -3000.24 | E68: 1965.42 | F68: 3098.7 | G68: 2004.21 | H68: -1469.68 | I68: 3093.41 | J68: -470.32 | K68: 552.34
A69: Debt - Issued - Long-Term - Cash Flow | B69: 2877.07 | C69: 4250.33 | D69: 911.14 | E69: 2632.26 | F69: 4592.4 | G69: 3050.75 | H69: 1910.33 | I69: 6066.14 | J69: 2617.89 | K69: 1676.18
A70: Debt - Reduced - Long-Term - Cash Flow | B70: 3781.29 | C70: 724.58 | D70: 3911.38 | E70: 666.84 | F70: 1493.7 | G70: 1046.54 | H70: 3380.01 | I70: 2972.73 | J70: 3088.21 | K70: 1123.85
A71: Other Financing Cash Flow - Increase/(Decrease) | B71: -171.25 | C71: -97.15 | D71: -197.85 | E71: -76.46 | F71: -79.11 | G71: -46.42 | H71: -34.99 | I71: -93.43 | J71: -56.97 | K71: -33.24
A72: Net Cash Flow from Financing Activities | B72: 1964.63 | C72: 3019.76 | D72: -1187.08 | E72: -679.37 | F72: 3495.59 | G72: 870.13 | H72: 1806.65 | I72: -910.89 | J72: -45.04 | K72: -373.34
A73: Change in Cash
A74: Net Change in Cash - Total | B74: -34.25 | C74: -36.43 | D74: -1698.62 | E74: -363.5 | F74: 1504.43 | G74: 331.6 | H74: -277.35 | I74: 496.97 | J74: 62.27 | K74: 58.81
A75: Net Cash from Continuing Operations | B75: -34.25 | C75: -36.43 | D75: -1698.62 | E75: -363.5 | F75: 1504.43 | G75: 331.6 | H75: -277.35 | I75: 496.97 | J75: 62.27 | K75: 58.81
A76: Net Cash - Beginning Balance | B76: 257.4 | C76: 272.85 | D76: 2047.25 | E76: 2275.38 | F76: 864.37 | G76: 557.1 | H76: 876.86 | I76: 327 | J76: 286.06 | K76: 117.63
A77: Net Cash - Ending Balance | B77: 221.45 | C77: 237.09 | D77: 279.11 | E77: 1909 | F77: 2292.67 | G77: 881.75 | H77: 585.03 | I77: 808.7 | J77: 349.18 | K77: 181.29
A78: Supplemental
A79: Income Taxes - Paid/(Reimbursed) - Cash Flow - Supplemental | B79: 220.58 | C79: 78.26 | D79: 27.33 | E79: -8.77 | F79: 8.05 | G79: 15.92 | H79: 63.5 | I79: 68.77 | J79: -21.2 | K79: 47.31
A80: Interest Paid - Cash Flow - Supplemental | B80: 1454.97 | C80: 1352.01 | D80: 1328.96 | E80: 1360 | F80: 1300.62 | G80: 1273.36 | H80: 1388.03 | I80: 1348.18 | J80: 1391.09 | K80: 1314.35
A81: CF from Optg Activities before Change in WC & Int Payments | B81: 4501.93 | C81: 2404.47 | D81: 3226.72 | E81: 3099.8 | F81: 1934.84 | G81: 3097.18 | H81: 2198.04 | I81: 4852.91 | J81: 4415.7 | K81: 4220.51
A82: Cash Dividends Paid & Common Stock Buyback - Net | C82: 1222.48 | D82: 1159.75 | E82: -189.27 | F82: 1133.02 | G82: 1079.7 | H82: -180.15 | I82: 829.15 | J82: 809.48
A83: Common Stock Buyback - Net | E83: -1253.46 | H83: -1101.61
A84: Depreciation, Depletion & Amortization - Cash Flow | B84: 2175.61 | C84: 1727.12 | D84: 1714.24 | E84: 2006.78 | F84: 1607.68 | G84: 1614.25 | H84: 1793.69 | I84: 2205.87 | J84: 2615.24 | K84: 2334.64
A85: Free Cash Flow to Equity | B85: -2772.94 | C85: 1779.74 | D85: -2965.1 | E85: -139.13 | F85: 3055.79 | G85: 1803.92 | H85: -1327.12 | I85: 1769.89 | J85: 1259.93 | K85: 1185.22
A86: Free Cash Flow Net of Dividends | B86: -2889.4 | C86: -3879.27 | D86: -1254.77 | E86: -605.42 | F86: -2787.62 | G86: -1350.29 | H86: -2755.33 | I86: 425.6 | J86: -390.83 | K86: -52.42
A87: Free Cash Flow | B87: -1560.47 | C87: -2656.79 | D87: -95.02 | E87: 458.76 | F87: -1654.61 | G87: -262.63 | H87: -1639.46 | I87: 1254.75 | J87: 418.65 | K87: 723.66
A88: Dividends Provided/Paid - Common | B88: 1341.26 | C88: 1237.32 | D88: 1161.05 | E88: 1076.72 | F88: 1134.36 | G88: 1079.7 | H88: 921.47 | I88: 829.15 | J88: 809.48 | K88: 776.08

Sheet Balance Sheet
A1: Company Fundamentals - Balance Sheet
A2: Company Name | B2: FirstEnergy Corp (FE.N)
A3: Country of Exchange | B3: United States of America
A4: Country of Headquarters | B4: United States of America
A5: TRBC Industry Group | B5: Electric Utilities & IPPs
A6: CF Template | B6: IND
A7: Consolidation Basis | B7: Consolidated
A8: Scaling | B8: Millions
A9: Period | B9: Annual
A10: Export Date | B10: 45975.878
A11: Statement Data | B11: 2024 | C11: 2023 | D11: 2022 | E11: 2021 | F11: 2020 | G11: 2019 | H11: 2018 | I11: 2017 | J11: 2016 | K11: 2015
A12: Period End Date | B12: 45657 | C12: 45291 | D12: 44926 | E12: 44561 | F12: 44196 | G12: 43830 | H12: 43465 | I12: 43100 | J12: 42735 | K12: 42369
A13: Statement Date | B13: 45656 | C13: 45290 | D13: 44925 | E13: 44560 | F13: 44195 | G13: 43829 | H13: 43464 | I13: 43464 | J13: 42734 | K13: 42734
A14: Standardized Currency | B14: USD | C14: USD | D14: USD | E14: USD | F14: USD | G14: USD | H14: USD | I14: USD | J14: USD | K14: USD
A15: Template Type | B15: Industrial - Differentiated | C15: Industrial - Differentiated | D15: Industrial - Differentiated | E15: Industrial - Differentiated | F15: Industrial - Differentiated | G15: Industrial - Differentiated | H15: Industrial - Differentiated | I15: Industrial - Differentiated | J15: Industrial - Differentiated | K15: Industrial - Differentiated
A16: Period End FX Rate | B16: 1.438 | C16: 1.3245 | D16: 1.3549 | E16: 1.2634 | F16: 1.273 | G16: 1.2986 | H16: 1.3637 | I16: 1.2577 | J16: 1.343 | K16: 1.3839
A17: Avg. FX Rate
A19: Balance Sheet - Standardized (Currency: Canadian Dollar)
A20: Field Name | B20: 30-12-2024 | C20: 30-12-2023 | D20: 30-12-2022 | E20: 30-12-2021 | F20: 30-12-2020 | G20: 30-12-2019 | H20: 30-12-2018 | I20: 30-12-2017 | J20: 30-12-2016 | K20: 30-12-2015
A21: Current Assets
A22: Cash & Short-Term Investments | B22: 159.62 | C22: 181.46 | D22: 216.78 | E22: 1847.09 | F22: 2207.38 | G22: 814.22 | H22: 500.48 | I22: 739.53 | J22: 267.26 | K22: 181.29
A23: Cash & Cash Equivalents | B23: 159.62 | C23: 181.46 | D23: 216.78 | E23: 1847.09 | F23: 2207.38 | G23: 814.22 | H23: 500.48 | I23: 739.53 | J23: 267.26 | K23: 181.29
A24: Derivative Financial Instruments - Hedging - Short-Term | J24: 188.02 | K24: 217.27
A25: Loans & Receivables - Net - Short-Term | B25: 2635.85 | C25: 2098.01 | D25: 2128.55 | E25: 1615.89 | F25: 1831.85 | G25: 1680.39 | H25: 2060.55 | I25: 1826.18 | J25: 2168.95 | K25: 2207.32
A26: Trade Accounts & Trade Notes Receivable - Net | B26: 2200.14 | C26: 1745.69 | D26: 1785.76 | E26: 1305.09 | F26: 1531.42 | G26: 1416.77 | H26: 1692.35 | I26: 1612.37 | J26: 1933.92 | K26: 1958.22
A27: Trade Accounts & Trade Notes Receivable - Gross | B27: 2279.23 | C27: 1830.46 | D27: 1971.38 | E27: 1505.97 | F27: 1740.19 | G27: 2856.92 | H27: 1760.54 | I27: 1674 | J27: 2005.1 | K27: 2053.71
A28: Provision - Trade Accounts & Trade Notes Receivable | B28: 79.09 | C28: 84.77 | D28: 185.62 | E28: 200.88 | F28: 208.77 | G28: 1440.15 | H28: 68.19 | I28: 61.63 | J28: 71.18 | K28: 95.49
A29: Receivables - Other - Total | B29: 435.71 | C29: 352.32 | D29: 342.79 | E29: 310.8 | F29: 300.43 | G29: 263.62 | H29: 368.2 | I29: 213.81 | J29: 235.03 | K29: 249.1
A30: Inventories - Total | B30: 789.46 | C30: 678.14 | D30: 570.41 | E30: 328.48 | F30: 403.54 | G30: 364.91 | H30: 343.65 | I30: 296.82 | J30: 757.45 | K30: 1086.36
A31: Inventories - Raw Materials | B31: 789.46 | C31: 678.14 | D31: 570.41 | E31: 328.48 | F31: 403.54 | G31: 364.91 | H31: 343.65 | I31: 296.82 | J31: 757.45 | K31: 1086.36
A32: Prepaid Expenses - Short-Term | B32: 345.12 | C32: 388.08 | D32: 294.01 | E32: 236.26 | F32: 199.86 | G32: 203.88 | H32: 238.65 | I32: 189.91 | J32: 131.61 | K32: 186.83
A33: Assets Held for Sale/Discontinued Operations - Short-Term | F33: 0 | G33: 42.85 | H33: 34.09 | I33: 794.87
A34: Other Current Assets - Total | B34: 61.83 | C34: 55.63 | D34: 62.33 | E34: 61.91 | F34: 85.29 | G34: 67.53 | H34: 84.55 | I34: 64.14 | J34: 448.56 | K34: 327.98
A35: Restricted Accounts - Short-Term | B35: 61.83 | C35: 55.63 | D35: 62.33 | E35: 61.91 | F35: 85.29 | G35: 67.53 | H35: 84.55 | I35: 64.14
A36: Other Current Assets | J36: 448.56 | K36: 327.98
A37: Total Current Assets | B37: 3991.89 | C37: 3401.32 | D37: 3272.08 | E37: 4089.63 | F37: 4727.92 | G37: 3173.78 | H37: 3261.97 | I37: 3911.45 | J37: 3961.85 | K37: 4207.06
A38: Non-Current Assets
A39: Investments - Long-Term | B39: 937.58 | C39: 878.14 | D39: 842.75 | E39: 827.53 | F39: 770.17 | G39: 738.9 | H39: 694.12 | I39: 636.4 | J39: 687.62 | K39: 700.25
A40: Investments - Available for Sale/Held to Maturity - Long-Term | B40: 937.58 | C40: 878.14 | D40: 842.75 | E40: 827.53 | F40: 770.17 | G40: 738.9 | H40: 694.12 | I40: 636.4 | J40: 687.62 | K40: 700.25
A41: Property, Plant & Equipment - Net - Total | B41: 59432.54 | C41: 51148.22 | D41: 49517.53 | E41: 44248.06 | F41: 42720.61 | G41: 41400.67 | H41: 40789.63 | I41: 35342.63 | J41: 39466.74 | K41: 51500.45
A42: Property, Plant & Equipment - excluding Assets Leased Out - Net - Total | B42: 59432.54 | C42: 51148.22 | D42: 49517.53 | E42: 44248.06 | F42: 42720.61 | G42: 41400.67 | H42: 40789.63 | I42: 35342.63 | J42: 39466.74 | K42: 51500.45
A43: Construction in Progress - Net | B43: 3960.25 | C43: 2802.64 | D43: 2293.85 | E43: 1786.45 | F43: 2008.79 | G43: 1701.17 | H43: 1684.17 | I43: 1256.44 | J43: 1814.39 | K43: 3351.81
A44: Right of Use Tangible Assets - Total - Net | B44: 327.86 | C44: 271.52 | D44: 354.98 | E44: 352.49 | F44: 337.35 | G44: 299.98
A45: Right of Use Tangible Assets - Operating Lease - Net | B45: 327.86 | C45: 271.52 | D45: 354.98 | E45: 352.49 | F45: 337.35 | G45: 299.98
A46: Property, Plant & Equipment - Other - Net | B46: 55144.42 | C46: 48074.05 | D46: 46868.7 | E46: 42109.12 | F46: 40374.47 | G46: 39399.52 | H46: 39105.46 | I46: 34086.19 | J46: 37652.35 | K46: 48148.65
A47: Utility Plant - Net | B47: 55144.42 | C47: 48074.05 | D47: 46868.7 | E47: 42109.12 | F47: 40374.47 | G47: 39399.52 | H47: 39105.46 | I47: 34086.19 | J47: 37652.35 | K47: 48148.65
A48: Property, Plant & Equipment - Gross - Total | B48: 80602.78 | C48: 69624.99 | D48: 67635.25 | E48: 60357.67 | F48: 57982.6 | G48: 56269.64 | H48: 55508.04 | I48: 47933.46 | J48: 60593.47 | K48: 72480.38
A49: Property, Plant & Equipment - excluding Assets Leased Out - Gross | B49: 80602.78 | C49: 69624.99 | D49: 67635.25 | E49: 60357.67 | F49: 57982.6 | G49: 56269.64 | H49: 55508.04 | I49: 47933.46 | J49: 60593.47 | K49: 72480.38
A50: Construction in Progress - Gross | B50: 3960.25 | C50: 2802.64 | D50: 2293.85 | E50: 1786.45 | F50: 2008.79 | G50: 1701.17 | H50: 1684.17 | I50: 1256.44 | J50: 1814.39 | K50: 3351.81
A51: Right of Use Tangible Assets - Total - Gross | B51: 578.08 | C51: 455.63 | D51: 509.44 | E51: 452.3 | F51: 402.27 | G51: 329.84
A52: Right of Use Tangible Assets - Operating Lease - Gross | B52: 578.08 | C52: 455.63 | D52: 509.44 | E52: 452.3 | F52: 402.27 | G52: 329.84
A53: Property, Plant & Equipment - Other - Gross | B53: 76064.45 | C53: 66366.72 | D53: 64831.97 | E53: 58118.93 | F53: 55571.54 | G53: 54238.63 | H53: 53823.88 | I53: 46677.02 | J53: 58779.08 | K53: 69128.57
A54: Utility Plant - Gross | B54: 76064.45 | C54: 66366.72 | D54: 64831.97 | E54: 58118.93 | F54: 55571.54 | G54: 54238.63 | H54: 53823.88 | I54: 46677.02 | J54: 58779.08 | K54: 69128.57
A55: Property, Plant & Equipment - Accumulated Depreciation & Impairment - Total | B55: 21170.24 | C55: 18476.78 | D55: 18117.72 | E55: 16109.61 | F55: 15262 | G55: 14868.97 | H55: 14718.41 | I55: 12590.83 | J55: 21126.73 | K55: 20979.92
A56: Property, Plant & Equipment - excluding Assets Leased Out - Accumulated Depreciation & Impairment - Total | B56: 21170.24 | C56: 18476.78 | D56: 18117.72 | E56: 16109.61 | F56: 15262 | G56: 14868.97 | H56: 14718.41 | I56: 12590.83 | J56: 21126.73 | K56: 20979.92
A57: Right of Use Tangible Assets - Total/Unspecified - Accumulated Depreciation | B57: 250.21 | C57: 184.11 | D57: 154.46 | E57: 99.81 | F57: 64.92 | G57: 29.87
A58: Right of Use Tangible Assets - Operating Lease - Accumulated Depreciation | B58: 250.21 | C58: 184.11 | D58: 154.46 | E58: 99.81 | F58: 64.92 | G58: 29.87
A59: Property, Plant & Equipment - Other - Accumulated Depreciation & Impairment | B59: 20920.02 | C59: 18292.67 | D59: 17963.26 | E59: 16009.8 | F59: 15197.07 | G59: 14839.1 | H59: 14718.41 | I59: 12590.83 | J59: 21126.73 | K59: 20979.92
A60: Utility Plant - Accumulated Depreciation & Impairment | B60: 20920.02 | C60: 18292.67 | D60: 17963.26 | E60: 16009.8 | F60: 15197.07 | G60: 14839.1 | H60: 14718.41 | I60: 12590.83 | J60: 21126.73 | K60: 20979.92
A61: Assets Held for Sale/Discontinued Operations - Long-Term | E61: 0 | F61: 57.29 | G61: 1145.37 | H61: 0 | I61: 4229.65
A62: Other Non-Current Assets - Total | B62: 2398.58 | C62: 1723.17 | D62: 1227.54 | E62: 1135.8 | F62: 1082.05 | G62: 1073.94 | H62: 2100.1 | I62: 1960.75 | J62: 6125.42 | K62: 6803.25
A63: Regulatory Assets - Long-Term | B63: 887.25 | C63: 488.74 | D63: 44.71 | E63: 89.7 | F63: 104.39 | G63: 128.56 | H63: 124.1 | I63: 50.31 | J63: 1361.8 | K63: 1865.5
A64: Other Non-Current Assets | B64: 1511.34 | C64: 1234.43 | D64: 1182.83 | E64: 1046.1 | F64: 977.66 | G64: 945.38 | H64: 1976 | I64: 1910.45 | J64: 4763.62 | K64: 4937.76
A65: Intangible Assets - Total - Net | B65: 8078.68 | C65: 7441.04 | D65: 7611.83 | E65: 7097.78 | F65: 7244.64 | G65: 7399.42 | H65: 7788.09 | I65: 7065.76 | J65: 7706.13 | K65: 8881.87
A66: Goodwill/Cost in Excess of Assets Purchased - Net | B66: 8078.68 | C66: 7441.04 | D66: 7611.83 | E66: 7097.78 | F66: 7151.71 | G66: 7295.53 | H66: 7661.27 | I66: 7065.76 | J66: 7544.97 | K66: 8881.87
A67: Intangible Assets - excluding Goodwill - Net - Total | F67: 92.93 | G67: 103.89 | H67: 126.82 | J67: 161.16
A68: Licenses, Franchises, Copyrights, Property Rights, Prototypes, Contract Based, Models & Designs - Net | F68: 92.93 | G68: 103.89 | H68: 120.01 | J68: 153.1
A69: Intangible Assets - Other - Net | H69: 6.82 | J69: 8.06
A70: Total Non-Current Assets | B70: 70847.38 | C70: 61190.58 | D70: 59199.65 | E70: 53309.16 | F70: 51874.75 | G70: 51758.3 | H70: 51371.94 | I70: 49235.18 | J70: 53985.91 | K70: 67885.83
A71: Total Assets
A72: Total Assets | B72: 74839.27 | C72: 64591.89 | D72: 62471.73 | E72: 57398.79 | F72: 56602.67 | G72: 54932.08 | H72: 54633.91 | I72: 53146.63 | J72: 57947.76 | K72: 72092.89
A73: Current Liabilities
A74: Trade Accounts Payable & Accruals - Short-Term | B74: 2946.46 | C74: 2593.37 | D74: 2749.09 | E74: 1944.37 | F74: 1856.03 | G74: 1963.48 | H74: 1749.63 | I74: 1363.35 | J74: 1888.26 | K74: 1949.92
A75: Trade Accounts & Trade Notes Payable - Short-Term | B75: 2264.85 | C75: 1803.97 | D75: 2036.41 | E75: 1191.39 | F75: 1052.77 | G75: 1305.09 | H75: 1315.97 | I75: 1040.12 | J75: 1400.75 | K75: 1487.69
A76: Accrued Expenses - Short-Term | B76: 681.61 | C76: 789.4 | D76: 712.68 | E76: 752.99 | F76: 803.26 | G76: 658.39 | H76: 433.66 | I76: 323.23 | J76: 487.51 | K76: 462.22
A77: Short-Term Debt & Current Portion of Long-Term Debt | B77: 2195.83 | C77: 2682.11 | D77: 611.06 | E77: 2029.02 | F77: 2986.46 | G77: 1792.07 | H77: 2390.57 | I77: 1079.11 | J77: 5855.48 | K77: 3977.33
A78: Short-Term Debt & Notes Payable | B78: 790.9 | C78: 1026.49 | D78: 135.49 | E78: 0 | F78: 2800.6 | G78: 1298.6 | H78: 1704.63 | I78: 377.31 | J78: 3592.53 | K78: 2363.7
A79: Current Portion of Long-Term Debt including Capitalized Leases | B79: 1404.93 | C79: 1655.63 | D79: 475.57 | E79: 2029.02 | F79: 185.86 | G79: 493.47 | H79: 685.94 | I79: 701.8 | J79: 2262.96 | K79: 1613.63
A80: Current Portion of Long-Term Debt excluding Capitalized Leases | B80: 1400.61 | C80: 1651.65 | D80: 467.44 | E80: 2012.6 | F80: 168.04 | G80: 473.99 | H80: 661.39 | J80: 2224.01
A81: Capitalized Leases - Current Portion | B81: 4.31 | C81: 3.97 | D81: 8.13 | E81: 16.42 | F81: 17.82 | G81: 19.48 | H81: 24.55 | J81: 38.95
A82: Derivative Liabilities - Hedging - Short-Term | J82: 104.75 | K82: 146.69
A83: Liabilities Held for Sale/Discontinued Operations - Short-Term | H83: 0 | I83: 1230.03
A84: Income Taxes - Payable - Short-Term | B84: 1045.43 | C84: 927.15 | D84: 905.07 | E84: 817.42 | F84: 814.72 | G84: 707.74 | H84: 726.85 | I84: 670.35 | J84: 778.94 | K84: 718.24
A85: Dividends/Distributions Payable | B85: 352.31 | C85: 311.26 | D85: 302.14 | E85: 280.47
A86: Operating Lease Liabilities - Current Portion/Short-Term | B86: 73.34 | C86: 62.25 | D86: 65.04 | E86: 49.27 | F86: 53.47 | G86: 41.56
A87: Other Current Liabilities - Total | B87: 572.32 | C87: 557.61 | D87: 730.29 | E87: 458.61 | F87: 659.41 | G87: 1808.95 | H87: 1452.34 | I87: 830.08 | J87: 942.79 | K87: 960.43
A88: Security Deposits | B88: 335.05 | C88: 300.66 | D88: 302.14
A89: Other Current Liabilities | B89: 237.27 | C89: 256.95 | D89: 428.15 | E89: 458.61 | F89: 659.41 | G89: 1808.95 | H89: 1452.34 | I89: 830.08 | J89: 942.79 | K89: 960.43
A90: Total Current Liabilities | B90: 7185.69 | C90: 7133.76 | D90: 5362.69 | E90: 5579.17 | F90: 6370.09 | G90: 6313.79 | H90: 6319.39 | I90: 5172.92 | J90: 9570.22 | K90: 7752.61
A91: Non-Current Liabilities
A92: Debt - Long-Term - Total | B92: 32349.25 | C92: 30311.18 | D92: 28727.94 | E92: 28108.12 | F92: 28172.76 | G92: 25475.93 | H92: 24207.04 | I92: 23502.64 | J92: 24431.86 | K92: 26431.11
A93: Long-Term Debt excluding Capitalized Leases | B93: 32336.31 | C93: 30296.61 | D93: 28704.91 | E93: 28079.07 | F93: 28133.3 | G93: 25417.5 | H93: 24132.04 | I93: 23502.64 | J93: 24331.13 | K93: 26248.43
A94: Debt - Non-Convertible - Long-Term | B94: 32336.31 | C94: 30296.61 | D94: 28704.91 | E94: 28079.07 | F94: 28133.3 | G94: 25417.5 | H94: 24132.04 | I94: 23502.64 | J94: 24331.13 | K94: 26248.43
A95: Capitalized Lease Obligations - Long-Term | B95: 12.94 | C95: 14.57 | D95: 23.03 | E95: 29.06 | F95: 39.46 | G95: 58.44 | H95: 75 | J95: 100.73 | K95: 182.67
A96: Liabilities Held for Sale/Discontinued Operations - Long-Term | F96: 0 | G96: 897.33 | H96: 0 | I96: 4437.17
A97: Deferred Tax & Investment Tax Credits - Long-Term | B97: 8071.49 | C97: 5999.99 | D97: 5693.29 | E97: 4342.31 | F97: 3939.94 | G97: 3699.71 | H97: 3411.98 | I97: 3988.17 | J97: 5056.4 | K97: 9373.15
A98: Deferred Tax - Liability - Long-Term | B98: 8071.49 | C98: 5999.99 | D98: 5693.29 | E98: 4342.31 | F98: 3939.94 | G98: 3699.71 | H98: 3411.98 | I98: 3988.17 | J98: 5056.4 | K98: 9373.15
A99: Operating Lease Liabilities - Long-Term | B99: 276.1 | C99: 237.09 | D99: 334.66 | E99: 342.38 | F99: 334.8 | G99: 312.96
A100: Other Non-Current Liabilities - Total | B100: 7227.39 | C100: 6451.64 | D100: 7932.94 | E100: 8066.81 | F100: 8572.38 | G100: 9174.61 | H100: 11403.26 | I100: 11109.26 | J100: 10507.63 | K100: 11345.21
A101: Provisions - Long-Term | B101: 2441.72 | C101: 2202.64 | D101: 3163.69 | E101: 3372.01 | F101: 4460.59 | G101: 4194.48 | H101: 5070.24 | I101: 5716.25 | J101: 6984.94 | K101: 7825.95
...

Sheet Valuation
A1: Company Fundamentals - Valuation
A2: Company Name | B2: FirstEnergy Corp (FE.N)
A3: Country of Exchange | B3: United States of America
A4: Country of Headquarters | B4: United States of America
A5: TRBC Industry Group | B5: Electric Utilities & IPPs
A6: CF Template | B6: IND
A7: Consolidation Basis | B7: Consolidated
A8: Scaling | B8: Millions
A9: Period | B9: Annual
A10: Export Date | B10: 45975.878
A11: Statement Data | B11: 2024 | C11: 2023 | D11: 2022 | E11: 2021 | F11: 2020 | G11: 2019 | H11: 2018 | I11: 2017 | J11: 2016 | K11: 2015
A12: Period End Date | B12: 45657 | C12: 45291 | D12: 44926 | E12: 44561 | F12: 44196 | G12: 43830 | H12: 43465 | I12: 43100 | J12: 42735 | K12: 42369
A13: Statement Date | B13: 45656 | C13: 45290 | D13: 44925 | E13: 44560 | F13: 44195 | G13: 43829 | H13: 43464 | I13: 43464 | J13: 43464 | K13: 42368
A14: Standardized Currency | B14: USD | C14: USD | D14: USD | E14: USD | F14: USD | G14: USD | H14: USD | I14: USD | J14: USD | K14: USD
A15: Template Type | B15: Industrial - Operating | C15: Industrial - Operating | D15: Industrial - Operating | E15: Industrial - Operating | F15: Industrial - Operating | G15: Industrial - Operating | H15: Industrial - Operating | I15: Industrial - Operating | J15: Industrial - Operating | K15: Industrial - Operating
A16: Period End FX Rate | B16: 1.438 | C16: 1.3245 | D16: 1.3549 | E16: 1.2634 | F16: 1.273 | G16: 1.2986 | H16: 1.3637 | I16: 1.2577 | J16: 1.343 | K16: 1.3839
A17: Avg. FX Rate | B17: 1.370032 | C17: 1.3493112 | D17: 1.3016236 | E17: 1.2534562 | F17: 1.3408481 | G17: 1.3264151 | H17: 1.2960156 | I17: 1.2975704 | J17: 1.3248434 | K17: 1.278554
A19: Valuation - Standardized (Currency: Canadian Dollar)
A20: Field Name | B20: 30-12-2024 | C20: 30-12-2023 | D20: 30-12-2022 | E20: 30-12-2021 | F20: 30-12-2020 | G20: 30-12-2019 | H20: 30-12-2018 | I20: 30-12-2017 | J20: 30-12-2016 | K20: 30-12-2015
A21: Enterprise Value
A22: Enterprise Value | B22: 69171.96 | C22: 61308.52 | D22: 62258.1 | E22: 56896.48 | F22: 50094.7 | G22: 60553.91 | H22: 52383.5 | I22: 40974.04 | J22: 47746.94 | K22: 48804.78
A23: Enterprise Value, 5 Year Average | B23: 64631.59 | C23: 59140.15 | D23: 58363.5 | E23: 51043.27 | F23: 49017.02 | G23: 48941.65 | H23: 49069.36 | I23: 44202.63 | J23: 48240.07 | K23: 49744.77
A24: Market Capitalization
A25: Market Capitalization | B25: 32967.43 | C25: 27862.25 | D25: 32489.59 | E25: 28606.42 | F25: 21142.86 | G25: 34100.13 | H25: 26189.55 | I25: 17131.83 | J25: 17726.86 | K25: 18576.25
A26: Market Capitalization, 5 Year Average | B26: 30828.53 | C26: 29278.24 | D26: 29453.99 | E26: 24847.68 | F26: 22632.31 | G26: 22260.09 | H26: 20688.85 | I26: 17719.49 | J26: 19953.54 | K26: 22035.77
A27: Price Close
A28: Price Close (End of Period) | B28: 57.2 | C28: 48.56 | D28: 56.82 | E28: 52.54 | F28: 38.97 | G28: 63.11 | H28: 51.21 | I28: 38.51 | J28: 41.59 | K28: 43.91
A29: Price Close (End of Period), 5 Year Average | B29: 54.81 | C29: 52.82 | D29: 54.27 | E29: 47.75 | F29: 45.41 | G29: 46.61 | H29: 46.33 | I29: 41.58 | J29: 47.39 | K29: 52.52
A30: FOCF Yield
A31: Free Cash Flow Yield - % | B31: -4.96 | C31: -9.36 | D31: -0.3 | E31: 1.61 | F31: -7.42 | G31: -0.75 | H31: -6.82 | I31: 7.11 | J31: 2.4 | K31: 4.21
A32: Free Cash Flow Yield - %, 5 Year Average | B32: -3.74 | C32: -2.77 | D32: -2.32 | E32: -1.24 | F32: -1.28 | G32: 0.74 | H32: -0.17 | I32: 1.05 | J32: -1.12 | K32: -0.4
A33: Dividend Yield
A34: Dividend Yield - Common Stock - Net - Issue Specific - % | B34: 4.27 | C34: 4.36 | D34: 3.72 | E34: 3.75 | F34: 5.1 | G34: 3.15 | H34: 4.85 | I34: 4.7 | J34: 4.65 | K34: 4.54
A35: Dividend Yield - Common Stock - Net - Issue Specific - %, 5 Year Average | B35: 4.19 | C35: 3.92 | D35: 4.01 | E35: 4.19 | F35: 4.37 | G35: 4.27 | H35: 4.46 | I35: 4.15
A36: Dividend Yield - Common Stock - Gross - Issue Specific - % | B36: 4.27 | C36: 4.36 | D36: 3.72 | E36: 3.75 | F36: 5.1 | G36: 3.15 | H36: 4.85 | I36: 4.7 | J36: 4.65 | K36: 4.54
A37: Dividend Yield - Common Stock - Gross - Issue Specific - %, 5 Year Average | B37: 4.19 | C37: 3.92 | D37: 4.01 | E37: 4.19 | F37: 4.37 | G37: 4.27 | H37: 4.46 | I37: 4.48 | J37: 4.63 | K37: 4.71
A38: Price to Book
A39: Price to Book Value per Share - Issue Specific | B39: 1.84 | C39: 2.02 | D39: 2.36 | E39: 2.73 | F39: 2.3 | G39: 3.77 | H39: 2.85 | I39: 3.47 | J39: 2.2 | K39: 1.08
A40: Price to Book Value per Share - Issue Specific, 5 Year Average | B40: 2.21 | C40: 2.58 | D40: 2.77 | E40: 2.98 | F40: 2.86 | G40: 2.29 | H40: 1.79 | I40: 1.48 | J40: 1.31 | K40: 1.25
A41: Price to Tangible Book
A42: Price to Tangible Book Value per Share | B42: 3.35 | C42: 4.37 | D42: 5.28 | E42: 7.76 | F42: 10.75 | G42: 20.58 | H42: 18.63 | J42: 27.24 | K42: 2.24
A43: Price to Tangible Book Value per Share, 5 Year Average | B43: 5.24 | C43: 7.41 | D43: 9.75 | E43: 21.51 | F43: 39.11 | G43: 11.3 | H43: 6.12 | I43: 4.06 | J43: 2.92 | K43: 2.51
A44: Price to Sales
A45: Price to Revenue from Business Activities - Total per Share | B45: 1.7 | C45: 1.64 | D45: 1.93 | E45: 2.04 | F45: 1.54 | G45: 2.39 | H45: 1.65 | I45: 1.24 | J45: 1.23 | K45: 0.9
A46: Price to Revenue from Business Activities - Total per Share, 5 Year Average | B46: 1.77 | C46: 1.9 | D46: 1.9 | E46: 1.75 | F46: 1.58 | G46: 1.4 | H46: 1.18 | I46: 1.06 | J46: 1.05 | K46: 1.04
A47: Price to FOCF
A48: Price to Free Cash Flow per Share | E48: 62.04 | I48: 14.06 | J48: 41.75 | K48: 23.77
A49: Price to Free Cash Flow per Share, 5 Year Average | G49: 135.08 | I49: 95.05
A50: Price to CF Per Share
A51: Price to Cash Flow per Share | B51: 8.45 | C51: 7.92 | D51: 13.22 | E51: 8 | F51: 7.3 | G51: 12.42 | H51: 8.75 | I51: 7.04 | J51: 8.89 | K51: 5.27
A52: Price to Cash Flow per Share, 5 Year Average | B52: 8.7 | C52: 9.45 | D52: 9.64 | E52: 8.61 | F52: 8.82 | G52: 8.14 | H52: 7.81 | I52: 7.79 | J52: 8.27 | K52: 8.38
A53: Price to Diluted EPS
A54: Price to EPS - Diluted - excluding Extraordinary Items Applicable to Common - Total | B54: 23.47 | C54: 18.74 | D54: 59.09 | E54: 18.32 | F54: 16.57 | G54: 29.1 | H54: 27.24 | I54: 15.04 | J54: 23.94 | K54: 23.28
A55: Price to EPS - Diluted - excluding Extraordinary Items Applicable to Common - Total, 5 Year Average | B55: 22.48 | C55: 23.59 | D55: 25.43 | E55: 20.54 | F55: 21.68 | G55: 23.18 | H55: 25.81 | I55: 27.08 | J55: 30.07 | K55: 27.99
A56: Price to Normalized Diluted EPS
A57: Price to EPS - Diluted - excluding Extraordinary Items - Normalized - Total | B57: 21.15 | C57: 17.01 | D57: 47.5 | E57: 26.5 | F57: 11.23 | G57: 16.74 | H57: 22.54 | I57: 12.98 | J57: 18.96 | K57: 11.69
A58: Price to EPS - Diluted - excluding Extraordinary Items - Normalized - Total, 5 Year Average | B58: 2.21 | C58: 2.58 | D58: 2.77 | E58: 2.98 | F58: 2.86 | G58: 2.29 | H58: 1.79 | I58: 1.48 | J58: 1.31 | K58: 1.25
A59: PEG Ratio
A60: PE Growth Ratio | B60: -1.76 | C60: 0.11 | D60: -0.86 | E60: 0.8 | F60: 1.56 | G60: 1.38 | H60: -0.84 | I60: 0.26 | J60: -4.68 | K60: 0.14
A61: PE Growth Ratio, 5 Year Average | B61: 75.62 | C61: 3.25 | D61: -1.34 | E61: 1.72 | F61: 3.46 | G61: 0.87 | H61: 2.9 | I61: 10.86 | J61: -2.97 | K61: -2.56
A62: EV to Sales
A63: Enterprise Value to Revenue from Business Activities - Total | B63: 3.57 | C63: 3.6 | D63: 3.69 | E63: 4.05 | F63: 3.65 | G63: 4.23 | H63: 3.41 | I63: 2.98 | J63: 3.32 | K63: 2.35
A64: Enterprise Value to Revenue from Business Activities - Total, 5 Year Average | B64: 3.7 | C64: 3.83 | D64: 3.8 | E64: 3.66 | F64: 3.52 | G64: 3.2 | H64: 2.86 | I64: 2.64 | J64: 2.53 | K64: 2.35
A65: EV to EBITDA
A66: Enterprise Value to Earnings before Interest, Taxes, Depreciation & Amortization (EBITDA) | B66: 12.14 | C66: 12.42 | D66: 13.99 | E66: 13.99 | F66: 11.45 | G66: 12.5 | H66: 10.54 | I66: 9.32 | J66: 11.73 | K66: 7.87
A67: Enterprise Value to Earnings before Interest, Taxes, Depreciation & Amortization (EBITDA), 5 Year Average | B67: 12.75 | C67: 12.83 | D67: 12.44 | E67: 11.53 | F67: 11.1 | G67: 10.25 | H67: 10.04 | I67: 9.99 | J67: 10 | K67: 9.68
A68: EV to CFO
A69: Enterprise Value to Net Cash Flow from Operating Activities | B69: 16.64 | C69: 33.37 | D69: 17.13 | E69: 16.02 | F69: 27.65 | G69: 18.9 | H69: 27.24 | I69: 8.56 | J69: 10.51 | K69: 10.19
A70: Enterprise Value to Net Cash Flow from Operating Activities, 5 Year Average | B70: 20.07 | C70: 20.73 | D70: 19.95 | E70: 16.95 | F70: 15.41 | G70: 12.97 | H70: 12.18 | I70: 10.97 | J70: 12.35 | K70: 12.64
A71: EV to FOCF
A72: Enterprise Value to Free Cash Flow | E72: 123.04 | I72: 33.69 | J72: 112.51 | K72: 62.31
A73: Enterprise Value to Free Cash Flow, 5 Year Average | G73: 488.19 | I73: 222.16

Sheet DCF
A1: Revenue Forecast | B1: Historical | N1: Forecast | U1: Cost Forecast | V1: Historical | AH1: Forecast | AO1: CapEx
A2: Year | B2: 2014 | C2: 2015 | D2: 2016 | E2: 2017 | F2: 2018 | G2: 2019 | H2: 2020 | I2: 2021 | J2: 2022 | K2: 2023 | L2: 2024 | M2: Revenue growth by Segement (CAGR) | N2: 2025E | O2: 2026E | P2: 2027E | Q2: 2028E | R2: 2029E | U2: Year | V2: 2014 | W2: 2015 | X2: 2016 | Y2: 2017 | Z2: 2018 | AA2: 2019 | AB2: 2020 | AC2: 2021 | AD2: 2022 | AE2: 2023 | AF2: 2024 | AG2: Cost growth (CAGR) | AH2: 2025E | AI2: 2026E | AJ2: 2027E | AK2: 2028E | AL2: 2029E | AO2: CapEx | AP2: Historical | BA2: Forecast
A3: Utility Revenue - Electric Operations | C3: 13598.7 | D3: 12994.06 | E3: 12965.32 | F3: 13312.67 | G3: 13569.23 | H3: 13812.08 | I3: 13307.94 | J3: 15331.82 | K3: 16804.32 | L3: 17980.3 | M3: =POWER((L3/D3),1/8)-1 -> 0.041433415 | N3: =L3*(1+M3) -> 18725.285 | O3: =N3*(1+M3) -> 19501.138 | P3: =O3*(1+M3) -> 20309.136 | Q3: =P3*(1+M3) -> 21150.613 | R3: =Q3*(1+M3) -> 22026.956 | U3: Cost Items | AN3: 2014 | AO3: Year | AP3: 2015 | AQ3: 2016 | AR3: 2017 | AS3: 2018 | AT3: 2019 | AU3: 2020 | AV3: 2021 | AW3: 2022 | AX3: 2023 | AY3: 2024 | AZ3: Cost growth (CAGR) | BA3: 2025E | BB3: 2026E | BC3: 2027E | BD3: 2028E | BE3: 2029E
A4: Utility Revenue - Non-Utility Operations | C4: 5612.85 | D4: 1181.76 | E4: 1214.53 | F4: 1281.76 | G4: 1067.76 | H4: 655.67 | I4: 645.53 | J4: 885.1 | K4: 561.31 | L4: 476.77 | M4: =POWER((L4/D4),1/8)-1 -> -0.10726522 | N4: =L4*(1+M4) -> 425.62916 | O4: =N4*(1+M4) -> 379.97395 | P4: =O4*(1+M4) -> 339.21596 | Q4: =P4*(1+M4) -> 302.82989 | R4: =Q4*(1+M4) -> 270.34677 | U4: Cost of Operating Revenue | V4: =9073.57 -> 9073.57 | W4: 9531.62 | X4: 6377.8 | Y4: 5774.19 | Z4: 6198.84 | AA4: 6159.87 | AB4: 5824.64 | AC4: 5950.16 | AD4: 7768.09 | AE4: 8240.24 | AF4: 8161.28 | AN4: 3915.02 | AO4: Capital Expenditures - Total | AP4: ='Cash Flow'!K48 -> 3700.14 | AQ4: ='Cash Flow'!J48 -> 4063.29 | AR4: ='Cash Flow'!I48 -> 3686.4 | AS4: ='Cash Flow'!H48 -> 3466.84 | AT4: ='Cash Flow'!G48 -> 3534.9 | AU4: ='Cash Flow'!F48 -> 3562.63 | AV4: ='Cash Flow'!E48 -> 3064.7 | AW4: ='Cash Flow'!D48 -> 3587.27 | AX4: ='Cash Flow'!C48 -> 4528.29 | AY4: ='Cash Flow'!B48 -> 5521.23 | AZ4: 0.035 | BA4: =AY4*50% -> 2760.615 | BB4: =BA4*(1+AZ4) -> 2857.2365 | BC4: =BB4*(1+AZ4) -> 2957.2398 | BD4: =BC4*(1+AZ4) -> 3060.7432 | BE4: =BD4*(1+AZ4) -> 3167.8692
A5: Revenue from Business Activities - Total | C5: 19211.55 | D5: 14175.82 | E5: 14179.85 | F5: 14594.43 | G5: 14636.99 | H5: 14467.75 | I5: 13953.47 | J5: 16216.93 | K5: 17365.64 | L5: 18457.07 | M5: =4.8% -> 0.048 | N5: =L5*(1+M5) -> 19343.009 | O5: =N5*(1+M5) -> 20271.474 | P5: =O5*(1+M5) -> 21244.505 | Q5: =P5*(1+M5) -> 22264.241 | R5: =Q5*(1+M5) -> 23332.924 | U5: Cost of Revenues - Total | V5: =9073.57 -> 9073.57 | W5: 9531.62 | X5: 6377.8 | Y5: 5774.19 | Z5: 6198.84 | AA5: 6159.87 | AB5: 5824.64 | AC5: 5950.16 | AD5: 7768.09 | AE5: 8240.24 | AF5: 8161.28 | AG5: =POWER((AF5/V5),1/10)-1 -> -0.010540532 | AO5: growth rate | AP5: =(AP4-AN4)/AN4 -> -0.054886054 | AQ5: =(AQ4-AP4)/AP4 -> 0.098144935 | AR5: =(AR4-AQ4)/AQ4 -> -0.092754886 | AS5: =(AS4-AR4)/AR4 -> -0.059559462 | AT5: =(AT4-AS4)/AS4 -> 0.019631711 | AU5: =(AU4-AT4)/AT4 -> 0.0078446349 | AV5: =(AV4-AU4)/AU4 -> -0.13976472 | AW5: =(AW4-AV4)/AV4 -> 0.17051261 | AX5: =(AX4-AW4)/AW4 -> 0.26232204 | AY5: =(AY4-AX4)/AX4 -> 0.21927483 | AZ5: =AVERAGE(AP5:AY5) -> 0.043076564
N6: =N3+N4 -> 19150.914 | O6: =O3+O4 -> 19881.112 | P6: =P3+P4 -> 20648.352 | Q6: =Q3+Q4 -> 21453.443 | R6: =R3+R4 -> 22297.302 | U6: Depreciation in Cost of Revenues | V6: 1347.34 | W6: 1639.11 | X6: 1236.08 | Y6: 1332.6 | Z6: 1472.27 | AA6: 1618.23 | AB6: 1708.24 | AC6: 1632 | AD6: 1789.73 | AE6: 1971.34 | AF6: 2166.02 | AG6: =POWER((AF6/V6),1/10)-1 -> 0.04862094 | AH6: =AF6*(1+AG16) -> 2287.4412 | AI6: =AH6*(1+AG16) -> 2415.669 | AJ6: =AI6*(1+AG16) -> 2551.0848 | AK6: =AJ6*(1+AG165) -> 2551.0848 | AL6: =AK6*(1+AG16) -> 2694.0918
A7: Net Working Capital | U7: Material Expenses | V7: 7726.23 | W7: 7892.51 | X7: 5141.72 | Y7: 4441.58 | Z7: 4726.57 | AA7: 4541.65 | AB7: 4116.4 | AC7: 4318.16 | AD7: 5978.36 | AE7: 6268.9 | AF7: 5995.26 | AG7: =POWER((AF7/V7),1/10)-1 -> -0.025046194 | AH7: =AF7*(1+AG9) -> 6012.4549 | AI7: =AH7+(1+AG9) -> 6013.4578 | AJ7: =AI7*(1+AG9) -> 6030.7049 | AK7: =AJ7*(1+AG9) -> 6048.0015 | AL7: =AK7*(1+AG9) -> 6065.3478
B8: Operating CA = AR+Inv+Prepaid+OCA | C8: Operating CL = AP+Acc+OCL | D8: Operating NWC | U8: Utility Cost of Revenue - Fuel Expense | V8: 2517.98 | W8: 2371.72 | X8: 756.49 | Y8: 644.89 | Z8: 697.26 | AA8: 659.23 | AB8: 494.77 | AC8: 602.91 | AD8: 950.19 | AE8: 725.93 | AF8: 635.69 | AG8: =POWER((AF8/V8),1/10)-1 -> -0.12859648
A9: 2015 | B9: 3396.53 | C9: 3518.8 | D9: -122.27 | E9: =D9/C5 -> -0.0063644006 | U9: Utility Cost of Revenue - Purchased Power | V9: 5208.25 | W9: 5520.8 | X9: 4385.23 | Y9: 3796.69 | Z9: 4029.31 | AA9: 3882.42 | AB9: 3621.63 | AC9: 3715.24 | AD9: 5028.17 | AE9: 5542.97 | AF9: 5359.57 | AG9: =POWER((AF9/V9),1/10)-1 -> 0.0028680892
A10: 2016 | B10: 2867.53 | C10: 3151 | D10: -283.47 | E10: =D10/D5 -> -0.019996727 | U10: Selling, General & Administrative Expenses - Total | V10: 1062.41 | W10: 1250.43 | X10: 1209.58 | Y10: 1219.72 | Z10: 1286.94 | AA10: 1402.02 | AB10: 1482.98 | AC10: 1344.96 | AD10: 1469.53 | AE10: 1570.6 | AF10: 1660.48 | AG10: =POWER((AF10/V10),1/10)-1 -> 0.0456688 | AH10: =AF10*(1+AG10) -> 1736.3121 | AI10: =AH10*(1+AG10) -> 1815.6074 | AJ10: =AI10*(1+AG10) -> 1898.524 | AK10: =AJ10*(1+AG10) -> 1985.2273 | AL10: =AK10*(1+AG10) -> 2075.8903
A11: 2017 | B11: 2712.53 | C11: 3479.4 | D11: -766.87 | E11: =D11/E5 -> -0.054081672 | U11: Other Operating Expense/(Income) - Net | V11: 4318.12 | W11: 5229.29 | X11: 3810.25 | Y11: 3982.24 | Z11: 3866.01 | AA11: 3745.8 | AB11: 4261.22 | AC11: 4631.52 | AD11: 4493.2 | AE11: 4497.25 | AF11: 5381.49 | AG11: =POWER((AF11/V11),1/10)-1 -> 0.022258624 | AH11: =AF11*(1+AG11) -> 5501.2746 | AI11: =AH11*(1+AG11) -> 5623.7254 | AJ11: =AI11*(1+AG11) -> 5748.9018 | AK11: =AJ11*(1+AG11) -> 5876.8644 | AL11: =AK11*(1+AG11) -> 6007.6753
A12: 2018 | B12: 1931.81 | C12: 2403 | D12: -471.19 | E12: =D12/F5 -> -0.032285605 | U12: Operating Expenses - Total | V12: 14454.1 | W12: =W5+W10+W11 -> 16011.34 | X12: =X5+X10+X11 -> 11397.63 | Y12: =Y5+Y10+Y11 -> 10976.15 | Z12: =Z5+Z10+Z11 -> 11351.79 | AA12: =AA5+AA10+AA11 -> 11307.69 | AB12: =AB5+AB10+AB11 -> 11568.84 | AC12: =AC5+AC10+AC11 -> 11926.64 | AD12: =AD5+AD10+AD11 -> 13730.82 | ... AF12: =AF5+AF10+AF11 -> 15203.25 | AH12: =SUM(AH6:AH11) -> 15537.483 | AI12: =SUM(AI6:AI11) -> 15868.46 | AJ12: =SUM(AJ6:AJ11) -> 16229.216 | AK12: =SUM(AK6:AK11) -> 16461.178 | AL12: =SUM(AL6:AL11) -> 16843.005
A13: 2019 | B13: 2220.09 | C13: 2515.5 | D13: -295.41 | E13: =D13/G5 -> -0.020182428 | U13: Growth rote
A14: 2020 | B14: 2053.13 | C14: 3772.5 | D14: -1719.37 | E14: =D14/H5 -> -0.11884156 | U14: Cost of Operating Revenue | W14: =(W4-V4)/V4 -> 0.050481784 | X14: =(X4-W4)/W4 -> -0.33087975 | Y14: =(Y4-X4)/X4 -> -0.094642353 | Z14: =(Z4-Y4)/Y4 -> 0.073542783 | AA14: =(AA4-Z4)/Z4 -> -0.0062866601 | AB14: =(AB4-AA4)/AA4 -> -0.054421603 | AC14: =(AC4-AB4)/AB4 -> 0.02154983 | AD14: =(AD4-AC4)/AC4 -> 0.30552624 | ... AF14: =(AF4-AE4)/AE4 -> -0.0095822452 | AG14: =AVERAGE(W14:AF14) -> 0.0016068734
A15: 2021 | B15: 2359.35 | C15: 3202 | D15: -842.65 | E15: =D15/I5 -> -0.060389996 | U15: Cost of Revenues - Total | W15: =(W5-V5)/V5 -> 0.050481784 | X15: =(X5-W5)/W5 -> -0.33087975 | Y15: =(Y5-X5)/X5 -> -0.094642353 | Z15: =(Z5-Y5)/Y5 -> 0.073542783 | AA15: =(AA5-Z5)/Z5 -> -0.0062866601 | AB15: =(AB5-AA5)/AA5 -> -0.054421603 | AC15: =(AC5-AB5)/AB5 -> 0.02154983 | AD15: =(AD5-AC5)/AC5 -> 0.30552624 | ... AF15: =(AF5-AE5)/AE5 -> -0.0095822452 | AG15: =AVERAGE(W15:AF15) -> 0.0016068734
A16: 2022 | B16: 2163.24 | C16: 2193.4 | D16: -30.16 | E16: =D16/I5 -> -0.0021614695 | U16: Depreciation in Cost of Revenues | W16: =(W6-V6)/V6 -> 0.21655261 | X16: =(X6-W6)/W6 -> -0.24588344 | Y16: =(Y6-X6)/X6 -> 0.078085561 | Z16: =(Z6-Y6)/Y6 -> 0.10481015 | AA16: =(AA6-Z6)/Z6 -> 0.099139424 | AB16: =(AB6-AA6)/AA6 -> 0.055622501 | AC16: =(AC6-AB6)/AB6 -> -0.044630731 | AD16: =(AD6-AC6)/AC6 -> 0.096648284 | ... AF16: =(AF6-AE6)/AE6 -> 0.098755161 | AG16: =AVERAGE(W16:AF16) -> 0.056057293
A17: 2023 | B17: 3271.6 | C17: 2831.1 | D17: 440.5 | E17: =D17/J5 -> 0.027162971 | U17: Material Expenses | W17: =(W7-V7)/V7 -> 0.021521492 | X17: =(X7-W7)/W7 -> -0.34853171 | Y17: =(Y7-X7)/X7 -> -0.13616844 | Z17: =(Z7-Y7)/Y7 -> 0.064164104 | AA17: =(AA7-Z7)/Z7 -> -0.039123508 | AB17: =(AB7-AA7)/AA7 -> -0.093633371 | AC17: =(AC7-AB7)/AB7 -> 0.049013701 | AD17: =(AD7-AC7)/AC7 -> 0.38446931 | ... AF17: =(AF7-AE7)/AE7 -> -0.043650401 | AG17: =AVERAGE(W17:AF17) -> -0.0093340211
A18: 2024 | B18: 3559.4 | C18: 2910.3 | D18: 649.1 | E18: =D18/L5 -> 0.035168095 | U18: Utility Cost of Revenue - Fuel Expense | W18: =(W8-V8)/V8 -> -0.058086244 | X18: =(X8-W8)/W8 -> -0.68103739 | Y18: =(Y8-X8)/X8 -> -0.14752343 | Z18: =(Z8-Y8)/Y8 -> 0.081207648 | AA18: =(AA8-Z8)/Z8 -> -0.054542065 | AB18: =(AB8-AA8)/AA8 -> -0.24947287 | AC18: =(AC8-AB8)/AB8 -> 0.2185662 | AD18: =(AD8-AC8)/AC8 -> 0.57600637 | ... AF18: =(AF8-AE8)/AE8 -> -0.12430951 | AG18: =AVERAGE(W18:AF18) -> -0.067520724
B19: Revenue | C19: Operating NWC (3% of Rev) | U19: Utility Cost of Revenue - Purchased Power | W19: =(W9-V9)/V9 -> 0.06001056 | X19: =(X9-W9)/W9 -> -0.20568939 | Y19: =(Y9-X9)/X9 -> -0.13420961 | Z19: =(Z9-Y9)/Y9 -> 0.061269158 | AA19: =(AA9-Z9)/Z9 -> -0.036455373 | AB19: =(AB9-AA9)/AA9 -> -0.067172022 | AC19: =(AC9-AB9)/AB9 -> 0.025847478 | AD19: =(AD9-AC9)/AC9 -> 0.35339036 | ... AF19: =(AF9-AE9)/AE9 -> -0.033086955 | AG19: =AVERAGE(W19:AF19) -> 0.012628738
A20: 2025 | B20: =N5 -> 19343.009 | C20: =B20*0.01 -> 193.43009 | U20: Selling, General & Administrative Expenses - Total | W20: =(W10-V10)/V10 -> 0.17697499 | X20: =(X10-W10)/W10 -> -0.032668762 | Y20: =(Y10-X10)/X10 -> 0.0083830751 | Z20: =(Z10-Y10)/Y10 -> 0.055111009 | AA20: =(AA10-Z10)/Z10 -> 0.089421418 | AB20: =(AB10-AA10)/AA10 -> 0.057745253 | AC20: =(AC10-AB10)/AB10 -> -0.09306936 | AD20: =(AD10-AC10)/AC10 -> 0.092619855 | ... AF20: =(AF10-AE10)/AE10 -> 0.057226538 | AG20: =AVERAGE(W20:AF20) -> 0.048052111
A21: 2026 | B21: =O5 -> 20271.474 | C21: =B21*0.01 -> 202.71474 | U21: Other Operating Expense/(Income) - Net | W21: =(W11-V11)/V11 -> 0.21101081 | X21: =(X11-W11)/W11 -> -0.2713638 | Y21: =(Y11-X11)/X11 -> 0.04513877 | Z21: =(Z11-Y11)/Y11 -> -0.029187091 | AA21: =(AA11-Z11)/Z11 -> -0.031094074 | AB21: =(AB11-AA11)/AA11 -> 0.13759944 | AC21: =(AC11-AB11)/AB11 -> 0.086899996 | AD21: =(AD11-AC11)/AC11 -> -0.029864926 | ... AF21: =(AF11-AE11)/AE11 -> 0.19661793 | AG21: =AVERAGE(W21:AF21) -> 0.031665843
A22: 2027 | B22: =P5 -> 21244.505 | C22: =B22*0.01 -> 212.44505 | U22: Operating Expenses - Total | W22: =(W12-V12)/V12 -> 0.10773691 | X22: =(X12-W12)/W12 -> -0.28815265 | Y22: =(Y12-X12)/X12 -> -0.036979618 | Z22: =(Z12-Y12)/Y12 -> 0.034223293 | AA22: =(AA12-Z12)/Z12 -> -0.0038848499 | AB22: =(AB12-AA12)/AA12 -> 0.023094903 | AC22: =(AC12-AB12)/AB12 -> 0.030927906 | AD22: =(AD12-AC12)/AC12 -> 0.15127312 | ... AF22: =(AF12-AE12)/AE12 -> 0.062563207 | AG22: =AVERAGE(W22:AF22) -> 0.012284413
A23: 2028 | B23: =Q5 -> 22264.241 | C23: =B23*0.01 -> 222.64241
A24: 2029 | B24: =R5 -> 23332.924 | C24: =B24*0.01 -> 233.32924 | AO24: WACC
AP25: Total Value of Equity | AS25: Total Value of Preference Shares | AV25: Total Value of Debt
V26: Forecast | AO26: Share Price | AP26: 45.94 | AS26: 0 | AV26: 27470
V27: 2025E | W27: 2026E | X27: 2027E | Y27: 2028E | Z27: 2029E | AA27: 2018 | AB27: 2019 | AC27: 2020 | AD27: 2021 | AE27: 2022 | AF27: 2023 | AG27: 2024 | AH27: 2025E | AI27: 2026E | AJ27: 2027E | AK27: 2028E | AL27: 2029E | AO27: Outstanding Shares | AP27: 577.67 | AS27: 0
U28: Total Revenue | V28: =N5 -> 19343.009 | W28: =O5 -> 20271.474 | X28: =P5 -> 21244.505 | Y28: =Q5 -> 22264.241 | Z28: =R5 -> 23332.924 | AA28: =F5 -> 14594.43 | AB28: =G5 -> 14636.99 | AC28: =H5 -> 14467.75 | AD28: =I5 -> 13953.47 | AE28: =J5 -> 16216.93 | AF28: =K5 -> 17365.64 | AG28: =L5 -> 18457.07 | AO28: TVE | AP28: =AP26*AP27 -> 26538.16 | AR28: TVP | AS28: =AS26*AS27 -> 0 | AU28: TVD | AV28: =AV26 -> 27470
U29: Revenue growth | V29: =(N5-L5)/L5 -> 0.048 | W29: =(W28-V28)/V28 -> 0.048 | X29: =(X28-W28)/W28 -> 0.048 | Y29: =(Y28-X28)/X28 -> 0.048 | Z29: =(Z28-Y28)/Y28 -> 0.048 | AO29: Total Market Value | AQ29: =AP28+AV28 -> 54008.16
U30: Total Expenses of Operating | V30: =AH12 -> 15537.483 | W30: =AI12 -> 15868.46 | X30: =AJ12 -> 16229.216 | Y30: =AK12 -> 16461.178 | Z30: =AL12 -> 16843.005 | AA30: =Z12 -> 11351.79 | AB30: =AA12 -> 11307.69 | AC30: =AB12 -> 11568.84 | AD30: =AC12 -> 11926.64 | AE30: =AD12 -> 13730.82 | AF30: =AE12 -> 14308.09 | AG30: =AF12 -> 15203.25 | AO30: Cost of Equity | AQ30: =DDM!F18 -> 0.0692475
U31: Depreciation and amortization | V31: =AH6 -> 2287.4412 | W31: =AI6 -> 2415.669 | X31: =AJ6 -> 2551.0848 | Y31: =AK6 -> 2551.0848 | Z31: =AL6 -> 2694.0918 | AA31: =Z6 -> 1472.27 | AB31: =AA6 -> 1618.23 | AC31: =AB6 -> 1708.24 | AD31: =AC6 -> 1632 | AE31: =AD6 -> 1789.73 | AF31: =AE6 -> 1971.34 | AG31: =AF6 -> 2166.02 | AO31: Cost of Debt | AQ31: =AQ32/AQ33*(1-AQ34) -> 0.036886333
U32: EBITDA | V32: =V34+V31 -> 3805.5265 | W32: =W34+W31 -> 4403.0142 | X32: =X34+X31 -> 5015.289 | Y32: =Y34+Y31 -> 5803.0626 | Z32: =Z34+Z31 -> 6489.9192 | AA32: =AA34+AA31 -> 3242.64 | AB32: =AB34+AB31 -> 3329.3 | AC32: =AC34+AC31 -> 2898.91 | ... AG32: =AG34+AG31 -> 3253.82 | AO32: Interest Expenses | AQ32: ='Income Statement'!B47 -> 1352.22
U33: EBITDA Margin | V33: =V32/V28 -> 0.19673911 | W33: =W32/W28 -> 0.21720247 | X33: =X32/X28 -> 0.23607465 | Y33: =Y32/Y28 -> 0.26064498 | Z33: =Z32/Z28 -> 0.27814427 | AO33: Value of Debt | AQ33: =AV28 -> 27470
U34: EBIT | V34: =V28-V30-V31 -> 1518.0853 | W34: =W28-W30-W31 -> 1987.3453 | X34: =X28-X30-X31 -> 2464.2041 | Y34: =Y28-Y30-Y31 -> 3251.9778 | Z34: =Z28-Z30-Z31 -> 3795.8275 | AA34: =AA28-AA30-AA31 -> 1770.37 | AB34: =AB28-AB30-AB31 -> 1711.07 | AC34: =AC28-AC30-AC31 -> 1190.67 | ... AG34: =AG28-AG30-AG31 -> 1087.8 | AO34: Effective Tax Rate | AQ34: =AQ35/AQ36 -> 0.25066366
U35: EBIT Margin | V35: =V34/V28 -> 0.078482374 | W35: =W34/W28 -> 0.098036545 | X35: =X34/X28 -> 0.11599254 | Y35: =Y34/Y28 -> 0.14606282 | Z35: =Z34/Z28 -> 0.16268117 | AO35: Tax Expense | AQ35: ='Income Statement'!B69 -> 516.5
U36: Effective Tax Rate | V36: =AQ34 -> 0.25066366 | W36: =V36 -> 0.25066366 | X36: =W36 -> 0.25066366 | Y36: =X36 -> 0.25066366 | Z36: =Y36 -> 0.25066366 | AO36: Pre-Tax Income | AQ36: ='Income Statement'!B67 -> 2060.53
B37: 2015 | C37: 2016 | D37: 2017 | E37: 2018 | F37: 2019 | G37: 2020 | H37: 2021 | I37: 2022 | J37: 2023 | K37: 2024 | L37: 2025E | M37: 2026E | N37: 2027E | O37: 2028E | P37: 2029E | U37: EBIT*(1-Tax Rate) | V37: =V34*(1-V36) -> 1137.5565 | W37: =W34*(1-W36) -> 1489.19 | X37: =X34*(1-X36) -> 1846.5177 | Y37: =Y34*(1-Y36) -> 2436.8251 | Z37: =Z34*(1-Z36) -> 2844.3514 | AA37: =AA34*(1-$Z$36) -> 1326.6026 | AB37: =AB34*(1-$Z$36) -> 1282.1669 | AC37: =AC34*(1-$Z$36) -> 892.21229 | AD37: =AD34*(1-$Z$36) -> 295.86047 | AE37: =AE34*(1-$Z$36) -> 521.82284 | AF37: =AF34*(1-$Z$36) -> 813.93662 | AG37: =AG34*(1-$Z$36) -> 815.12807 | AO37: Cost of Preference Shares | AQ37: 0
B38: 19211.55 | C38: 14175.82 | D38: 14179.85 | E38: 14594.43 | F38: 14636.99 | G38: 14467.75 | H38: 13953.47 | I38: 16216.93 | J38: 17365.64 | K38: 18457.07 | L38: 19343 | M38: 20271 | N38: 21244 | O38: 22264 | P38: 23332 | U38: (Plus)D&A | V38: =V31 -> 2287.4412 | W38: =W31 -> 2415.669 | X38: =X31 -> 2551.0848 | Y38: =Y31 -> 2551.0848 | Z38: =Z31 -> 2694.0918 | AA38: =AA31 -> 1472.27 | AB38: =AB31 -> 1618.23 | AC38: =AC31 -> 1708.24 | ... AG38: =AG31 -> 2166.02 | AO38: DPS for PS
U39: (less)changes in working capital | V39: =C20 -> 193.43009 | W39: =C21 -> 202.71474 | X39: =C22 -> 212.44505 | Y39: =C23 -> 222.64241 | Z39: =C24 -> 233.32924 | AA39: =D12 -> -471.19 | AB39: =D13 -> -295.41 | AC39: =D14 -> -1719.37 | AD39: =D15 -> -842.65 | AE39: =D16 -> -30.16 | AF39: =D17 -> 440.5 | AG39: =D18 -> 649.1
U40: (less)Capex | V40: =BA4 -> 2760.615 | W40: =BB4 -> 2857.2365 | X40: =BC4 -> 2957.2398 | Y40: =BD4 -> 3060.7432 | Z40: =BE4 -> 3167.8692 | AA40: =AS4 -> 3466.84 | AB40: =AT4 -> 3534.9 | AC40: =AU4 -> 3562.63 | AD40: =AV4 -> 3064.7 | AE40: =AW4 -> 3587.27 | AF40: =AX4 -> 4528.29 | AG40: =AY4 -> 5521.23
U41: Unlevered Free cash flow of firm | V41: =V37+V38-V39-V40 -> 470.95259 | W41: =W37+W38-W39-W40 -> 844.90773 | X41: =X37+X38-X39-X40 -> 1227.9177 | Y41: =Y37+Y38-Y39-Y40 -> 1704.5244 | Z41: =Z37+Z38-Z39-Z40 -> 2137.2447 | AA41: 2018 | AB41: 2019 | AC41: 2020 | AD41: 2021 | AE41: 2022 | AF41: 2023 | AG41: 2024 | AO41: WACC | AP41: =(AP28/AQ29 * AQ30) + (AS28/AQ29 * AQ37) + (AV28/AQ29 * AQ31) -> 0.052787742
AA42: -1639.46 | AB42: -262.63 | AC42: -1654.61 | AD42: 458.76 | AE42: -95.02 | AF42: -2656.79 | AG42: -1560.47 | AO42: Tax Rate | AP42: =AQ34 -> 0.25066366
AO43: After-tax cost of debt | AP43: =AQ31 -> 0.036886333
U44: Current WACC | V44: =AP49 -> 0.052787742 | AO44: Cost of Equity | AP44: =AQ30 -> 0.0692475
U45: Present value (5-year CF) | V45: =V41/(1+V44)+W41/(1+V44)^2+X41/(1+V44)^3+Y41/(1+V44)^4+Z41/(1+V44)^5 -> 5302.0144 | AO45: Net debt | AP45: =AQ33 -> 27470
AO46: Value of Preference Shares | AP46: =AS28 -> 0
U47: Share price calculation | AO47: Market value of equity | AP47: =AP28 -> 26538.16
U48: Perpetual growth rate | V48: 0.025 | AO48: Enterprise value | AP48: =AQ29 -> 54008.16
U49: Terminal Value | V49: =Z41*(1+V48)/(V44-V48) -> 78836.052 | AO49: WACC | AP49: =AP41 -> 0.052787742
U50: Implied EV/EBITDA | V50: =V49/Z32 -> 12.147463
U51: Present value of terminal value | V51: =V49/(1+V44)^5 -> 60956.605
U52: Present value (5-year CF) | V52: =V45 -> 5302.0144
U53: Enterprise Value | V53: =V52+V51 -> 66258.619
U54: Total debt | V54: =AV28 -> 27470
U55: Cash | V55: ='Balance Sheet'!B22 -> 159.62
U56: Net Debt/ Net Cash | V56: =V54-V55 -> 27310.38
U57: Minority interest | V57: 0
U58: Equity Value | V58: =V53-V56-V57 -> 38948.239
U59: Number of share outstanding | V59: =AP27 -> 577.67
U60: indicated per share price (CAD) | V60: =V58/V59 -> 67.422991

Sheet DDM
A1: Year | B1: Total Dividends | C1: Growth Rate | E1: Growth Rate | H1: Dividend at end of 2025 | I1: =B15 -> 1.78 | J1: =B14*(1+$C$17) -> 1.760825 | K1: =1/(1+$F$18)^1 -> 0.93523716 | L1: =J1*K1 -> 1.646789 | M1: 2025
A2: 2025(Est) | B2: =J1 -> 1.760825 | C2: =POWER((B15/B5),1/10)-1 -> 0.021423278 | E2: Stage 1 growth rate (2025–2029) | F2: =D9 -> 0.026666526 | H2: Dividend at end of 2026 | I2: =I1*(1+F2) -> 1.8274664 | J2: =J1*(1+$C$17) -> 1.8400621 | K2: =1/(1+$F$18)^2 -> 0.87466855 | L2: =J2*K2 -> 1.6094445 | M2: 2026
A3: year | B3: Dividend | E3: Stage 2 growth rate (beyond 2029) | F3: 0.025 | H3: Dividend at end of 2027 | I3: =I2*(1+F2) -> 1.8761986 | J3: =J2*(1+$C$17) -> 1.9228649 | K3: =1/(1+$F$18)^3 -> 0.81802254 | L3: =J3*K3 -> 1.5729468 | M3: 2027
A4: 2014 | B4: 1.44 | H4: Dividend at end of 2028 | I4: =I3*(1+F2) -> 1.9262303 | J4: =J3*(1+$C$17) -> 2.0093938 | K4: =1/(1+$F$18)^4 -> 0.76504508 | L4: =J4*K4 -> 1.5372769 | M4: 2028
A5: 2015 | B5: 1.44 | C5: =(B5-B4)/B4 -> 0 | H5: Dividend at end of 2029 | I5: =I4*(1+F2) -> 1.9775962 | J5: =J4*(1+$C$17) -> 2.0998166 | K5: =1/(1+$F$18)^5 -> 0.71549859 | L5: =J5*K5 -> 1.5024158 | M5: 2029
A6: 2016 | B6: 1.44 | C6: =(B6-B5)/B5 -> 0 | E6: Risk-free Rate | H6: Terminal Value (TV) at Year 2028
A7: 2017 | B7: 1.44 | C7: =(B7-B6)/B6 -> 0 | E7: 10 YEAR CAD BOND | F7: 0.0336 | H7: D2029/(Re-g2) | I7: =I5/(F18-F3) -> 44.693964 | J7: =J5*(1+F3)/(F18-F3) -> 48.642567 | K7: =1/(1+$F$18)^5 -> 0.71549859 | L7: =J7*K7 -> 34.803688
A8: 2018 | B8: 1.44 | C8: =(B8-B7)/B7 -> 0 | H8: Price 2025 | I8: =NPV(F18,I1,I2,I3,I4+I7) -> 40.464472 | J8: =NPV(F18,J1,J2,J3,J4+J7) -> 43.580214 | L8: =SUM(L1:L7) -> 42.672561
A9: 2019 | B9: 1.52 | C9: =(B9-B8)/B8 -> 0.055555556 | D9: =POWER((B15/B9),1/6)-1 -> 0.026666526 | E9: Market Return : Rm
A10: 2020 | B10: 1.56 | C10: =(B10-B9)/B9 -> 0.026315789 | E10: 30 Year Annualized S&P 500 Return (Dividends Reinvested) | F10: 0.1092
A11: 2021 | B11: 1.56 | C11: =(B11-B10)/B10 -> 0 | E11: 20 Year Annualized S&P 500 Return (Dividends Reinvested) | F11: 0.1035
A12: 2022 | B12: 1.56 | C12: =(B12-B11)/B11 -> 0 | E12: Rm average | F12: =AVERAGE(F10:F11) -> 0.10635
A13: 2023 | B13: 1.58 | C13: =(B13-B12)/B12 -> 0.012820513
A14: 2024 | B14: 1.685 | C14: =(B14-B13)/B13 -> 0.066455696 | E14: Beta
A15: 2025 | B15: 1.78 | C15: =(B15-B14)/B14 -> 0.056379822 | E15: 0.49
C16: =(D9+C2)/2 -> 0.024044902
C17: 0.045 | E17: Discount Raate
E18: CAPM : Re = Rf + B (Rm-Rf) | F18: =F7+E15*(F12-F7) -> 0.0692475

Sheet CCA
A1: Company Name | C1: EV / EBITDA | D1: Price / EPS | E1: Price / Cash Flow Per Share
A2: FirstEnergy Corp | C2: 10.94 | D2: 16.96 | E2: 7.87
A3: American Electric Power Company Inc | C3: 11.6 | D3: 19.26 | E3: 9.55
A4: Nextera Energy Inc | C4: 14.87 | D4: 21.13 | E4: 11.41
A5: Southern Co | C5: 12.18 | D5: 19.84 | E5: 9.48
A6: Duke Energy Corp | C6: 11.34 | D6: 18.3 | E6: 8.2
A7: Public Service Enterprise Group Inc | C7: 13.08 | D7: 18.81 | E7: 10.8
A8: Dominion Energy Inc | C8: 12.56 | D8: 16.87 | E8: 9.27
A10: Average | C10: =AVERAGE(C3:C8) -> 12.605 | D10: =AVERAGE(D3:D8) -> 19.035 | E10: =AVERAGE(E3:E8) -> 9.785
C11: =C10*B16 -> 68438.091 | D11: =D10*B17 -> 44.1612 | E11: =E10*B20 -> 67.21477
C12: =C11-34385-1819+159.6 -> 32393.691
C13: =C12/576.6 -> 56.180526
C14: =C13*0.5+D11*0.3+E11*0.2 -> 54.781577
B15: 30-12-2024 | C15: 30-12-2023 | D15: 30-12-2022 | E15: 30-12-2021 | F15: 30-12-2020 | G15: 30-12-2019 | H15: 30-12-2018 | I15: 30-12-2017 | J15: 30-12-2016 | K15: 30-12-2015
A16: Earnings before Interest, Taxes, Depreciation & Amortization (EBITDA) | B16: 5429.44 | C16: 5028.88 | D16: 4275.83 | E16: 4033.62 | F16: 4607.15 | G16: 4947.53 | H16: 4725.27 | I16: 4536.31 | J16: 4014.28 | K16: 5726.64
A17: EPS - Diluted - including Extraordinary Items Applicable to Common - Total | B17: 2.32 | C17: 2.59 | D17: 0.92 | E17: 2.95 | F17: 2.66 | G17: 2.22 | H17: 2.57 | I17: -5.04 | J17: -19.21 | K17: 1.74
A18: Net Cash Flow from Operating Activities | B18: 3960.76 | C18: 1871.49 | D18: 3492.26 | E18: 3523.47 | F18: 1908.03 | G18: 3272.27 | H18: 1827.38 | I18: 4941.15 | J18: 4481.95 | K18: 4423.8
B19: 576.6
B20: =B18/B19 -> 6.8691641

Sheet Ratio
B1: 2024 | C1: 2023 | D1: 2022 | E1: 2021 | F1: 2020 | G1: 2019 | H1: 2018 | I1: 2017
A2: Cash Ratio | B2: ='Balance Sheet'!B23/'Balance Sheet'!B90 -> 0.022213594 | C2: ='Balance Sheet'!C23/'Balance Sheet'!C90 -> 0.025436796 | D2: ='Balance Sheet'!D23/'Balance Sheet'!D90 -> 0.040423743 | E2: ='Balance Sheet'!E23/'Balance Sheet'!E90 -> 0.33106896 | F2: ='Balance Sheet'!F23/'Balance Sheet'!F90 -> 0.34652258 | G2: ='Balance Sheet'!G23/'Balance Sheet'!G90 -> 0.12895899 | H2: ='Balance Sheet'!H23/'Balance Sheet'!H90 -> 0.079197517 | I2: ='Balance Sheet'!I23/'Balance Sheet'!I90 -> 0.14296181
A3: DE | B3: ='Balance Sheet'!B109/'Balance Sheet'!B128 -> 2.7932944 | C3: ='Balance Sheet'!C109/'Balance Sheet'!C128 -> 3.4674794 | D3: ='Balance Sheet'!D109/'Balance Sheet'!D128 -> 3.3322374 | E3: ='Balance Sheet'!E109/'Balance Sheet'!E128 -> 4.2371159 | F3: ='Balance Sheet'!F109/'Balance Sheet'!F128 -> 5.1439828 | G3: ='Balance Sheet'!G109/'Balance Sheet'!G128 -> 5.0646563 | H3: ='Balance Sheet'!H109/'Balance Sheet'!H128 -> 4.8795136 | I3: ='Balance Sheet'!I109/'Balance Sheet'!I128 -> 9.7661203 | M3: FE History Yearly 10 Years
A4: DA | B4: ='Balance Sheet'!B109/'Balance Sheet'!B72 -> 0.7363769 | C4: ='Balance Sheet'!C109/'Balance Sheet'!C72 -> 0.77616013 | D4: ='Balance Sheet'!D109/'Balance Sheet'!D72 -> 0.76917239 | E4: ='Balance Sheet'!E109/'Balance Sheet'!E72 -> 0.80905521 | F4: ='Balance Sheet'!F109/'Balance Sheet'!F72 -> 0.83723913 | G4: ='Balance Sheet'!G109/'Balance Sheet'!G72 -> 0.83511019 | H4: ='Balance Sheet'!H109/'Balance Sheet'!H72 -> 0.8299179 | I4: ='Balance Sheet'!I109/'Balance Sheet'!I72 -> 0.90711603 | M4: Exchange Date | N4: Close | Q4: 20.09 | R4: 0.1248 | S4: 0.0298 | T4: 0.0964 | U4: 7.11 | V4: 0.0849 | W4: 0.6749 | X4: 0.0486 | Y4: 5.74
M5: 46022 | N5: 47.72
A6: Price Earning Ratio | B6: =N6/B7 -> 17.071177 | C6: =N7/C7 -> 14.12712 | D6: =N7/D7 -> 39.611059 | E6: =N8/E7 -> 14.213148 | F6: =N10/F7 -> 11.467272 | G6: =N11/G7 -> 21.588701 | H6: =N12/H7 -> 14.531025 | I6: =N13/I7 -> -6.0774337 | M6: 45657 | N6: 39.78
A7: EPS | B7: ='Income Statement'!B94/'Income Statement'!B114 -> 2.3302435 | C7: ='Income Statement'!C94/'Income Statement'!C114 -> 2.5950087 | D7: ='Income Statement'!D94/'Income Statement'!D114 -> 0.92549912 | E7: ='Income Statement'!E94/'Income Statement'!E114 -> 2.950789 | F7: ='Income Statement'!F94/'Income Statement'!F114 -> 2.6693358 | G7: ='Income Statement'!G94/'Income Statement'!G114 -> 2.2511776 | H7: ='Income Statement'!H94/'Income Statement'!H114 -> 2.584126 | I7: ='Income Statement'!I94/'Income Statement'!I114 -> -5.0383108 | M7: 45291 | N7: 36.66
A8: Price to Book | B8: 1.84 | C8: 2.02 | D8: 2.36 | E8: 2.73 | F8: 2.3 | G8: 3.77 | H8: 2.85 | I8: 3.47 | M8: 44926 | N8: 41.94
A9: Dividend Yield (%) | B9: 4.27 | C9: 4.36 | D9: 3.72 | E9: 3.75 | F9: 5.1 | G9: 3.15 | H9: 4.85 | I9: 4.7 | M9: 44561 | N9: 41.59
M10: 44196 | N10: 30.61
M11: 43830 | N11: 48.6
B12: INCOME STATEMENT -COMMON SIZING | M12: 43465 | N12: 37.55
M13: 43100 | N13: 30.62
A14: Cost of Sales | B14: ='Income Statement'!B29/'Income Statement'!B26 -> 0.44217636 | C14: ='Income Statement'!C29/'Income Statement'!C26 -> 0.47451404 | D14: ='Income Statement'!D29/'Income Statement'!D26 -> 0.47901113 | E14: ='Income Statement'!E29/'Income Statement'!E26 -> 0.42642869 | F14: ='Income Statement'!F29/'Income Statement'!F26 -> 0.40259474 | G14: ='Income Statement'!G29/'Income Statement'!G26 -> 0.42084267 | H14: ='Income Statement'!H29/'Income Statement'!H26 -> 0.42474012 | I14: ='Income Statement'!I29/'Income Statement'!I26 -> 0.40721094 | M14: 42735 | N14: 30.97 | R14: 2024 | S14: 2023 | T14: 2022 | U14: 2021 | V14: 2020 | W14: 2019 | X14: 2018 | Y14: 2017 | AD14: 2024 | AE14: 2023 | AF14: 2022 | AG14: 2021 | AH14: 2020 | AI14: 2019 | AJ14: 2018 | AK14: 2017
A15: Gross Profit | B15: ='Income Statement'!B34/'Income Statement'!B26 -> 0.55782364 | C15: ='Income Statement'!C34/'Income Statement'!C26 -> 0.52548538 | D15: ='Income Statement'!D34/'Income Statement'!D26 -> 0.52098887 | E15: ='Income Statement'!E34/'Income Statement'!E26 -> 0.57357202 | F15: ='Income Statement'!F34/'Income Statement'!F26 -> 0.59740526 | G15: ='Income Statement'!G34/'Income Statement'!G26 -> 0.57915733 | H15: ='Income Statement'!H34/'Income Statement'!H26 -> 0.57525988 | I15: ='Income Statement'!I34/'Income Statement'!I26 -> 0.59278906 | M15: 42369 | N15: 31.73 | Q15: Net Margin - % | R15: 0.23 | S15: 0.223 | T15: 0.155 | U15: 0.166 | V15: 0.139 | W15: 0.189 | X15: 0.327 | Y15: 0.206 | AB15: Net Margin - % | AC15: IND | AD15: 0.152 | AE15: 0.15 | AF15: 0.117 | AG15: 0.148 | AH15: 0.139 | AI15: 0.143 | AJ15: 0.119 | AK15: 0.123
A16: Total Expenses | B16: ='Income Statement'!B42/'Income Statement'!B26 -> 0.82370821 | C16: ='Income Statement'!C42/'Income Statement'!C26 -> 0.82393163 | D16: ='Income Statement'!D42/'Income Statement'!D26 -> 0.84669725 | E16: ='Income Statement'!E42/'Income Statement'!E26 -> 0.85474366 | F16: ='Income Statement'!F42/'Income Statement'!F26 -> 0.79962952 | G16: ='Income Statement'!G42/'Income Statement'!G26 -> 0.77254203 | H16: ='Income Statement'!H42/'Income Statement'!H26 -> 0.77781729 | I16: ='Income Statement'!I42/'Income Statement'!I26 -> 0.77406672 | Q16: Return on Average Total Assets | R16: 0.031 | S16: 0.037 | T16: 0.022 | U16: 0.021 | V16: 0.02 | W16: 0.031 | X16: 0.053 | Y16: 0.037 | AC16: FE | AD16: 0.084 | AE16: 0.093 | AF16: 0.035 | AG16: 0.111 | AH16: 0.093 | AI16: 0.082 | AJ16: 0.093 | AK16: 0.083
A17: Interest Expenses | B17: ='Income Statement'!B47/'Income Statement'!B26 -> 0.073262983 | C17: ='Income Statement'!C47/'Income Statement'!C26 -> 0.079797808 | D17: ='Income Statement'!D47/'Income Statement'!D26 -> 0.076651376 | E17: ='Income Statement'!E47/'Income Statement'!E26 -> 0.095759693 | F17: ='Income Statement'!F47/'Income Statement'!F26 -> 0.091566415 | G17: ='Income Statement'!G47/'Income Statement'!G26 -> 0.087177077 | H17: ='Income Statement'!H47/'Income Statement'!H26 -> 0.093330812 | I17: ='Income Statement'!I47/'Income Statement'!I26 -> 0.087206846 | Q17: Total Debt Percentage of Total Equity | R17: 1.677 | S17: 1.705 | T17: 1.693 | U17: 1.609 | V17: 1.625 | W17: 1.492 | X17: 1.318 | Y17: 1.245 | AB17: Return on Average Total Assets | AC17: IND | AD17: 0.03 | AE17: 0.024 | AF17: 0.022 | AG17: 0.02 | AH17: 0.02 | AI17: 0.027 | AJ17: 0.028 | AK17: 0.03
A18: Operating Profit | B18: ='Income Statement'!B44/'Income Statement'!B26 -> 0.17629179 | C18: ='Income Statement'!C44/'Income Statement'!C26 -> 0.17606837 | D18: ='Income Statement'!D44/'Income Statement'!D26 -> 0.15330275 | E18: ='Income Statement'!E44/'Income Statement'!E26 -> 0.14525706 | F18: ='Income Statement'!F44/'Income Statement'!F26 -> 0.20037048 | G18: ='Income Statement'!G44/'Income Statement'!G26 -> 0.22745797 | H18: ='Income Statement'!H44/'Income Statement'!H26 -> 0.22218271 | I18: ='Income Statement'!I44/'Income Statement'!I26 -> 0.22593328 | Q18: Asset Turnover | R18: 0.2 | S18: 0.2 | T18: 0.22 | V18: 0.19 | W18: 0.22 | X18: 0.24 | Y18: 0.24 | AC18: FE | AD18: 0.022 | AE18: 0.025 | AF18: 0.01 | AG18: 0.028 | AH18: 0.023 | AI18: 0.022 | AJ18: 0.025 | AK18: 0.021
A19: Income Tax | B19: ='Income Statement'!B69/'Income Statement'!B26 -> 0.027983857 | C19: ='Income Statement'!C69/'Income Statement'!C26 -> 0.02074614 | D19: ='Income Statement'!D69/'Income Statement'!D26 -> 0.080263034 | E19: ='Income Statement'!E69/'Income Statement'!E26 -> 0.028746255 | F19: ='Income Statement'!F69/'Income Statement'!F26 -> 0.011677697 | G19: ='Income Statement'!G69/'Income Statement'!G26 -> 0.019302466 | H19: ='Income Statement'!H69/'Income Statement'!H26 -> 0.041381541 | I19: ='Income Statement'!I69/'Income Statement'!I26 -> 0.047767078 | Q19: Current Ratio | R19: 0.44 | S19: 0.53 | T19: 0.51 | U19: 0.63 | V19: 0.44 | W19: 0.4 | X19: 0.48 | Y19: 0.51 | AB19: Total Debt Percentage of Total Equity | AC19: IND | AD19: 1.677 | AE19: 1.705 | AF19: 1.619 | AG19: 1.403 | AH19: 1.399 | AI19: 1.278 | AJ19: 1.318 | AK19: 1.245
A20: Net Income | B20: ='Income Statement'!B94/'Income Statement'!B26 -> 0.072594946 | C20: ='Income Statement'!C94/'Income Statement'!C26 -> 0.085625407 | D20: ='Income Statement'!D94/'Income Statement'!D26 -> 0.032586932 | E20: ='Income Statement'!E94/'Income Statement'!E26 -> 0.11525305 | F20: ='Income Statement'!F94/'Income Statement'!F26 -> 0.10000035 | G20: ='Income Statement'!G94/'Income Statement'!G26 -> 0.082283311 | H20: ='Income Statement'!H94/'Income Statement'!H26 -> 0.087114742 | I20: ='Income Statement'!I94/'Income Statement'!I26 -> -0.15775978 | Q20: Quick Ratio | R20: 0.31 | S20: 0.36 | T20: 0.41 | U20: 0.55 | V20: 0.31 | W20: 0.28 | X20: 0.37 | Y20: 0.4 | AC20: FE | AD20: 1.751 | AE20: 2.282 | AF20: 2.035 | AG20: 2.75 | AH20: 3.382 | AI20: 3.011 | AJ20: 2.862 | AK20: 4.98
Q21: Accounts Receivable Turnover | R21: 7.48 | S21: 7.07 | T21: 8.13 | V21: 7.99 | W21: 8.57 | X21: 8.48 | Y21: 8.1 | AB21: Current Ratio | AC21: IND | AD21: 0.67 | AE21: 0.74 | AF21: 0.66 | AG21: 0.82 | AH21: 0.66 | AI21: 0.64 | AJ21: 0.67 | AK21: 0.74
Q22: Payables Turnover | R22: 5.86 | S22: 5.85 | T22: 6.11 | V22: 5.6 | W22: 5.85 | X22: 6.24 | Y22: 5.85 | AC22: FE | AD22: 0.56 | AE22: 0.48 | AF22: 0.61 | AG22: 0.73 | AH22: 0.74 | AI22: 0.5 | AJ22: 0.52 | AK22: 0.76
B23: BALANCE SHEET -COMMON SIZING | AB23: Quick Ratio | AC23: IND | AD23: 0.46 | AE23: 0.49 | AF23: 0.5 | AG23: 0.58 | AH23: 0.5 | AI23: 0.46 | AJ23: 0.5 | AK23: 0.55
AC24: FE | AD24: 0.45 | AE24: 0.38 | AF24: 0.5 | AG24: 0.67 | AH24: 0.68 | AI24: 0.44 | AJ24: 0.46 | AK24: 0.7
A25: Cash & Cash Equivalent | B25: ='Balance Sheet'!B23/'Balance Sheet'!B72 -> 0.0021328375 | C25: ='Balance Sheet'!C23/'Balance Sheet'!C72 -> 0.002809331 | D25: ='Balance Sheet'!D23/'Balance Sheet'!D72 -> 0.0034700496 | E25: ='Balance Sheet'!E23/'Balance Sheet'!E72 -> 0.032179947 | F25: ='Balance Sheet'!F23/'Balance Sheet'!F72 -> 0.038997807 | G25: ='Balance Sheet'!G23/'Balance Sheet'!G72 -> 0.014822304 | H25: ='Balance Sheet'!H23/'Balance Sheet'!H72 -> 0.0091606111 | I25: ='Balance Sheet'!I23/'Balance Sheet'!I72 -> 0.013914899 | Q25: Net Margin - % | R25: 0.159 | S25: 0.152 | T25: 0.117 | U25: 0.1 | V25: 0.152 | W25: 0.222 | X25: 0.097 | Y25: 0.029 | AB25: Accounts Receivable Turnover | AC25: IND | AD25: 6.47 | AE25: 6.28 | AF25: 5.47 | AG25: 4.5 | AH25: 5.86 | AI25: 5.77 | AJ25: 6.19 | AK25: 6.14
A26: Receivables | B26: ='Balance Sheet'!B25/'Balance Sheet'!B72 -> 0.035220146 | C26: ='Balance Sheet'!C25/'Balance Sheet'!C72 -> 0.032481013 | D26: ='Balance Sheet'!D25/'Balance Sheet'!D72 -> 0.034072212 | E26: ='Balance Sheet'!E25/'Balance Sheet'!E72 -> 0.028151987 | F26: ='Balance Sheet'!F25/'Balance Sheet'!F72 -> 0.032363314 | G26: ='Balance Sheet'!G25/'Balance Sheet'!G72 -> 0.030590322 | H26: ='Balance Sheet'!H25/'Balance Sheet'!H72 -> 0.037715587 | I26: ='Balance Sheet'!I25/'Balance Sheet'!I72 -> 0.034361163 | Q26: Return on Average Total Assets | R26: 0.03 | S26: 0.028 | T26: 0.026 | U26: 0.018 | V26: 0.026 | W26: 0.04 | X26: 0.02 | Y26: 0.006 | AC26: FE | AD26: 7.89 | AE26: 8.16 | AF26: 8.74 | AG26: 8.19 | AH26: 7.9 | AI26: 7.87 | AJ26: 7.6 | AK26: 7.13
A27: Inventory | B27: ='Balance Sheet'!B30/'Balance Sheet'!B72 -> 0.01054874 | C27: ='Balance Sheet'!C30/'Balance Sheet'!C72 -> 0.010498841 | D27: ='Balance Sheet'!D30/'Balance Sheet'!D72 -> 0.00913069 | E27: ='Balance Sheet'!E30/'Balance Sheet'!E72 -> 0.0057227687 | F27: ='Balance Sheet'!F30/'Balance Sheet'!F72 -> 0.0071293457 | G27: ='Balance Sheet'!G30/'Balance Sheet'!G72 -> 0.0066429307 | H27: ='Balance Sheet'!H30/'Balance Sheet'!H72 -> 0.0062900495 | I27: ='Balance Sheet'!I30/'Balance Sheet'!I72 -> 0.0055849261 | Q27: Total Debt Percentage of Total Equity | R27: 1.768 | S27: 1.76 | T27: 1.667 | U27: 1.649 | V27: 1.512 | W27: 1.462 | X27: 1.597 | Y27: 1.965 | AB27: Payables Turnover | AC27: IND | AD27: 5.9 | AE27: 5.63 | AF27: 6.11 | AG27: 5.565 | AH27: 5.22 | AI27: 5.85 | AJ27: 6.24 | AK27: 5.85
A28: Current Assets | B28: ='Balance Sheet'!B37/'Balance Sheet'!B72 -> 0.05333951 | C28: ='Balance Sheet'!C37/'Balance Sheet'!C72 -> 0.052658623 | D28: ='Balance Sheet'!D37/'Balance Sheet'!D72 -> 0.052376971 | E28: ='Balance Sheet'!E37/'Balance Sheet'!E72 -> 0.071249411 | F28: ='Balance Sheet'!F37/'Balance Sheet'!F72 -> 0.083528215 | G28: ='Balance Sheet'!G37/'Balance Sheet'!G72 -> 0.05777644 | H28: ='Balance Sheet'!H37/'Balance Sheet'!H72 -> 0.059705959 | I28: ='Balance Sheet'!I37/'Balance Sheet'!I72 -> 0.073597329 | Q28: Asset Turnover | R28: 0.19 | S28: 0.18 | T28: 0.22 | U28: 0.18 | V28: 0.17 | W28: 0.18 | X28: 0.21 | Y28: 0.21 | AC28: FE | AD28: 4.06 | AE28: 4.26 | AF28: 4.88 | AG28: 5.36 | AH28: 4.74 | AI28: 4.71 | AJ28: 5.34 | AK28: 4.76
A29: Account Payables | B29: ='Balance Sheet'!B75/'Balance Sheet'!B72 -> 0.030262855 | C29: ='Balance Sheet'!C75/'Balance Sheet'!C72 -> 0.027928738 | D29: ='Balance Sheet'!D75/'Balance Sheet'!D72 -> 0.032597304 | E29: ='Balance Sheet'!E75/'Balance Sheet'!E72 -> 0.020756361 | F29: ='Balance Sheet'!F75/'Balance Sheet'!F72 -> 0.018599299 | G29: ='Balance Sheet'!G75/'Balance Sheet'!G72 -> 0.023758248 | H29: ='Balance Sheet'!H75/'Balance Sheet'!H72 -> 0.024087055 | I29: ='Balance Sheet'!I75/'Balance Sheet'!I72 -> 0.019570761 | Q29: Current Ratio | R29: 0.67 | S29: 0.77 | T29: 0.66 | U29: 0.82 | V29: 0.71 | W29: 0.78 | X29: 0.67 | Y29: 0.74
A30: Non-Current Liabilities | B30: ='Balance Sheet'!B107/'Balance Sheet'!B72 -> 0.64036207 | C30: ='Balance Sheet'!C107/'Balance Sheet'!C72 -> 0.66571655 | D30: ='Balance Sheet'!D107/'Balance Sheet'!D72 -> 0.68333036 | E30: ='Balance Sheet'!E107/'Balance Sheet'!E72 -> 0.71185508 | F30: ='Balance Sheet'!F107/'Balance Sheet'!F72 -> 0.72469868 | G30: ='Balance Sheet'!G107/'Balance Sheet'!G72 -> 0.72017207 | H30: ='Balance Sheet'!H107/'Balance Sheet'!H72 -> 0.71425018 | I30: ='Balance Sheet'!I107/'Balance Sheet'!I72 -> 0.80978305 | Q30: Quick Ratio | R30: 0.46 | S30: 0.53 | T30: 0.49 | U30: 0.58 | V30: 0.51 | W30: 0.59 | X30: 0.5 | Y30: 0.55
A31: Current Liabilities | B31: ='Balance Sheet'!B90/'Balance Sheet'!B72 -> 0.096014966 | C31: ='Balance Sheet'!C90/'Balance Sheet'!C72 -> 0.11044359 | D31: ='Balance Sheet'!D90/'Balance Sheet'!D72 -> 0.085841868 | E31: ='Balance Sheet'!E90/'Balance Sheet'!E72 -> 0.097200133 | F31: ='Balance Sheet'!F90/'Balance Sheet'!F72 -> 0.11254045 | G31: ='Balance Sheet'!G90/'Balance Sheet'!G72 -> 0.11493812 | H31: ='Balance Sheet'!H90/'Balance Sheet'!H72 -> 0.11566791 | I31: ='Balance Sheet'!I90/'Balance Sheet'!I72 -> 0.097332982 | Q31: Accounts Receivable Turnover | R31: 6.48 | S31: 6.58 | T31: 8.77 | U31: 7.34 | V31: 6.04 | W31: 5.74 | X31: 5.8 | Y31: 5.88 | AB31: Years | AC31: 2024 | AD31: 2023 | AE31: 2022 | AF31: 2021 | AG31: 2020 | AH31: 2019 | AI31: 2018 | AJ31: 2017
A32: Shareholders' Equity | B32: ='Balance Sheet'!B128/'Balance Sheet'!B72 -> 0.2636231 | C32: ='Balance Sheet'!C128/'Balance Sheet'!C72 -> 0.22383987 | D32: ='Balance Sheet'!D128/'Balance Sheet'!D72 -> 0.23082761 | E32: ='Balance Sheet'!E128/'Balance Sheet'!E72 -> 0.19094479 | F32: ='Balance Sheet'!F128/'Balance Sheet'!F72 -> 0.16276087 | G32: ='Balance Sheet'!G128/'Balance Sheet'!G72 -> 0.16488981 | H32: ='Balance Sheet'!H128/'Balance Sheet'!H72 -> 0.1700821 | I32: ='Balance Sheet'!I128/'Balance Sheet'!I72 -> 0.09288397 | Q32: Payables Turnover | R32: 5.5 | S32: 5.63 | T32: 7.77 | U32: 6.68 | V32: 5.22 | W32: 4.95 | X32: 5.21 | Y32: 5.04 | AB32: Current Ratio | AC32: 0.56 | AD32: 0.48 | AE32: 0.61 | AF32: 0.73 | AG32: 0.74 | AH32: 0.5 | AI32: 0.52 | AJ32: 0.76
AB33: Quick Ratio | AC33: 0.45 | AD33: 0.38 | AE33: 0.5 | AF33: 0.67 | AG33: 0.68 | AH33: 0.44 | AI33: 0.46 | AJ33: 0.7
AB34: Cash Ratio | AC34: 0.02 | AD34: 0.03 | AE34: 0.04 | AF34: 0.33 | AG34: 0.35 | AH34: 0.13 | AI34: 0.08 | AJ34: 0.14
Q35: Net Margin - % | R35: 0.151 | S35: 0.117 | T35: 0.117 | U35: 0.148 | V35: 0.144 | W35: 0.123 | X35: 0.119 | Y35: 0.123
Q36: Return on Average Total Assets | R36: 0.03 | S36: 0.023 | T36: 0.026 | V36: 0.027 | W36: 0.027 | X36: 0.029 | Y36: 0.03
Q37: Total Debt Percentage of Total Equity | R37: 1.677 | S37: 1.705 | T37: 1.693 | U37: 1.609 | V37: 1.625 | W37: 1.492 | X37: 1.318 | Y37: 1.245
Q38: Asset Turnover | R38: 0.2 | S38: 0.2 | T38: 0.22 | V38: 0.19 | W38: 0.22 | X38: 0.24 | Y38: 0.24 | AB38: Years | AC38: 2024 | AD38: 2023 | AE38: 2022 | AF38: 2021 | AG38: 2020 | AH38: 2019 | AI38: 2018 | AJ38: 2017
Q39: Current Ratio | R39: 0.44 | S39: 0.53 | T39: 0.51 | U39: 0.63 | V39: 0.44 | W39: 0.4 | X39: 0.48 | Y39: 0.51 | AB39: AR Turnover | AC39: 7.89 | AD39: 8.16 | AE39: 8.74 | AF39: 8.19 | AG39: 7.9 | AH39: 7.87 | AI39: 7.6 | AJ39: 7.13
Q40: Quick Ratio | R40: 0.31 | S40: 0.36 | T40: 0.41 | U40: 0.55 | V40: 0.31 | W40: 0.28 | X40: 0.37 | Y40: 0.4 | AB40: AR Collection Days | AC40: 46.42 | AD40: 44.86 | AE40: 41.86 | AF40: 44.68 | AG40: 46.35 | AH40: 46.52 | AI40: 48.15 | AJ40: 51.36
Q41: Accounts Receivable Turnover | R41: 6.47 | S41: 6.28 | T41: 4.32 | U41: 3.57 | V41: 3 | W41: 5.55 | X41: 6.19 | Y41: 6.14 | AB41: Payables Turnover | AC41: 4.06 | AD41: 4.26 | AE41: 4.88 | AF41: 5.36 | AG41: 4.74 | AH41: 4.71 | AI41: 5.34 | AJ41: 4.76
Q42: Payables Turnover | R42: 5.9 | S42: 5.24 | T42: 3.81 | U42: 3.49 | V42: 3.58 | W42: 7.57 | X42: 8.15 | Y42: 7.86 | AB42: Average Payables Payment Days | AC42: 90.23 | AD42: 85.85 | AE42: 75 | AF42: 68.23 | AG42: 77.18 | AH42: 77.63 | AI42: 68.56 | AJ42: 76.9
AB43: Inventory Turnover | AC43: 11.23 | AD43: 13.09 | AE43: 17.53 | AF43: 16.45 | AG43: 14.53 | AH43: 17.43 | AI43: 19.6 | AJ43: 11.13
Q44: Net Margin - % | R44: 0.152 | S44: 0.149 | T44: 0.131 | U44: 0.151 | V44: 0.047 | W44: 0.143 | X44: 0.108 | Y44: 0.126 | AB44: Average Inventory Days | AC44: 32.59 | AD44: 27.96 | AE44: 20.88 | AF44: 22.24 | AG44: 25.19 | AH44: 21 | AI44: 18.67 | AJ44: 32.9
Q45: Return on Average Total Assets | R45: 0.025 | S45: 0.024 | T45: 0.022 | U45: 0.022 | V45: 0.007 | W45: 0.024 | X45: 0.019 | Y45: 0.022 | AB45: Source: Refinitiv
Q46: Total Debt Percentage of Total Equity | R46: 1.644 | S46: 1.585 | T46: 1.421 | U46: 1.313 | V46: 1.276 | W46: 1.278 | X46: 1.322 | Y46: 1.304
Q47: Asset Turnover | R47: 0.17 | S47: 0.16 | T47: 0.17 | U47: 0.15 | V47: 0.15 | W47: 0.16 | X47: 0.17 | Y47: 0.17 | AB47: Years | AC47: 2024 | AD47: 2023 | AE47: 2022 | AF47: 2021 | AG47: 2020 | AH47: 2019 | AI47: 2018 | AJ47: 2017
Q48: Current Ratio | R48: 0.67 | S48: 0.74 | T48: 0.7 | U48: 0.62 | V48: 0.53 | W48: 0.62 | X48: 0.65 | Y48: 0.68 | AB48: AR Turnover | AC48: 7.89 | AD48: 8.16 | AE48: 8.74 | AF48: 8.19 | AG48: 7.9 | AH48: 7.87 | AI48: 7.6 | AJ48: 7.13
Q49: Quick Ratio | R49: 0.44 | S49: 0.49 | T49: 0.51 | U49: 0.42 | V49: 0.34 | W49: 0.4 | X49: 0.44 | Y49: 0.42 | AB49: AR Collection Days | AC49: 46.42 | AD49: 44.86 | AE49: 41.86 | AF49: 44.68 | AG49: 46.35 | AH49: 46.52 | AI49: 48.15 | AJ49: 51.36
Q50: Accounts Receivable Turnover | R50: 6.9 | S50: 6.8 | T50: 7.17 | U50: 7.28 | V50: 7.52 | W50: 8.1 | X50: 8.3 | Y50: 8.7 | AB50: Payables Turnover | AC50: 4.06 | AD50: 4.26 | AE50: 4.88 | AF50: 5.36 | AG50: 4.74 | AH50: 4.71 | AI50: 5.34 | AJ50: 4.76
Q51: Payables Turnover | R51: 4.32 | S51: 4.57 | T51: 4.98 | U51: 5.15 | V51: 4.98 | W51: 5.18 | X51: 5.53 | Y51: 5.45 | AB51: Average Payables Payment Days | AC51: 90.23 | AD51: 85.85 | AE51: 75 | AF51: 68.23 | AG51: 77.18 | AH51: 77.63 | AI51: 68.56 | AJ51: 76.9
AB52: Inventory Turnover | AC52: 11.23 | AD52: 13.09 | AE52: 17.53 | AF52: 16.45 | AG52: 14.53 | AH52: 17.43 | AI52: 19.6 | AJ52: 11.13
AB53: Average Inventory Days | AC53: 32.59 | AD53: 27.96 | AE53: 20.88 | AF53: 22.24 | AG53: 25.19 | AH53: 21 | AI53: 18.67 | AJ53: 32.9
Q54: Net Margin - % | R54: 0.172 | S54: 0.228 | T54: 0.105 | U54: -0.067 | V54: 0.198 | W54: 0.168 | X54: 0.148 | Y54: 0.091
Q55: Return on Average Total Assets | R55: 0.034 | S55: 0.052 | T55: 0.021 | U55: -0.013 | V55: 0.039 | W55: 0.036 | X55: 0.033 | Y55: 0.02
Q56: Total Debt Percentage of Total Equity | R56: 1.409 | S56: 1.307 | T56: 1.476 | U56: 1.346 | V56: 1.079 | W56: 1.075 | X56: 1.077 | Y56: 0.983
Q57: Asset Turnover | R57: 0.2 | S57: 0.23 | T57: 0.2 | V57: 0.2 | W57: 0.22 | X57: 0.22 | Y57: 0.22
Q58: Current Ratio | R58: 0.65 | S58: 0.67 | T58: 0.64 | U58: 0.88 | V58: 0.66 | W58: 0.64 | X58: 0.71 | Y58: 0.79
Q59: Quick Ratio | R59: 0.48 | S59: 0.46 | T59: 0.5 | U59: 0.78 | V59: 0.5 | W59: 0.46 | X59: 0.53 | Y59: 0.59
Q60: Accounts Receivable Turnover | R60: 5.09 | S60: 5.51 | T60: 4.42 | V60: 5.86 | W60: 5.77 | X60: 5.26 | Y60: 5.56
Q61: Payables Turnover | R61: 6.72 | S61: 6.06 | T61: 6.39 | U61: 5.98 | V61: 5.52 | W61: 5.5 | X61: 4.7 | Y61: 4.86
Q63: Net Margin - % | R63: 0.13 | S63: 0.15 | T63: 0.036 | U63: 0.181 | V63: 0.094 | W63: 0.046 | X63: 0.191 | Y63: 0.18
Q64: Return on Average Total Assets | R64: 0.018 | S64: 0.02 | T64: 0.005 | U64: 0.021 | V64: 0.013 | W64: 0.007 | X64: 0.028 | Y64: 0.031
Q65: Total Debt Percentage of Total Equity | R65: 1.383 | S65: 1.605 | T65: 1.495 | U65: 1.403 | V65: 1.399 | W65: 0.949 | X65: 1.595 | Y65: 1.927
Q66: Asset Turnover | R66: 0.14 | S66: 0.13 | T66: 0.14 | U66: 0.12 | V66: 0.14 | W66: 0.16 | X66: 0.14 | Y66: 0.17
Q67: Current Ratio | R67: 0.87 | S67: 0.82 | T67: 0.69 | U67: 0.87 | V67: 0.98 | W67: 0.85 | X67: 1.17 | Y67: 1.1
Q68: Quick Ratio | R68: 0.78 | S68: 0.74 | T68: 0.62 | U68: 0.75 | V68: 0.85 | W68: 0.72 | X68: 1.02 | Y68: 0.95
Q69: Accounts Receivable Turnover | R69: 5.74 | S69: 5.71 | T69: 5.47 | U69: 4.5 | V69: 5.75 | W69: 6.39 | X69: 5.79 | Y69: 7.21
Q70: Payables Turnover | R70: 9.55 | S70: 9.61 | T70: 8.48 | U70: 7.59 | V70: 9.26 | W70: 10.29 | X70: 8.76 | Y70: 8.59
Q72: Net Margin - % | R72: 0.107 | S72: 0.107 | T72: 0.108 | U72: 0.09 | V72: 0.066 | W72: 0.088 | X72: 0.058 | Y72: 0.115
Q73: Return on Average Total Assets | R73: 0.024 | S73: 0.024 | T73: 0.018 | U73: 0.012 | V73: 0.009 | W73: 0.025 | X73: 0.018 | Y73: 0.033
Q74: Total Debt Percentage of Total Equity | R74: 1.733 | S74: 1.709 | T74: 1.619 | U74: 1.219 | V74: 1.128 | W74: 1.093 | X74: 1.105 | Y74: 1.106
... Q79: Payables Turnover | R79: 5.9 | S79: 5.24 | T79: 3.81 | U79: 3.49 | V79: 3.58 | W79: 7.57 | X79: 8.15 | Y79: 7.86
R80: INDUSTRY MEDIAN
Q81: Net Margin - % | R81: 0.152 | S81: 0.15 | T81: 0.117 | U81: 0.148 | V81: 0.139 | W81: 0.143 | X81: 0.119 | Y81: 0.123
Q82: Return on Average Total Assets | R82: 0.03 | S82: 0.024 | T82: 0.022 | U82: 0.02 | V82: 0.02 | W82: 0.027 | X82: 0.028 | Y82: 0.03
Q83: Total Debt Percentage of Total Equity | R83: 1.677 | S83: 1.705 | T83: 1.619 | U83: 1.403 | V83: 1.399 | W83: 1.278 | X83: 1.318 | Y83: 1.245
Q84: Asset Turnover | R84: 0.2 | S84: 0.2 | T84: 0.2 | U84: 0.145 | V84: 0.17 | W84: 0.22 | X84: 0.22 | Y84: 0.22
Q85: Current Ratio | R85: 0.67 | S85: 0.74 | T85: 0.66 | U85: 0.82 | V85: 0.66 | W85: 0.64 | X85: 0.67 | Y85: 0.74
Q86: Quick Ratio | R86: 0.46 | S86: 0.49 | T86: 0.5 | U86: 0.58 | V86: 0.5 | W86: 0.46 | X86: 0.5 | Y86: 0.55
Q87: Accounts Receivable Turnover | R87: 6.47 | S87: 6.28 | T87: 5.47 | U87: 4.5 | V87: 5.86 | W87: 5.77 | X87: 6.19 | Y87: 6.14
Q88: Payables Turnover | R88: 5.9 | S88: 5.63 | T88: 6.11 | U88: 5.565 | V88: 5.22 | W88: 5.85 | X88: 6.24 | Y88: 5.85
