Workbook

Sheet Balance Sheet
A1: Company Fundamentals - Balance Sheet
A2: Company Name | B2: Altus Group Ltd (AIF.TO)
A3: Country of Exchange | B3: Canada
A4: Country of Headquarters | B4: Canada
A5: TRBC Industry Group | B5: Real Estate Operations
A6: CF Template | B6: IND
A7: Consolidation Basis | B7: Consolidated
A8: Scaling | B8: Millions
A9: Period | B9: Annual
A10: Export Date | B10: 46068.684
A11: Statement Data | B11: 2015 | C11: 2016 | D11: 2017 | E11: 2018 | F11: 2019 | G11: 2020 | H11: 2021 | I11: 2022 | J11: 2023 | K11: 2024
A12: Period End Date | B12: 42369 | C12: 42735 | D12: 43100 | E12: 43465 | F12: 43830 | G12: 44196 | H12: 44561 | I12: 44926 | J12: 45291 | K12: 45657
A13: Statement Date | B13: 42368 | C13: 42734 | D13: 43189 | E13: 43464 | F13: 43829 | G13: 44195 | H13: 44560 | I13: 44925 | J13: 45290 | K13: 45656
A14: Standardized Currency | B14: CAD | C14: CAD | D14: CAD | E14: CAD | F14: CAD | G14: CAD | H14: CAD | I14: CAD | J14: CAD | K14: CAD
A15: Template Type | B15: Industrial - Differentiated | C15: Industrial - Differentiated | D15: Industrial - Differentiated | E15: Industrial - Differentiated | F15: Industrial - Differentiated | G15: Industrial - Differentiated | H15: Industrial - Differentiated | I15: Industrial - Differentiated | J15: Industrial - Differentiated | K15: Industrial - Differentiated
A17: Balance Sheet - Company Specific (Currency: Canadian Dollar)
A18: Field Name | B18: 30-12-2015 | C18: 30-12-2016 | D18: 30-12-2017 | E18: 30-12-2018 | F18: 30-12-2019 | G18: 30-12-2020 | H18: 30-12-2021 | I18: 30-12-2022 | J18: 30-12-2023 | K18: 30-12-2024
A19: Cash and cash equivalents | B19: 19.6 | C19: 43.67 | D19: 28.07 | E19: 48.74 | F19: 60.26 | G19: 69.64 | H19: 51.27 | I19: 55.27 | J19: 41.89 | K19: 41.88
A20: Cash on hand | H20: 49.54 | I20: 54.77 | J20: 41.89
A21: Short-term deposits | H21: 1.74 | I21: 0.5 | J21: 0
A22: Trade receivables and other | B22: 134.5 | C22: 137.4 | D22: 143.67 | E22: 154.3 | F22: 181.96 | G22: 193.07 | H22: 223.32 | I22: 255.52 | J22: 250.46 | K22: 144.81
A23: Trade Receivable, Gross | B23: 104.11 | C23: 109.98 | D23: 108.74
A24: Allowance for Doubtful Accounts | B24: -8.14 | C24: -8.19 | D24: -7.85
A25: Contract assets: unbilled revenue on customer contracts (1) | B25: 28.71 | C25: 26.01 | D25: 32.45
A26: Prepayments | B26: 8.85 | C26: 9.26 | D26: 9.21
A27: Other receivables | B27: 1.57 | C27: 0.96 | D27: 1.11
A28: Receivables from related parties | B28: 0 | C28: 0
A29: Less non-current portion: prepayments | B29: -0.59 | C29: -0.61
A30: Income taxes recoverable | B30: 0.79 | C30: 4.53 | D30: 5.68 | E30: 6.02 | F30: 2.4 | G30: 3.39 | H30: 3.28 | I30: 7.4 | J30: 9.53 | K30: 5.1
A31: Derivative financial instruments | B31: 0.03 | C31: 0.62 | D31: 1.02 | E31: 0.48 | F31: 1.45 | G31: 2.48 | H31: 5.87 | I31: 1.69 | J31: 0.68 | K31: 8.93
A32: Assets held for sale | K32: 282.23
A33: Total current assets | B33: 154.93 | C33: 186.22 | D33: 178.44 | E33: 209.54 | F33: 246.07 | G33: 268.57 | H33: 283.73 | I33: 319.88 | J33: 302.56 | K33: 482.95
A34: Trade receivables and other | B34: 0.59 | C34: 0.61 | D34: 4.97 | E34: 8.98 | F34: 3.7 | G34: 1.37 | H34: 2.82 | I34: 6.97 | J34: 10.51 | K34: 9.62
A35: Contract assets: Unbilled revenue on customer contracts | D35: 0.37
A36: Prepayments | D36: 0.69
A37: Promissory note receivable | D37: 3.91
A38: Derivative financial instruments | B38: 0.04 | C38: 3.41 | D38: 6.03 | E38: 0.61 | F38: 5.98 | G38: 8.8 | H38: 15.66 | I38: 18.52 | J38: 8.13 | K38: 9.98
A39: Investments | B39: 17.45 | C39: 23.19 | D39: 108.07 | E39: 4.9 | F39: 11.48 | G39: 10.36 | H39: 20.81 | I39: 19.31 | J39: 14.51 | K39: 14.58
A40: Deferred tax assets | B40: 19.71 | C40: 21.96 | D40: 15.29 | E40: 19.58 | F40: 22.16 | G40: 19.93 | H40: 24.09 | I40: 28.86 | J40: 30.65 | K40: 56.8
A41: Property, plant and equipment, Gross | B41: 64.44 | G41: 49.63
A42: Depreciation | B42: -33.67 | G42: -29.25
A43: Property, plant and equipment | B43: 30.78 | C43: 26.65 | D43: 30.37 | E43: 33.2 | F43: 29.04 | G43: 20.38 | H43: 21.62 | I43: 21.58 | J43: 19.77 | K43: 13.22
A44: Leasehold Improvements - Gross | B44: 16.2 | C44: 15.91 | D44: 20.33 | E44: 24.72 | F44: 25.51 | G44: 22.84 | H44: 22.9 | I44: 25.78 | J44: 27.03 | K44: 17.58
A45: Leasehold Improvements - Accumulated Depreciation | B45: -5.43 | C45: -6.52 | D45: -7.41 | E45: -9.48 | F45: -11.84 | G45: -12.23 | H45: -14.31 | I45: -16.71 | J45: -18.96 | K45: -12.18
A46: Furnitures, Fixtures and Equipment | B46: 27.17 | C46: 27.6 | D46: 29.36 | E46: 31.36 | F46: 30.03 | G46: 12.55 | H46: 13.83 | I46: 14.23 | J46: 14.51 | K46: 9.13
A47: Accumulated Depreciation, Furnitures, Fixtures and Equipment | B47: -15.67 | C47: -17.82 | D47: -19.11 | E47: -20.97 | F47: -21.61 | G47: -8.66 | H47: -9.34 | I47: -10.29 | J47: -10.95 | K47: -6.98
A48: Computer Equipment - Gross | B48: 21.08 | C48: 17.95 | D48: 16.68 | E48: 15.86 | F48: 16.48 | G48: 14.24 | H48: 19.01 | I48: 21.94 | J48: 24.17 | K48: 19.36
A49: Computer Equipment - Accumulated Depreciation | B49: -12.57 | C49: -10.47 | D49: -9.48 | E49: -8.28 | F49: -9.53 | G49: -8.36 | H49: -10.47 | I49: -13.37 | J49: -16.03 | K49: -13.69
A50: Total Intangible Assets excluding Goodwill, Gross | B50: 359.28 | G50: 410.03
A51: Amortization of Intangibles | B51: -224.41 | G51: -332.11
A52: Intangibles | B52: 134.87 | C52: 108.21 | D52: 132.96 | E52: 114.89 | F52: 92.6 | G52: 77.93 | H52: 286.67 | I52: 292.81 | J52: 270.64 | K52: 214.61
A53: Brands of Acquired Businesses - Gross | B53: 15.67 | C53: 15.42 | D53: 24.47 | E53: 24.73 | F53: 24.55 | G53: 22.47 | H53: 22.73 | I53: 23.54 | J53: 23.93 | K53: 11.53
A54: Brands of Acquired Businesses - Accumulated Amortisation | B54: -15.49 | C54: -15.19 | D54: -16.99 | E54: -24.13 | F54: -24.16 | G54: -22.25 | H54: -22.24 | I54: -22.22 | J54: -23.11 | K54: -11.47
A55: Computer Application Software - Gross | B55: 12.39 | C55: 13.06 | D55: 8.46 | E55: 5.8 | F55: 5.31 | G55: 5.37 | H55: 9.9 | I55: 27.66 | J55: 35.18 | K55: 18.99
A56: Computer Application Software - Accumulated Amortisation | B56: -8.84 | C56: -9.92 | D56: -6.53 | E56: -4.26 | F56: -4.2 | G56: -4.05 | H56: -4.45 | I56: -6.59 | J56: -13.56 | K56: -11.73
A57: Custom Software Applications - Gross | B57: 25.88 | C57: 26.17 | D57: 24.92 | E57: 26.51 | F57: 25.61 | G57: 25.16 | H57: 31.89 | I57: 33.51 | J57: 32.7 | K57: 31.77
A58: Custom Software Applications - Accumulated Amortisation | B58: -22.19 | C58: -23.41 | D58: -23.31 | E58: -25.98 | F58: -25.1 | G58: -25.16 | H58: -25.64 | I58: -27.73 | J58: -27.93 | K58: -27.56
A59: Internally Generated Software - Gross | B59: 16.24 | C59: 14.34 | D59: 23.42 | E59: 35.8 | F59: 34.27 | G59: 35.5 | H59: 130.88 | I59: 150.29 | J59: 156.75 | K59: 144.52
A60: Internally Generated Software - Accumulated Amortisation | B60: -7.32 | C60: -9.57 | D60: -12.77 | E60: -17.53 | F60: -21.35 | G60: -25.36 | H60: -30.66 | I60: -44.56 | J60: -57.25 | K60: -68.39
A61: Data Agreements - Net | H61: 26.43 | I61: 25.79 | J61: 22.91 | K61: 22.33
A62: Data Agreements - Gross | H62: 26.7 | I62: 28.48 | J62: 27.86 | K62: 30.22
A63: Data Agreements - Accumulated Amortisation | H63: -0.27 | I63: -2.69 | J63: -4.95 | K63: -7.89
A64: Customer Backlog - Gross | B64: 17.87 | C64: 17.71 | D64: 37.41 | E64: 39.32 | F64: 39.86 | G64: 45.77 | H64: 45.78 | I64: 45.65 | J64: 45.97 | K64: 10
A65: Customer Backlog - Accumulated Amortisation | B65: -16.89 | C65: -17.21 | D65: -17.84 | E65: -23.36 | F65: -27.23 | G65: -32.52 | H65: -37.89 | I65: -42.6 | J65: -44.59 | K65: -10
A66: Customer Lists - Gross | B66: 210.18 | C66: 202.74 | D66: 206.02 | E66: 217.75 | F66: 220.35 | G66: 203.31 | H66: 286.2 | I66: 297.24 | J66: 299.1 | K66: 233.51
A67: Customer Lists - Accumulated Amortisation | B67: -134.11 | C67: -143.56 | D67: -156.33 | E67: -180.66 | F67: -192.23 | G67: -184.4 | H67: -194.91 | I67: -212.83 | J67: -222.82 | K67: -172.88
A68: Databases, Gross | B68: 6.66 | C68: 6.66 | D68: 6.87 | E68: 6.88 | F68: 6.89 | G68: 6.9 | H68: 6.88 | I68: 6.92 | J68: 6.17 | K68: 6.19
A69: Databases - Accumulated Amortisation | B69: -4.11 | C69: -5.09 | D69: -6.08 | E69: -6.65 | F69: -6.67 | G69: -6.9 | H69: -6.88 | I69: -6.88 | J69: -6.13 | K69: -6.15
A70: Non- compete Agreements - Gross | B70: 24.97 | C70: 25.05 | D70: 34.73 | E70: 38.1 | F70: 39.38 | G70: 38.02 | H70: 43.95 | I70: 44.33 | J70: 45.37 | K70: 21.26
A71: Non- compete Agreements - Accumulated Amortisation | B71: -15.45 | C71: -17.69 | D71: -20.7 | E71: -26.45 | F71: -30.67 | G71: -31.47 | H71: -35.28 | I71: -40.19 | J71: -43.14 | K71: -20.56
A72: Indefinite Brands | B72: 29.43 | C72: 28.7 | D72: 27.22 | E72: 29.02 | F72: 28 | G72: 27.54 | H72: 40 | I72: 41.48 | J72: 41.11 | K72: 43.25
A73: Goodwill | B73: 239.35 | C73: 220.6 | D73: 249.99 | E73: 266.48 | F73: 260.38 | G73: 261.07 | H73: 467.31 | I73: 497.58 | J73: 509.98 | K73: 404.18
A74: Goodwill, Gross | B74: 291.5 | C74: 283.57 | D74: 310.78 | E74: 344.09 | F74: 342.86 | G74: 310.21 | H74: 515.95 | I74: 548.4 | J74: 560.74 | K74: 464.54
A75: Accumulated impairment, Goodwill | B75: -52.16 | C75: -62.97 | D75: -60.79 | E75: -77.61 | F75: -82.48 | G75: -49.14 | H75: -48.64 | I75: -50.82 | J75: -50.76 | K75: -60.37
A76: Right-of-use assets | E76: 0 | F76: 63.73 | G76: 51.69 | H76: 59.99 | I76: 38.87 | J76: 25.28 | K76: 19.42
A77: Right of Use Tangible Assets - Capital/Finance Lease - Gross | F77: 78.68 | G77: 75.77 | H77: 91.63 | I77: 90.94 | J77: 84.28 | K77: 67.51
A78: Right of Use Tangible Assets - Capital/Finance Lease - Accumulated Depreciation | F78: -14.95 | G78: -24.07 | H78: -31.64 | I78: -52.06 | J78: -58.99 | K78: -48.09
A79: Investment in joint venture | G79: 15.31 | H79: 16.5 | I79: 19.51 | J79: 22.66 | K79: 25.61
A80: Total Non-current Assets | B80: 442.79 | C80: 404.63 | D80: 547.68 | E80: 448.65 | F80: 489.06 | G80: 466.83 | H80: 915.47 | I80: 944.01 | J80: 912.13 | K80: 768.01
A81: Total Assets | B81: 597.72 | C81: 590.85 | D81: 726.12 | E81: 658.18 | F81: 735.13 | G81: 735.4 | H81: 1199.2 | I81: 1263.89 | J81: 1214.69 | K81: 1250.96
A82: Trade payables and other | B82: 81.28 | C82: 91.57 | D82: 101.45 | E82: 117.52 | F82: 128.57 | G82: 140.29 | H82: 193.39 | I82: 222.94 | J82: 199.22 | K82: 216.39
A83: Trade payables | D83: 8.2 | E83: 11.17 | F83: 9.94 | G83: 7.6 | H83: 10.63 | I83: 7.35 | J83: 17.54 | K83: 14.96
A84: Accrued expenses | D84: 52.67 | E84: 56.87 | F84: 67.75 | G84: 78.91 | H84: 98.44 | I84: 96.95 | J84: 93.58 | K84: 87.86
A85: Contract liabilities: deferred revenue | D85: 30.29 | E85: 30.03 | F85: 38.86 | G85: 42.35 | H85: 73.05 | I85: 90.07 | J85: 72.57 | K85: 71.93
A86: Deferred consideration payables | H86: 3.21 | I86: 1.74 | J86: 1.67 | K86: 0
A87: Contingent consideration payables | D87: 1.14 | E87: 11.11 | F87: 5.38 | G87: 0.05 | H87: 0 | I87: 3 | J87: 0.2 | K87: 0
A88: Share repurchase commitment | K88: 30
A89: Dividends payable | D89: 5.82 | E89: 5.9 | F89: 6.03 | G89: 6.12 | H89: 6.72 | I89: 6.82 | J89: 6.88 | K89: 6.93
A90: Due to related party (GeoVerra) | G90: 0.33 | H90: 0.09 | I90: 0
A91: Lease inducements | D91: 0.73 | E91: 0.91 | F91: 0
A92: Provisions | D92: 2.6 | E92: 1.55 | F92: 0.61 | G92: 4.94 | H92: 1.26 | I92: 17.01 | J92: 6.77 | K92: 4.71
A93: Income taxes payable | B93: 1.01 | C93: 5.1 | D93: 2.89 | E93: 6.8 | F93: 4.55 | G93: 1.19 | H93: 2.63 | I93: 2.06 | J93: 4.71 | K93: 3.02
A94: Lease liabilities | B94: 0.79 | C94: 0.83 | D94: 0.54 | E94: 0.19 | F94: 12.56 | G94: 11.7 | H94: 13.91 | I94: 14.86 | J94: 14.35 | K94: 11.01
A95: Borrowings | B95: 1.34 | C95: 6.18 | D95: 0.13 | E95: 0.67 | F95: 137.93 | G95: 0
A96: Borrowings | B96: 2.13 | C96: 7 | D96: 0.66 | E96: 0.86
A97: Derivative financial instruments | B97: 0 | D97: 0.92 | E97: 0
A98: Amounts payable to unitholders | C98: 0.85
A99: Liabilities directly associated with assets held for sale | K99: 57.68
A100: Total Current Liabilities | B100: 84.43 | C100: 104.52 | D100: 105.92 | E100: 125.18 | F100: 283.61 | G100: 153.18 | H100: 209.93 | I100: 239.86 | J100: 218.28 | K100: 288.1
A101: Lease liabilities | B101: 1.34 | C101: 0.75 | D101: 0.24 | E101: 0.07 | F101: 63.42 | G101: 51.88 | H101: 57.23 | I101: 45.46 | J101: 33.76 | K101: 26.75
...

Sheet Income Statement
A1: Company Fundamentals - Income Statement
A2: Company Name | B2: Altus Group Ltd (AIF.TO)
A3: Country of Exchange | B3: Canada
A4: Country of Headquarters | B4: Canada
A5: TRBC Industry Group | B5: Real Estate Operations
A6: CF Template | B6: IND
A7: Consolidation Basis | B7: Consolidated
A8: Scaling | B8: Millions
A9: Period | B9: Annual
A10: Export Date | B10: 46068.684
A11: Statement Data | B11: 2015 | C11: 2016 | D11: 2017 | E11: 2018 | F11: 2019 | G11: 2020 | H11: 2021 | I11: 2022 | J11: 2023 | K11: 2024
A12: Period End Date | B12: 42369 | C12: 42735 | D12: 43100 | E12: 43465 | F12: 43830 | G12: 44196 | H12: 44561 | I12: 44926 | J12: 45291 | K12: 45657
A13: Statement Date | B13: 42734 | C13: 42734 | D13: 43464 | E13: 43464 | F13: 44195 | G13: 44195 | H13: 44560 | I13: 44925 | J13: 45290 | K13: 45656
A14: Standardized Currency | B14: CAD | C14: CAD | D14: CAD | E14: CAD | F14: CAD | G14: CAD | H14: CAD | I14: CAD | J14: CAD | K14: CAD
A15: Template Type | B15: Industrial - Operating | C15: Industrial - Operating | D15: Industrial - Operating | E15: Industrial - Operating | F15: Industrial - Operating | G15: Industrial - Operating | H15: Industrial - Operating | I15: Industrial - Operating | J15: Industrial - Operating | K15: Industrial - Operating
A17: Income Statement - Company Specific (Currency: Canadian Dollar)
A18: Field Name | B18: 30-12-2015 | C18: 30-12-2016 | D18: 30-12-2017 | E18: 30-12-2018 | F18: 30-12-2019 | G18: 30-12-2020 | H18: 30-12-2021 | I18: 30-12-2022 | J18: 30-12-2023 | K18: 30-12-2024
A19: Revenues | B19: 416.41 | C19: 442.89 | D19: 476.56 | E19: 510.43 | F19: 525.72 | G19: 561.16 | H19: 625.39 | I19: 735.45 | J19: 772.84 | K19: 519.73
A20: Total Revenue | B20: 416.41 | C20: 442.89 | D20: 476.56 | E20: 510.43 | F20: 525.72 | G20: 561.16 | H20: 625.39 | I20: 735.45 | J20: 772.84 | K20: 519.73
A21: Employee compensation | B21: 260.35 | C21: 274.2 | D21: 295.17 | E21: 330.61 | F21: 329.09 | G21: 354.95 | H21: 401.46 | I21: 463.95 | J21: 481.77 | K21: 336.33
A22: Non-cash share-based compensation costs | F22: 5.64 | G22: 10.26 | H22: 19.45 | I22: 24.54 | J22: 19.79 | K22: 13.29
A23: Gain (loss) on equity derivatives net | F23: -1.11 | G23: 0.47 | H23: -2.04
A24: Gain (loss) on equity derivatives net of mark to market adjustments | I24: 2.48 | J24: 4.59 | K24: -2.89
A25: Employee compensation - Balancing value | F25: 324.56 | G25: 344.22 | H25: 384.04 | I25: 436.92 | J25: 457.38 | K25: 325.93
A26: Occupancy | B26: 18.55 | C26: 19.96 | D26: 20.71 | E26: 21.34 | F26: 7.29 | G26: 7.59 | H26: 7.74 | I26: 7.03 | J26: 7.85 | K26: 5.4
A27: Other operating | B27: 76.06 | C27: 79.82 | D27: 87.44 | E27: 98.04 | F27: 101.89 | G27: 102.19 | H27: 123.02 | I27: 152.89 | J27: 176.48 | K27: 100.46
A28: Unrealized foreign exchange gain (loss) | F28: 0.99 | G28: 0.17 | H28: 1.1 | I28: -3.85 | J28: 1.62 | K28: 0.76
A29: Gain (loss) on disposal of PPE and Intangibles | F29: 0.36 | G29: 0.46 | H29: -0.25 | I29: 0.83 | J29: 0.45 | K29: -2.5
A30: Share-based compensation | F30: 0 | G30: 0.75 | H30: 0
A31: Termination Benefits | F31: 1.75 | G31: 1.14 | H31: 0
A32: Non-Recurring Income/Expense - Other | I32: 11.74 | J32: 13.74 | K32: 5.86
A33: Office and other operating - Balancing value | F33: 98.79 | G33: 99.68 | H33: 122.17 | I33: 144.18 | J33: 160.67 | K33: 96.34
A34: Amortization of intangibles | B34: 33.04 | C34: 26.2 | D34: 29.18 | E34: 41.03 | F34: 29.53 | G34: 24.78 | H34: 29.02 | I34: 41 | J34: 40.72 | K34: 32.04
A35: Depreciation of right-of-use assets | F35: 12.32 | G35: 11.21 | H35: 12.12 | I35: 11.97 | J35: 11.12 | K35: 8.27
A36: Depreciation of property, plant and equipment | B36: 7.02 | C36: 7.23 | D36: 7.26 | E36: 8.09 | F36: 5.85 | G36: 5.62 | H36: 5.45 | I36: 6.56 | J36: 6.1 | K36: 3.71
A37: Acquisition and related transition costs (income) | B37: -0.43 | C37: 0.62 | D37: 3.32 | E37: 2.39 | F37: 0.19 | G37: -0.89 | H37: 10.14 | I37: 4.93 | J37: 3.83 | K37: 8.91
A38: Share of (profit) loss of joint venture | B38: 1.27 | C38: 2.62 | D38: 2.42 | E38: 0 | F38: 0 | G38: -0.46 | H38: -1.19 | I38: -3.01 | J38: -3.15 | K38: -2.95
A39: Restructuring costs (recovery) | B39: 2.69 | C39: 4.06 | D39: 4.74 | E39: 6.37 | F39: -0.3 | G39: 11.98 | H39: 0.02 | I39: 38.9 | J39: 0.39 | K39: 12.05
A40: Impairment of right of use assets | I40: 6.91 | J40: -0.56
A41: Restructuring costs (recovery) - Balancing value | I41: 31.99 | J41: 0.95
A42: (Gain) loss on investments | B42: -3.48 | C42: -9.93 | D42: -115.18 | E42: -0.04 | F42: -0.28 | G42: -0.02 | H42: -2.93 | I42: 0.16 | J42: 0.3 | K42: -0.45
A43: Impairment charge - goodwill | B43: 0 | C43: 12.5 | D43: 0 | E43: 13.7
A44: Impairment charge | K44: 7
A45: Total Operating Expense | B45: 395.06 | C45: 417.26 | D45: 335.07 | E45: 521.53 | F45: 485.59 | G45: 516.97 | H45: 584.84 | I45: 724.37 | J45: 725.41 | K45: 510.78
A46: Operating profit (loss) | B46: 21.35 | C46: 25.63 | D46: 141.49 | E46: -11.1 | F46: 40.13 | G46: 44.19 | H46: 40.55 | I46: 11.08 | J46: 47.43 | K46: 8.95
A47: Finance costs (income), net - leases | F47: -2.71 | G47: -2.49
A48: Interest on lease liabilities | H48: -2.22 | I48: -1.91 | J48: -1.22 | K48: -0.94
A49: Finance costs, net | B49: -11.25 | C49: -4.55 | D49: -3.63 | E49: -6.7 | F49: -6.57 | G49: -4.14 | H49: -4.13 | I49: -5.28 | J49: -23.88 | K49: -18.46
A50: Other | B50: 0.06 | C50: 0 | H50: -0.34 | I50: -0.1 | J50: -0.22 | K50: -0.23
A51: Interest on Bank credit facilities | B51: -5.51 | C51: -4.06 | D51: -4.65 | E51: -6.01 | F51: -5.63 | G51: -3.94 | H51: -3.92 | I51: -12.54 | J51: -20.79 | K51: -18.44
A52: Interest on lease liabilities | F52: -2.71 | G52: -2.49
A53: Contingent consideration payable: unwinding of discount | B53: -0.25 | C53: -0.2 | D53: -0.17 | E53: -0.65 | F53: -0.47 | G53: -0.1 | H53: -0.11
A54: Provisions: unwinding of discount | B54: -0.02 | C54: -0.01 | D54: -0.01 | E54: -0.04 | F54: -0.12 | G54: -0.03 | H54: 0
A55: Change in fair value of interest rate swaps | D55: 1.36 | E55: -0.22 | F55: -0.5 | G55: -0.14 | H55: 0 | I55: 6.86 | J55: -3.06 | K55: -0.2
A56: Distributions payable on Altus UK LLP class B and D units | B56: -0.1 | C56: -0.03
A57: Change in fair value of interest rate swaps | B57: -1.24 | C57: 0.74
A58: Interest on convertible debentures | B58: -4.1 | C58: -0.67 | D58: -0.18 | E58: 0
A59: Interest on finance leases | B59: -0.13 | C59: -0.13 | D59: -0.08 | E59: -0.04
A60: Change in fair value of Altus UK LLP Class B and D units, net of change in fair value of related equity derivative | B60: -0.01 | C60: -0.21 | D60: -0.03 | E60: 0
A61: Finance income | B61: 0.05 | C61: 0.02 | D61: 0.13 | E61: 0.25 | F61: 0.15 | G61: 0.08 | H61: 0.25 | I61: 0.51 | J61: 0.19 | K61: 0.42
A62: Finance costs, net - Balancing value | F62: 2.71 | G62: 2.49
A63: Profit (loss) before income taxes from continuing operations | B63: 10.1 | C63: 21.08 | D63: 137.86 | E63: -17.8 | F63: 30.85 | G63: 37.56 | H63: 34.2 | I63: 3.88 | J63: 22.33 | K63: -10.44
A64: Income tax expense (recovery) | B64: 0.85 | C64: 6.81 | D64: 28.44 | E64: 0.64 | F64: 6.96 | G64: 10.55 | H64: 8.63 | I64: 4.77 | J64: 12.1 | K64: -9.65
A65: Current | B65: 4.73 | C65: 9.97 | D65: 14.36 | E65: 12.71 | F65: 14.31 | G65: 12.71 | H65: 19.05 | I65: 10.8 | J65: 16.54 | K65: 17.5
A66: Current income tax on profits for the year | B66: 4.6 | C66: 10.01 | D66: 13.88 | E66: 12.64 | F66: 14.57 | G66: 12.37 | H66: 18.57 | I66: 11.49 | J66: 17.54 | K66: 18.6
A67: Adjustments in respect of prior years | B67: 0.13 | C67: -0.04 | D67: 0.48 | E67: 0.07 | F67: -0.26 | G67: 0.34 | H67: 0.48 | I67: -0.7 | J67: -1 | K67: -1.11
A68: Deferred | B68: -3.88 | C68: -3.16 | D68: 14.09 | E68: -12.07 | F68: -7.35 | G68: -2.16 | H68: -10.42 | I68: -6.03 | J68: -4.44 | K68: -27.15
A69: Origination and reversal of temporary differences | B69: -4.36 | C69: -2.52 | D69: 8.76 | E69: -12.17 | F69: -7.33 | G69: -2.01 | H69: -10.54 | I69: -6.43 | J69: -5.31 | K69: -28.15
A70: Adjustments in respect of prior years | B70: 0.48 | C70: -0.19 | D70: -0.43 | E70: 0.1 | F70: 0 | G70: -0.41 | H70: -0.57 | I70: 0.33 | J70: 0.88 | K70: 1.01
A71: Change in income tax rates | B71: 0 | C71: -0.45 | D71: 5.75 | E71: 0.01 | F71: 0 | G71: 0.26 | H71: 0.69 | I71: 0.07 | J71: 0
A72: Deferred - Balancing value | F72: -0.02
A73: Income Taxes - Total | B73: 0.85 | C73: 6.81 | D73: 28.44 | E73: 0.64 | F73: 6.96 | G73: 10.55 | H73: 8.63 | I73: 4.77 | J73: 12.1 | K73: -9.65
A74: Profit (loss) for the period | B74: 9.25 | C74: 14.27 | D74: 109.42 | E74: -18.44 | F74: 23.89 | G74: 27.01 | H74: 25.57 | I74: -0.89 | J74: 10.23 | K74: -0.79
A75: Profit (loss) for the period | B75: 9.25 | C75: 14.27 | D75: 109.42 | E75: -18.44 | F75: 23.89 | G75: 27.01 | H75: 25.57 | I75: -0.89 | J75: 10.23 | K75: -0.79
A76: Profit (loss) for the year from discontinued operations | F76: -5.7 | G76: -5.58 | H76: 0 | K76: 14.22
A77: Extraordinary Items (after Tax) | F77: -5.7 | G77: -5.58 | H77: 0 | K77: 14.22
A78: Non controlling interest | H78: -0.11 | I78: 0 | J78: 0
A79: Minority Interest - Total | H79: -0.11 | I79: 0 | J79: 0
A80: Profit (loss) for the period attributable to shareholders | B80: 9.25 | C80: 14.27 | D80: 109.42 | E80: -18.44 | F80: 18.19 | G80: 21.43 | H80: 25.69 | I80: -0.89 | J80: 10.23 | K80: 13.42
A81: Profit (loss) for the period | B81: 9.25 | C81: 14.27 | D81: 109.42 | E81: -18.44 | F81: 23.89 | G81: 27.01 | H81: 25.69 | I81: -0.89 | J81: 10.23 | K81: -0.79
A82: Profit (loss) for the period | B82: 9.25 | C82: 14.27 | D82: 109.42 | E82: -18.44 | F82: 18.19 | G82: 21.43 | H82: 25.69 | I82: -0.89 | J82: 10.23 | K82: 13.42
A83: Profit (loss) for the year | D83: 109.42 | E83: -18.44 | F83: 18.19 | G83: 21.43 | H83: 25.57 | I83: -0.89 | J83: 10.23 | K83: 13.42
A84: Currency translation differences | D84: -9.87 | E84: 17.7 | F84: -13.77 | G84: 1.53 | H84: -4.83 | I84: 11.03 | J84: -2.06 | K84: 30.55
A85: Share of other comprehensive loss of associates | D85: -0.05 | E85: 0
A86: Changes in investments measured at fair value through other comprehensive income, net of tax | D86: -26.46 | E86: 0 | J86: -1.14 | K86: -1.65
A87: Change in fair value of FVOCI investments | D87: 0 | E87: -44.35 | F87: 0.09 | G87: -0.99 | H87: 2.48 | I87: -0.33
A88: Other Comprehensive Income - Net of Tax - Total | D88: -36.38 | E88: -26.65 | F88: -13.68 | G88: 0.55 | H88: -2.35 | I88: 10.7 | J88: -3.2 | K88: 28.91
A89: Comprehensive Income - Attributable to Minority Interest - Total | I89: 0 | J89: 0
A90: Shareholders of the Company Earnings (loss) per share attributable to the shareholders of the Company during the year | I90: 9.81 | J90: 7.03 | K90: 42.33
A91: attributable to shareholders | D91: 73.04 | E91: -45.09 | F91: 4.51 | G91: 21.98 | H91: 23.22 | I91: 9.81 | J91: 7.03 | K91: 42.33
A92: As Reported Basic Weighted Avg. Shares | B92: 33.35 | C92: 36.81 | D92: 38.03 | E92: 38.76 | F92: 39.46 | G92: 40.16 | H92: 41.68 | I92: 44.64 | J92: 45.3 | K92: 45.79
A93: As Reported Diluted Weighted Avg. Shares | B93: 33.82 | C93: 37.48 | D93: 38.66 | E93: 38.76 | F93: 40.08 | G93: 41.21 | H93: 42.9 | I93: 44.64 | J93: 45.91 | K93: 45.79
A94: Basic earnings (loss) per share | B94: 0.28 | C94: 0.39 | D94: 2.88 | E94: -0.48 | F94: 0.47 | G94: 0.53 | H94: 0.62 | I94: -0.02 | J94: 0.23 | K94: 0.29
A95: Diluted earnings (loss) per share | B95: 0.28 | C95: 0.39 | D95: 2.88 | E95: -0.48 | F95: 0.61 | G95: 0.67 | H95: 0.62 | I95: -0.02 | J95: 0.23 | K95: -0.02
A96: Diluted EPS Excluding ExtraOrd Items | B96: 0.27 | C96: 0.38 | D96: 2.83 | E96: -0.48 | F96: 0.6 | G96: 0.66 | H96: 0.6 | I96: -0.02 | J96: 0.22 | K96: -0.02
A97: Diluted Net Income | B97: 9.25 | C97: 14.27 | D97: 109.42 | E97: -18.44 | F97: 18.19 | G97: 21.43 | H97: 25.69 | I97: -0.89 | J97: 10.23 | K97: 13.42
A98: Diluted earnings (loss) per share | B98: 0.27 | C98: 0.38 | D98: 2.83 | E98: -0.48 | F98: 0.46 | G98: 0.52 | H98: 0.6 | I98: -0.02 | J98: 0.22 | K98: 0.29
A99: Diluted Net Income excluding Extra Items applicable to Common - (Company Level) | B99: 9.25 | C99: 14.27 | D99: 109.42 | E99: -18.44 | F99: 23.89 | G99: 27.01 | H99: 25.69 | I99: -0.89 | J99: 10.23 | K99: -0.79
A100: Audit Fees | B100: 0.99 | C100: 1.04 | D100: 1.07 | E100: 1.2 | F100: 1.26 | G100: 1.26 | H100: 1.37 | I100: 1.39 | J100: 1.5 | K100: 1.81
A101: Audit-Related Fees | B101: 0.18 | C101: 0.17 | D101: 0.28 | E101: 0.21 | F101: 0.08 | G101: 0.1 | H101: 0.72 | I101: 0.23 | J101: 0.19 | K101: 0.19
...

Sheet Cash Flow
A1: Company Fundamentals - Cash Flow
A2: Company Name | B2: Altus Group Ltd (AIF.TO)
A3: Country of Exchange | B3: Canada
A4: Country of Headquarters | B4: Canada
A5: TRBC Industry Group | B5: Real Estate Operations
A6: CF Template | B6: IND
A7: Consolidation Basis | B7: Consolidated
A8: Scaling | B8: Millions
A9: Period | B9: Annual
A10: Export Date | B10: 46068.684
A11: Statement Data | B11: 2015 | C11: 2016 | D11: 2017 | E11: 2018 | F11: 2019 | G11: 2020 | H11: 2021 | I11: 2022 | J11: 2023 | K11: 2024
A12: Period End Date | B12: 42369 | C12: 42735 | D12: 43100 | E12: 43465 | F12: 43830 | G12: 44196 | H12: 44561 | I12: 44926 | J12: 45291 | K12: 45657
A13: Statement Date | B13: 42368 | C13: 42734 | D13: 43464 | E13: 43464 | F13: 43829 | G13: 44195 | H13: 44560 | I13: 44925 | J13: 45290 | K13: 45656
A14: Standardized Currency | B14: CAD | C14: CAD | D14: CAD | E14: CAD | F14: CAD | G14: CAD | H14: CAD | I14: CAD | J14: CAD | K14: CAD
A15: Template Type | B15: Industrial - Indirect | C15: Industrial - Indirect | D15: Industrial - Indirect | E15: Industrial - Indirect | F15: Industrial - Indirect | G15: Industrial - Indirect | H15: Industrial - Indirect | I15: Industrial - Indirect | J15: Industrial - Indirect | K15: Industrial - Indirect
A17: Cash Flow - Company Specific (Currency: Canadian Dollar)
A18: Field Name | B18: 30-12-2015 | C18: 30-12-2016 | D18: 30-12-2017 | E18: 30-12-2018 | F18: 30-12-2019 | G18: 30-12-2020 | H18: 30-12-2021 | I18: 30-12-2022 | J18: 30-12-2023 | K18: 30-12-2024
A19: Profit (loss) before income taxes | B19: 10.1 | C19: 21.08 | D19: 137.86 | E19: -17.8 | F19: 25.15 | G19: 37.56 | H19: 34.2 | I19: 3.88 | J19: 22.33 | K19: 8.76
A20: Depreciation of right-of-use assets | F20: 13.44 | G20: 11.26 | H20: 12.12 | I20: 11.97 | J20: 11.12 | K20: 9.95
A21: Depreciation of property, plant and equipment | B21: 7.02 | C21: 7.23 | D21: 7.26 | E21: 8.09 | F21: 7.84 | G21: 5.73 | H21: 5.45 | I21: 6.56 | J21: 6.1 | K21: 4.55
A22: Amortization of intangibles | B22: 33.04 | C22: 26.2 | D22: 29.18 | E22: 41.03 | F22: 30 | G22: 24.79 | H22: 29.02 | I22: 41 | J22: 40.72 | K22: 35.92
A23: Amortization of lease inducements | B23: 0.32 | C23: -0.26 | D23: 0.9 | E23: 0.69 | F23: 0
A24: Finance costs (income), net - leases | F24: 2.89 | G24: 2.56 | H24: 2.22 | I24: 1.91 | J24: 1.22 | K24: 1.19
A25: Tax credits recorded through employee compensation | B25: -0.02 | C25: -0.13
A26: Amortization of capitalized software development costs | B26: 0.53 | C26: 0.52 | D26: 0.29 | E26: 0
A27: Finance costs (income), net - other | B27: 11.25 | C27: 4.55 | D27: 3.63 | E27: 6.7 | F27: 6.57 | G27: 4.12 | H27: 4.13 | I27: 5.28 | J27: 23.88 | K27: 17.98
A28: Share-based compensation | B28: 5.95 | C28: 7.12 | D28: 7.82 | E28: 9.46 | F28: 9.84 | G28: 15.4 | H28: 23.94 | I28: 29.38 | J28: 23.07 | K28: 23.67
A29: Unrealized foreign exchange (gain) loss | B29: -1.68 | C29: 1.79 | D29: 0.85 | E29: -0.98 | F29: 0.99 | G29: 0.17 | H29: 1.1 | I29: -3.85 | J29: 1.62 | K29: -0.34
A30: (Gain) loss on investments | D30: -115.18 | E30: -0.04 | F30: -0.28 | G30: -0.02 | H30: -2.93 | I30: 0.16 | J30: 0.3 | K30: -0.45
A31: (Gain) loss on disposal of property, plant and equipment and intangibles | B31: 0.42 | C31: 0.12 | D31: 0.86 | E31: 1.62 | F31: 0.27 | G31: 0.52 | H31: -0.25 | I31: 0.83 | J31: 0.45 | K31: -2.02
A32: (Gain) loss on equity derivatives | B32: 0.21 | C32: -3.96 | D32: -1.24 | E32: 4.82 | F32: -6.84 | G32: -3.99 | H32: -10.25 | I32: 8.74 | J32: 8.6 | K32: -9.94
A33: Impairment charge leases | C33: 12.5 | E33: 13.7 | F33: 0.07 | G33: 0.04 | H33: 0
A34: Impairment charge - goodwill | F34: 6.4 | G34: 0
A35: Share of (profit) loss of joint venture | B35: 1.27 | C35: 2.62 | D35: 2.42 | E35: 0 | G35: -0.46 | H35: -1.19 | I35: -3.01 | J35: -3.15 | K35: -2.95
A36: Operating working capital | B36: -1.68 | C36: 11.74 | D36: 9.41 | E36: -3.83 | F36: -23.11 | G36: -1.91 | H36: -18.83 | I36: 0.18 | J36: -24.12 | K36: 11.7
A37: Net cash generated by (used in) operations | C37: 81.18 | D37: 84.08 | E37: 63.45 | F37: 73.23 | G37: 94.86 | H37: 78.72 | I37: 104.25 | J37: 107.58 | K37: 122.06
A38: Interest paid on borrowings | B38: -7.2 | C38: -4.25 | D38: -4.31 | E38: -5.37 | F38: -5.04 | G38: -3.55 | H38: -3.61 | I38: -11.73 | J38: -20.27 | K38: -18.06
A39: Interest paid on leases | F39: -2.88 | G39: -2.56 | H39: -2.22 | I39: -1.91 | J39: -1.22 | K39: -1.19
A40: Income taxes paid | B40: -8.61 | C40: -10.41 | D40: -23.77 | E40: -13.52 | F40: -15.45 | G40: -19.05 | H40: -19.55 | I40: -14.83 | J40: -14.89 | K40: -23.59
A41: Income taxes refunded | B41: 0.71 | C41: 0.71 | D41: 1.84 | E41: 4.93 | F41: 2.58 | G41: 2.6 | H41: 2.96 | I41: 1.31 | J41: 0.24 | K41: 0.7
A42: (Gain) loss on investments | B42: -3.48 | C42: -9.93
A43: Fair value loss (gain) on net assets directly associated with discontinued operations | G43: 5.16 | H43: 0
A44: (Gain) loss on sale of the discontinued operations | G44: -0.48 | H44: 0
A45: Profit (loss) from discontinued operations before income taxes | G45: -5.58 | H45: 0
A46: Impairment of right | I46: 6.91 | J46: -0.56 | K46: -0.32
A47: Contingent consideration payables | I47: 3.01 | J47: -2.99 | K47: -0.2
A48: Deferred consideration payables | I48: -3.38 | J48: -1.61 | K48: -1.67
A49: Liabilities for cash-settled share-based compensation | I49: -5.3 | J49: 0.59 | K49: 19.25
A50: Impairment of non-financial assets | K50: 7
A51: Net cash provided by (used in) operating activities | B51: 48.14 | C51: 67.24 | D51: 57.84 | E51: 49.49 | F51: 52.43 | G51: 72.3 | H51: 56.31 | I51: 77.08 | J51: 71.43 | K51: 79.92
A52: Purchase of investments | B52: 0 | D52: -6.72 | E52: -3.9 | F52: -0.71 | G52: -0.36 | H52: -4.16 | I52: -0.86 | J52: -0.84 | K52: -0.88
A53: Purchase of intangibles | B53: -1.74 | C53: -2.6 | D53: -0.62 | E53: -0.83 | F53: -0.15 | G53: -0.77 | H53: -4.66 | I53: -19.05 | J53: -7.66 | K53: -6.06
A54: Purchase of property, plant and equipment | B54: -12.32 | C54: -4.23 | D54: -11.79 | E54: -11.54 | F54: -5.79 | G54: -3.58 | H54: -5.96 | I54: -5.43 | J54: -4.83 | K54: -1.39
A55: Proceeds from disposal of property, plant and equipment and intangibles | B55: 0.16 | C55: 0.48 | D55: 0.45 | E55: 0.27 | F55: 0.15 | G55: 0.1 | H55: 0
A56: Proceeds from disposal of investment | D56: 0 | E56: 54.17 | F56: 0.55 | G56: 0
A57: Acquisitions, net of cash acquired | B57: -12.96 | C57: -1.71 | D57: -62.91 | E57: -27.19 | F57: -12.48 | G57: -12.49 | H57: -358.85 | I57: -29.85 | J57: -25.09 | K57: 0
A58: Cash contribution to investment in joint venture | G58: -3.79 | H58: 0
A59: Proceeds from investments | H59: 0.33 | I59: 0.02 | J59: 0.03 | K59: 0.09
A60: Proceeds from disposal of investments | I60: 1.11 | J60: 3.47 | K60: 0
A61: Proceeds from sale of disposal group | K61: 11.02
A62: Net cash provided by (used in) investing activities | B62: -26.86 | C62: -8.06 | D62: -81.59 | E62: 10.98 | F62: -18.43 | G62: -20.9 | H62: -373.31 | I62: -54.06 | J62: -34.92 | K62: 2.77
A63: Proceeds from exercise of options | B63: 4.01 | C63: 1.45 | D63: 3.91 | E63: 0.84 | F63: 6.88 | G63: 11.99 | H63: 13.81 | I63: 8.16 | J63: 10.42 | K63: 17.68
A64: Redemption of Altus UK LLP Class B and D units | B64: -0.19 | C64: -2.06 | D64: -0.88 | E64: 0
A65: Financing fees paid | B65: -1.27 | C65: -0.09 | G65: -0.72 | H65: -0.41 | I65: -1.9 | J65: -0.01 | K65: -0.17
A66: Proceeds from borrowings | B66: 10 | C66: 6 | D66: 54.92 | E66: 51.28 | F66: 21.6 | G66: 38.14 | H66: 341.02 | I66: 84.5 | J66: 72.15 | K66: 34.43
A67: Repayment of borrowings | B67: -13.91 | C67: -17.15 | D67: -22.84 | E67: -73.23 | F67: -12.87 | G67: -53.26 | H67: -178.82 | I67: -57.14 | J67: -83.6 | K67: -72.36
A68: Dividends paid | B68: -16.49 | C68: -18.55 | D68: -21.81 | E68: -18.8 | F68: -19.2 | G68: -21.86 | H68: -21.56 | I68: -24.7 | J68: -26.58 | K68: -24.73
A69: Interest paid to Altus UK LLP Class B and D unitholders | B69: -0.1 | C69: -0.03
A70: Treasury shares purchased for share-based compensation | B70: -3.11 | C70: -3.59 | D70: -3.59 | E70: -3.06 | F70: -5.35 | G70: -3.61 | H70: -6.31 | I70: -4.61 | J70: -4.82 | K70: -3.48
A71: Payments of principal on lease liabilities | F71: -11.84 | G71: -11.96 | H71: -12.07 | I71: -14.98 | J71: -15.09 | K71: -15.94
A72: Proceeds from share issuance, net of transaction costs | H72: 164.77 | I72: 0
A73: Cancellation of shares | I73: -8 | J73: -4.78 | K73: -11.04
A74: Proceeds from right-of-use asset lease inducements | J74: 0.53 | K74: 0
A75: Net cash provided by (used in) financing activities | B75: -21.06 | C75: -34.02 | D75: 9.71 | E75: -42.97 | F75: -20.79 | G75: -41.3 | H75: 300.43 | I75: -18.66 | J75: -51.78 | K75: -75.62
A76: Effect of foreign currency translation | B76: 1.94 | C76: -1.09 | D76: -1.57 | E76: 3.17 | F76: -1.68 | G76: -0.72 | H76: -1.79 | I76: -0.37 | J76: 1.9 | K76: 1.63
A77: Cash and cash equivalents, beginning of period | B77: 17.45 | C77: 19.6 | D77: 43.67 | E77: 28.07 | F77: 48.74 | G77: 60.26 | H77: 69.64 | I77: 51.27 | J77: 55.27 | K77: 41.89
A78: Cash and cash equivalents, end of period | B78: 19.6 | C78: 43.67 | D78: 28.07 | E78: 48.74 | F78: 60.26 | G78: 69.64 | H78: 51.27 | I78: 55.27 | J78: 41.89 | K78: 50.59
A79: Net increase (decrease) in cash and cash equivalents | B79: 2.15 | C79: 24.07 | D79: -15.6 | E79: 20.67 | F79: 11.52 | G79: 9.38 | H79: -18.37 | I79: 4 | J79: -13.37 | K79: 8.7

Sheet Financials
A1: Profitability
B2: 2015 | C2: 2016 | D2: 2017 | E2: 2018 | F2: 2019 | G2: 2020 | H2: 2021 | I2: 2022 | J2: 2023 | K2: 2024
A3: GPM | B3: 1 | C3: 1 | D3: 1 | E3: 1 | F3: 1 | G3: 1 | H3: 1 | I3: 1 | J3: 1 | K3: 1
A4: NPM | B4: ='Income Statement'!B82/'Income Statement'!B20 -> 0.022213684 | C4: ='Income Statement'!C82/'Income Statement'!C20 -> 0.03222019 | D4: ='Income Statement'!D82/'Income Statement'!D20 -> 0.22960383 | E4: ='Income Statement'!E82/'Income Statement'!E20 -> -0.036126403 | F4: ='Income Statement'!F82/'Income Statement'!F20 -> 0.034600167 | G4: ='Income Statement'!G82/'Income Statement'!G20 -> 0.038188752 | H4: ='Income Statement'!H82/'Income Statement'!H20 -> 0.041078367 | I4: ='Income Statement'!I82/'Income Statement'!I20 -> -0.0012101434 | ... K4: ='Income Statement'!K82/'Income Statement'!K20 -> 0.025821099
A5: ROA | B5: ='Income Statement'!B82/'Balance Sheet'!B81 -> 0.015475473 | C5: ='Income Statement'!C82/'Balance Sheet'!C81 -> 0.024151646 | D5: ='Income Statement'!D82/'Balance Sheet'!D81 -> 0.15069135 | E5: ='Income Statement'!E82/'Balance Sheet'!E81 -> -0.028016652 | F5: ='Income Statement'!F82/'Balance Sheet'!F81 -> 0.024743923 | G5: ='Income Statement'!G82/'Balance Sheet'!G81 -> 0.029140604 | H5: ='Income Statement'!H82/'Balance Sheet'!H81 -> 0.021422615 | I5: ='Income Statement'!I82/'Balance Sheet'!I81 -> -0.00070417521 | ... K5: ='Income Statement'!K82/'Balance Sheet'!K81 -> 0.010727761
A6: ROE | B6: ='Income Statement'!B82/'Balance Sheet'!B130 -> 0.026383343 | C6: ='Income Statement'!C82/'Balance Sheet'!C130 -> 0.041897883 | D6: ='Income Statement'!D82/'Balance Sheet'!D130 -> 0.26554385 | E6: ='Income Statement'!E82/'Balance Sheet'!E130 -> -0.051446587 | F6: ='Income Statement'!F82/'Balance Sheet'!F130 -> 0.05057695 | G6: ='Income Statement'!G82/'Balance Sheet'!G130 -> 0.055887339 | H6: ='Income Statement'!H82/'Balance Sheet'!H130 -> 0.043580783 | I6: ='Income Statement'!I82/'Balance Sheet'!I130 -> -0.0014836548 | ... K6: ='Income Statement'!K82/'Balance Sheet'!K130 -> 0.021742653
A7: OPM | B7: ='Income Statement'!B46/'Income Statement'!B20 -> 0.051271583 | C7: ='Income Statement'!C46/'Income Statement'!C20 -> 0.0578699 | D7: ='Income Statement'!D46/'Income Statement'!D20 -> 0.29689861 | E7: ='Income Statement'!E46/'Income Statement'!E20 -> -0.021746371 | F7: ='Income Statement'!F46/'Income Statement'!F20 -> 0.076333409 | G7: ='Income Statement'!G46/'Income Statement'!G20 -> 0.078747594 | H7: ='Income Statement'!H46/'Income Statement'!H20 -> 0.06483954 | I7: ='Income Statement'!I46/'Income Statement'!I20 -> 0.015065606 | ... K7: ='Income Statement'!K46/'Income Statement'!K20 -> 0.01722048
A10: Liquidity
B11: 2015 | C11: 2016 | D11: 2017 | E11: 2018 | F11: 2019 | G11: 2020 | H11: 2021 | I11: 2022 | J11: 2023 | K11: 2024
A12: Current Ratio | B12: ='Balance Sheet'!B33/'Balance Sheet'!B100 -> 1.8350113 | C12: ='Balance Sheet'!C33/'Balance Sheet'!C100 -> 1.7816686 | D12: ='Balance Sheet'!D33/'Balance Sheet'!D100 -> 1.6846677 | E12: ='Balance Sheet'!E33/'Balance Sheet'!E100 -> 1.6739096 | F12: ='Balance Sheet'!F33/'Balance Sheet'!F100 -> 0.86763513 | G12: ='Balance Sheet'!G33/'Balance Sheet'!G100 -> 1.7532968 | H12: ='Balance Sheet'!H33/'Balance Sheet'!H100 -> 1.3515458 | I12: ='Balance Sheet'!I33/'Balance Sheet'!I100 -> 1.3336113 | ... K12: ='Balance Sheet'!K33/'Balance Sheet'!K100 -> 1.6763277
A16: Operating
B17: 2015 | C17: 2016 | D17: 2017 | E17: 2018 | F17: 2019 | G17: 2020 | H17: 2021 | I17: 2022 | J17: 2023 | K17: 2024
A18: Accounts Receivable Turnover | B18: 3.3 | C18: 3.42 | D18: 3.49 | E18: 3.4 | F18: 3.05 | G18: 2.95 | H18: 2.96 | I18: 3 | J18: 2.96 | K18: 2.54
A19: Average Receivables Collection Days | B19: 110.98 | C19: 107.07 | D19: 104.76 | E19: 107.72 | F19: 119.98 | G19: 124.19 | H19: 123.79 | I19: 121.8 | J19: 123.82 | K19: 144.33
A22: Leverage
B23: 2015 | C23: 2016 | D23: 2017 | E23: 2018 | F23: 2019 | G23: 2020 | H23: 2021 | I23: 2022 | J23: 2023 | K23: 2024
A24: TDTA | B24: 22.83 | C24: 20.98 | D24: 20.77 | E24: 19.66 | F24: 29.14 | G24: 25.29 | H24: 29.86 | I24: 29.92 | J24: 29.27 | K24: 25.55
A25: TDTC | B25: 28.01 | C25: 26.68 | D25: 26.79 | E25: 26.52 | F25: 37.33 | G25: 32.66 | H25: 37.67 | I25: 38.66 | J25: 37.11 | K25: 34.12
A26: TDTE | B26: 38.91 | C26: 36.39 | D26: 36.6 | E26: 36.09 | F26: 59.57 | G26: 48.51 | H26: 60.75 | I26: 63.04 | J26: 59.01 | K26: 51.79
A27: ICR | B27: 2.2 | C27: 7.3 | D27: 7.49 | E27: 1.87 | F27: 3.78 | G27: 6.39 | H27: 7.4 | I27: 4.38 | J27: 3.14 | K27: 1.79

Sheet Process_CSCF
A1: Historical FCF | L1: Projected FCF
B2: 2015 | C2: 2016 | D2: 2017 | E2: 2018 | F2: 2019 | G2: 2020 | H2: 2021 | I2: 2022 | J2: 2023 | K2: 2024 | L2: 2025 | M2: 2026 | N2: 2027 | O2: 2028 | P2: 2029 | Q2: 2030 & >
A3: Cash Flow from Operation | B3: {='Cash Flow'!B51:K51} -> 48.14 | C3: 67.24 | D3: 57.84 | E3: 49.49 | F3: 52.43 | G3: 72.3 | H3: 56.31 | I3: 77.08 | J3: 71.43 | K3: 79.92
A4: Capital Expenditure | B4: {='Cash Flow'!B54:K54} -> -12.32 | C4: -4.23 | D4: -11.79 | E4: -11.54 | F4: -5.79 | G4: -3.58 | H4: -5.96 | I4: -5.43 | J4: -4.83 | K4: -1.39
A5: FCF | B5: =B3+B4 -> 35.82 | C5: =C3+C4 -> 63.01 | D5: =D3+D4 -> 46.05 | E5: =E3+E4 -> 37.95 | F5: =F3+F4 -> 46.64 | G5: =G3+G4 -> 68.72 | H5: =H3+H4 -> 50.35 | I5: =I3+I4 -> 71.65 | ... K5: =K3+K4 -> 78.53 | L5: =K5*(1+L7) -> 82.4565 | M5: =L5*(1+M7) -> 86.167042 | N5: =M5*(1+N7) -> 89.613724 | O5: =N5*(1+O7) -> 92.750205 | P5: =O5*(1+P7) -> 95.532711 | Q5: =P5*(1+DCF_CSCF!B8)/(L12-DCF_CSCF!B8) -> 1801.6928
A6: Growth Rate (YoY) | B6: =(C5-B5)/B5 -> 0.75907314 | C6: =(D5-C5)/C5 -> -0.26916362 | D6: =(E5-D5)/D5 -> -0.17589577 | E6: =(F5-E5)/E5 -> 0.22898551 | F6: =(G5-F5)/F5 -> 0.47341338 | G6: =(H5-G5)/G5 -> -0.26731665 | H6: =(I5-H5)/H5 -> 0.42303873 | I6: =(J5-I5)/I5 -> -0.070481507 | J6: =(K5-J5)/J5 -> 0.17912913
A7: Shor-term Growth Rates (Assumptions) | L7: 0.05 | M7: =L7-0.5% -> 0.045 | N7: =M7-0.5% -> 0.04 | O7: =N7-0.5% -> 0.035 | P7: =O7-0.5% -> 0.03
B8: 2015-2024 | C8: 2020-2024
A9: Average Growth Rate | B9: =AVERAGE(B6:J6) -> 0.14230915 | C9: =AVERAGE(G6:J6) -> 0.066092426 | K9: Industry Name | L9: Number of Firms | M9: Beta | N9: Cost of Equity | O9: E/(D+E) | P9: Std Dev in Stock | Q9: Cost of Debt | R9: Tax Rate | S9: After-tax Cost of Debt | T9: D/(D+E) | U9: Cost of Capital | V9: Cost of Capital (Local Currency)
A10: Median Growth Rate | B10: =MEDIAN(B6:J6) -> 0.17912913 | C10: =MEDIAN(G6:J6) -> 0.054323811 | K10: Real Estate (Operations & Services) | L10: 54 | M10: 0.96549741 | N10: 0.082561184 | O10: 0.80229597 | P10: 0.50559626 | Q10: 0.052913 | R10: 0.086974403 | S10: 0.03968475 | T10: 0.19770403 | U10: 0.07408434 | V10: 0.07408434
A11: CAGR | B11: =((K5/B5)^(1/10)-1) -> 0.081660578 | C11: =((K5/G5)^(1/10)-1) -> 0.013433473
K12: WAACC | L12: =(O10*N10)+(T10*S10) -> 0.07408434

Sheet DCF_CSCF
A1: Input and Assumptions
J2: Cells in YELLOW are input
A3: Last Updated on | B3: 46073
A4: Last Financial Statement Date | B4: ='Balance Sheet'!K12 -> 45657 | J4: Cells in BEIGE are looked up
A5: Current Market Price | B5: 40.25
A6: # of share outstanding in million (FY 2024) | B6: 40.4 | J6: Cells in WHITE are calculated
A7: Initial FCF Growth (Short-term Rate) | B7: =Process_CSCF!C10 -> 0.054323811 | C7: Growth is phased down from the initial rate
A8: Growth rate of FCF (long term growth) | B8: 0.02 | J8: Cells in RED are output
A9: Discount Rate (WACC) | B9: =Process_CSCF!L12 -> 0.07408434
A13: Investment Criteria
A15: Decision | B15: Difference Between Value and Price
A16: Sell | B16: =ROUND((B37-B5) / B5, 3) -> -0.126 | C16: {=_xlfn.IFS(B16>0.1,"BUY",B16<-0.1,"SELL",TRUE,"HOLD")} -> SELL
A17: Underperform
A18: HOLD
A19: BUY
A20: Strong Buy
A22: Free Cash Flow Projection
A24: Year | B24: Today | C24: Yr 1 | D24: Yr 2 | E24: Yr 3 | F24: Yr 4 | G24: Yr 5 | H24: Terminal Value @ Yr 5
A26: FCF | B26: =Process_CSCF!K5 -> 78.53 | C26: =Process_CSCF!L5 -> 82.4565 | D26: =Process_CSCF!M5 -> 86.167042 | E26: =Process_CSCF!N5 -> 89.613724 | F26: =Process_CSCF!O5 -> 92.750205 | G26: =Process_CSCF!P5 -> 95.532711
A27: FCF with Terminal Value | B27: {=Process_CSCF!K5:Q5} -> 78.53 | C27: 82.4565 | D27: 86.167042 | E27: 89.613724 | F27: 92.750205 | G27: 95.532711 | H27: 1801.6928
A28: Present Value | B28: =B27/(1+$B$9)^0 -> 78.53 | C28: =C27/(1+$B$9)^1 -> 76.769111 | D28: =D27/(1+$B$9)^2 -> 74.690337 | E28: =E27/(1+$B$9)^3 -> 72.320159 | F28: =F27/(1+$B$9)^4 -> 69.688535 | G28: =G27/(1+$B$9)^5 -> 66.828264 | H28: =H27/(1+$B$9)^5 -> 1260.3432
A31: Free Cash Flow Projection
A33: Enterprise Value | B33: =SUM(B28:H28) -> 1699.1696
A34: Firm Cash | B34: ='Balance Sheet'!K19 -> 41.88
A35: Firm Debt | B35: ='Balance Sheet'!K103+'Balance Sheet'!K94 -> 319.65
A36: Equity Value | B36: =B33+B34-B35 -> 1421.3996
A37: Fair Share Price | B37: =B36/B6 -> 35.183158
A38: Recommendation | B38: SELL
A40: Sensitivity Analysis
A41: Terminal Growth Rate vs Discount Rate (CSCF)
B42: =B37 -> 35.183158 | C42: 0.055 | D42: 0.06 | E42: 0.0741 | F42: 0.08 | G42: 0.085 | H42: 0.09
B43: 0 | C43: 28.892736 | D43: 28.191396 | E43: 26.312668 | F43: 25.567677 | G43: 24.954345 | H43: 24.356996
B44: 0.005 | C44: 30.791237 | D44: 30.045541 | E44: 28.048268 | F44: 27.256384 | G44: 26.604498 | H44: 25.969648
B45: 0.01 | C45: 32.985989 | D45: 32.189016 | E45: 30.054698 | F45: 29.208604 | G45: 28.512149 | H45: 27.833945
B46: 0.015 | C46: 35.5522 | D46: 34.695272 | E46: 32.400715 | F46: 31.491237 | G46: 30.742669 | H46: 30.013774
B47: 0.02 | C47: 38.592896 | D47: 37.664926 | E47: 35.180503 | F47: 34.19592 | G47: 33.385604 | H47: 32.596645
B48: 0.025 | C48: 42.253075 | D48: 41.239591 | E48: 38.526619 | F48: 37.451631 | G48: 36.566987 | H48: 35.705726
B49: 0.03 | C49: 46.743521 | D49: 45.625125 | E49: 42.631761 | F49: 41.445861 | G49: 40.470028 | H49: 39.520066
B50: 0.035 | C50: 52.382879 | D50: 51.132728 | E50: 47.787233 | F50: 46.462042 | G50: 45.37169 | H50: 44.31033
B51: 0.04 | C51: 59.676768 | D51: 58.256207 | E51: 54.455268 | F51: 52.94992 | G51: 51.711449 | H51: 50.50601

Sheet Process_Pro_Forma
A1: REVENUE
A2: Historical | L2: Projected
B3: 2015 | C3: 2016 | D3: 2017 | E3: 2018 | F3: 2019 | G3: 2020 | H3: 2021 | I3: 2022 | J3: 2023 | K3: 2024 | L3: 2025 | M3: 2026 | N3: 2027 | O3: 2028 | P3: 2029
A4: Revenue | B4: {='Income Statement'!B20:K20} -> 416.41 | C4: 442.89 | D4: 476.56 | E4: 510.43 | F4: 525.72 | G4: 561.16 | H4: 625.39 | I4: 735.45 | J4: 772.84 | K4: 519.73
A5: Growth (Calculated) | B5: =(C4-B4)/B4 -> 0.063591172 | C5: =(D4-C4)/C4 -> 0.076023392 | D5: =(E4-D4)/D4 -> 0.071071848 | E5: =(F4-E4)/E4 -> 0.029955136 | F5: =(G4-F4)/F4 -> 0.067412311 | G5: =(H4-G4)/G4 -> 0.11445933 | H5: =(I4-H4)/H4 -> 0.17598618 | I5: =(J4-I4)/I4 -> 0.050839622 | J5: =(K4-J4)/J4 -> -0.32750634 | L5: =K4*(1+L7) -> 547.31918 | M5: =L5*(1+M7) -> 573.63631 | N5: =M5*(1+N7) -> 598.35068 | O5: =N5*(1+O7) -> 621.13808 | P5: =O5*(1+P7) -> 641.68762
A6: AVERAGE | B6: =AVERAGE(B5:I5) -> 0.081167375
A7: Gowth Assumptions | L7: =DCF_Pro_Forma!B10 -> 0.053083687 | M7: =L7-0.5% -> 0.048083687 | N7: =M7-0.5% -> 0.043083687 | O7: =N7-0.5% -> 0.038083687 | P7: =O7-0.5% -> 0.033083687
A9: EBIT
A10: Historical | L10: Projected
B11: 2015 | C11: 2016 | D11: 2017 | E11: 2018 | F11: 2019 | G11: 2020 | H11: 2021 | I11: 2022 | J11: 2023 | K11: 2024 | L11: 2025 | M11: 2026 | N11: 2027 | O11: 2028 | P11: 2029
A12: EBIT | B12: {='Income Statement'!B46:K46} -> 21.35 | C12: 25.63 | D12: 141.49 | E12: -11.1 | F12: 40.13 | G12: 44.19 | H12: 40.55 | I12: 11.08 | J12: 47.43 | K12: 8.95 | L12: =L5*L15 -> 32.839151 | M12: =M5*M15 -> 34.418179 | N12: =N5*N15 -> 35.901041 | O12: =O5*O15 -> 37.268285 | P12: =P5*P15 -> 38.501257
A13: EBIT Margin | B13: =B12/B4 -> 0.051271583 | C13: =C12/C4 -> 0.0578699 | D13: =D12/D4 -> 0.29689861 | E13: =E12/E4 -> -0.021746371 | F13: =F12/F4 -> 0.076333409 | G13: =G12/G4 -> 0.078747594 | H13: =H12/H4 -> 0.06483954 | I13: =I12/I4 -> 0.015065606 | ... K13: =K12/K4 -> 0.01722048
A14: AVERAGE/MEDIAN | B14: =AVERAGE(F13:K13) -> 0.052262946 | C14: =MEDIAN(F13:K13) -> 0.063105294
A15: Growth Assumptions | L15: 0.06 | M15: 0.06 | N15: 0.06 | O15: 0.06 | P15: 0.06
A17: TAX
A18: Historical | L18: Projected
B19: 2015 | C19: 2016 | D19: 2017 | E19: 2018 | F19: 2019 | G19: 2020 | H19: 2021 | I19: 2022 | J19: 2023 | K19: 2024 | L19: 2025 | M19: 2026 | N19: 2027 | O19: 2028 | P19: 2029
A20: Tax | B20: {=-('Cash Flow'!B40:K40)} -> 8.61 | C20: 10.41 | D20: 23.77 | E20: 13.52 | F20: 15.45 | G20: 19.05 | H20: 19.55 | I20: 14.83 | J20: 14.89 | K20: 23.59 | L20: =L12*$B$22 -> 8.2097878 | M20: =M12*$B$22 -> 8.6045446 | N20: =N12*$B$22 -> 8.9752602 | O20: =O12*$B$22 -> 9.3170712 | P20: =P12*$B$22 -> 9.6253142
A21: Implied Tax Rate | B21: =B20/B12 -> 0.40327869 | C21: =C20/C12 -> 0.40616465 | D21: =D20/D12 -> 0.16799774 | E21: =E20/E12 -> -1.218018 | F21: =F20/F12 -> 0.38499875 | G21: =G20/G12 -> 0.43109301 | H21: =H20/H12 -> 0.48212084 | I21: =I20/I12 -> 1.3384477 | ... K21: =K20/K12 -> 2.6357542
A22: Tax Rate (25% of EBIT) | B22: 0.25
A24: DEPRECIATION AND OTHER NON-CASH ITEMS
A25: Historical | L25: Projected
B26: 2015 | C26: 2016 | D26: 2017 | E26: 2018 | F26: 2019 | G26: 2020 | H26: 2021 | I26: 2022 | J26: 2023 | K26: 2024 | L26: 2025 | M26: 2026 | N26: 2027 | O26: 2028 | P26: 2029
A27: Depreciation & Ammortization | B27: ='Cash Flow'!B20+'Cash Flow'!B21+'Cash Flow'!B22+'Cash Flow'!B26 -> 40.59 | C27: ='Cash Flow'!C20+'Cash Flow'!C21+'Cash Flow'!C22+'Cash Flow'!C26 -> 33.95 | D27: ='Cash Flow'!D20+'Cash Flow'!D21+'Cash Flow'!D22+'Cash Flow'!D26 -> 36.73 | E27: ='Cash Flow'!E20+'Cash Flow'!E21+'Cash Flow'!E22+'Cash Flow'!E26 -> 49.12 | F27: ='Cash Flow'!F20+'Cash Flow'!F21+'Cash Flow'!F22+'Cash Flow'!F26 -> 51.28 | G27: ='Cash Flow'!G20+'Cash Flow'!G21+'Cash Flow'!G22+'Cash Flow'!G26 -> 41.78 | H27: ='Cash Flow'!H20+'Cash Flow'!H21+'Cash Flow'!H22+'Cash Flow'!H26 -> 46.59 | I27: ='Cash Flow'!I20+'Cash Flow'!I21+'Cash Flow'!I22+'Cash Flow'!I26 -> 59.53 | ... K27: ='Cash Flow'!K20+'Cash Flow'!K21+'Cash Flow'!K22+'Cash Flow'!K26 -> 50.42 | L27: =L5*L30 -> 43.785535 | M27: =M5*M30 -> 45.890905 | N27: =N5*N30 -> 47.868054 | O27: =O5*O30 -> 49.691046 | P27: =P5*P30 -> 51.335009
A28: D&A of Revenue | B28: =B27/B4 -> 0.097476045 | C28: =C27/C4 -> 0.076655603 | D28: =D27/D4 -> 0.077073191 | E28: =E27/E4 -> 0.096232588 | F28: =F27/F4 -> 0.097542418 | G28: =G27/G4 -> 0.074452919 | H28: =H27/H4 -> 0.074497514 | I28: =I27/I4 -> 0.08094364 | ... K28: =K27/K4 -> 0.09701191
A29: AVERAGE | B29: =AVERAGE(B28:K28) -> 0.084685607
A30: Growth Assumptions | L30: 0.08 | M30: 0.08 | N30: 0.08 | O30: 0.08 | P30: 0.08
A32: CHANGE IN WORKING CAPITAL
A33: Historical | L33: Projected
B34: 2015 | C34: 2016 | D34: 2017 | E34: 2018 | F34: 2019 | G34: 2020 | H34: 2021 | I34: 2022 | J34: 2023 | K34: 2024 | L34: 2025 | M34: 2026 | N34: 2027 | O34: 2028 | P34: 2029
A35: Net Working Capital | B35: =('Balance Sheet'!B22+'Balance Sheet'!B25+'Balance Sheet'!B26+'Balance Sheet'!B27) - ('Balance Sheet'!B82+'Balance Sheet'!B84+'Balance Sheet'!B85) -> 92.35 | C35: =('Balance Sheet'!C22+'Balance Sheet'!C25+'Balance Sheet'!C26+'Balance Sheet'!C27) - ('Balance Sheet'!C82+'Balance Sheet'!C84+'Balance Sheet'!C85) -> 82.06 | D35: =('Balance Sheet'!D22+'Balance Sheet'!D25+'Balance Sheet'!D26+'Balance Sheet'!D27) - ('Balance Sheet'!D82+'Balance Sheet'!D84+'Balance Sheet'!D85) -> 2.03 | E35: =('Balance Sheet'!E22+'Balance Sheet'!E25+'Balance Sheet'!E26+'Balance Sheet'!E27) - ('Balance Sheet'!E82+'Balance Sheet'!E84+'Balance Sheet'!E85) -> -50.12 | F35: =('Balance Sheet'!F22+'Balance Sheet'!F25+'Balance Sheet'!F26+'Balance Sheet'!F27) - ('Balance Sheet'!F82+'Balance Sheet'!F84+'Balance Sheet'!F85) -> -53.22 | G35: =('Balance Sheet'!G22+'Balance Sheet'!G25+'Balance Sheet'!G26+'Balance Sheet'!G27) - ('Balance Sheet'!G82+'Balance Sheet'!G84+'Balance Sheet'!G85) -> -68.48 | H35: =('Balance Sheet'!H22+'Balance Sheet'!H25+'Balance Sheet'!H26+'Balance Sheet'!H27) - ('Balance Sheet'!H82+'Balance Sheet'!H84+'Balance Sheet'!H85) -> -141.56 | I35: =('Balance Sheet'!I22+'Balance Sheet'!I25+'Balance Sheet'!I26+'Balance Sheet'!I27) - ('Balance Sheet'!I82+'Balance Sheet'!I84+'Balance Sheet'!I85) -> -154.44 | ... K35: =('Balance Sheet'!K22+'Balance Sheet'!K25+'Balance Sheet'!K26+'Balance Sheet'!K27) - ('Balance Sheet'!K82+'Balance Sheet'!K84+'Balance Sheet'!K85) -> -231.37
A36: Change in Working Capital | B36: =C35-B35 -> -10.29 | C36: =D35-C35 -> -80.03 | D36: =E35-D35 -> -52.15 | E36: =F35-E35 -> -3.1 | F36: =G35-F35 -> -15.26 | G36: =H35-G35 -> -73.08 | H36: =I35-H35 -> -12.88 | I36: =J35-I35 -> 39.53 | J36: =K35-J35 -> -116.46 | L36: =L5*$B$37 -> 2.7365959 | M36: =M5*$B$37 -> 2.8681815 | N36: =N5*$B$37 -> 2.9917534 | O36: =O5*$B$37 -> 3.1056904 | P36: =P5*$B$37 -> 3.2084381
A37: NWC Assumption Rate | B37: 0.005
A39: CAPITAL EXPENDITURE
A40: Historical | L40: Projected
B41: 2015 | C41: 2016 | D41: 2017 | E41: 2018 | F41: 2019 | G41: 2020 | H41: 2021 | I41: 2022 | J41: 2023 | K41: 2024 | L41: 2025 | M41: 2026 | N41: 2027 | O41: 2028 | P41: 2029
A42: CapEx (PPE & Intangibles) | B42: =-('Cash Flow'!B53+'Cash Flow'!B54) -> 14.06 | C42: =-('Cash Flow'!C53+'Cash Flow'!C54) -> 6.83 | D42: =-('Cash Flow'!D53+'Cash Flow'!D54) -> 12.41 | E42: =-('Cash Flow'!E53+'Cash Flow'!E54) -> 12.37 | F42: =-('Cash Flow'!F53+'Cash Flow'!F54) -> 5.94 | G42: =-('Cash Flow'!G53+'Cash Flow'!G54) -> 4.35 | H42: =-('Cash Flow'!H53+'Cash Flow'!H54) -> 10.62 | I42: =-('Cash Flow'!I53+'Cash Flow'!I54) -> 24.48 | ... K42: =-('Cash Flow'!K53+'Cash Flow'!K54) -> 7.45 | L42: =L45*L5 -> 8.2097878 | M42: =M45*M5 -> 8.6045446 | N42: =N45*N5 -> 8.9752602 | O42: =O45*O5 -> 9.3170712 | P42: =P45*P5 -> 9.6253142
A43: CapEx % of Revenue | B43: =B42/B4 -> 0.033764799 | C43: =C42/C4 -> 0.015421436 | D43: =D42/D4 -> 0.026040792 | E43: =E42/E4 -> 0.024234469 | F43: =F42/F4 -> 0.01129879 | G43: =G42/G4 -> 0.0077517998 | H43: =H42/H4 -> 0.016981404 | I43: =I42/I4 -> 0.033285743 | ... K43: =K42/K4 -> 0.014334366
A44: AVERAGE | B44: =AVERAGE(B43:K43) -> 0.019927477
A45: Growth Assumptions | L45: 0.015 | M45: 0.015 | N45: 0.015 | O45: 0.015 | P45: 0.015

Sheet DCF_Pro_Forma
A1: Input and Assumptions
J2: Cells in YELLOW are input
A3: Last Updated on | B3: =DCF_CSCF!B3 -> 46073
A4: Last Financial Statement Date | B4: ='Balance Sheet'!K18 -> 30-12-2024 | J4: Cells in BEIGE are looked up
A5: Current Market Price | B5: =DCF_CSCF!B5 -> 40.25
A6: # of share outstanding in million | B6: =DCF_CSCF!B6 -> 40.4 | J6: Cells in WHITE are calculated
A7: Growth rate of FCF (long term growth) | B7: 0.02
A8: Discount rate (WACC) | B8: 0.0741
A9: Inflation | B9: 0.025
A10: Assumption on the average growth rate of | B10: =(Process_Pro_Forma!B6+B9)/2 -> 0.053083687
A11: Industry Tax Rate | B11: 0.2
A14: Effective Tax Rate | B14: =Process_Pro_Forma!B22 -> 0.25
A16: Investment Criteria
A18: Decision | B18: Difference Between Value and Price
A19: Sell | B19: =ROUND((B45-B5) / B5, 3) -> -0.469 | C19: {=_xlfn.IFS(B19>0.1,"BUY",B19<-0.1,"SELL",TRUE,"HOLD")} -> SELL
A20: Underperform
A21: HOLD
A22: BUY
A23: Strong Buy
A25: Free Cash Flow Projection
A27: Year | B27: Today | C27: Yr 1 | D27: Yr 2 | E27: Yr 3 | F27: Yr 4 | G27: Yr 5 | H27: Terminal Value @ Yr 5
A28: EBIT (Operating Income) | C28: {=Process_Pro_Forma!L12:P12} -> 32.839151 | D28: 34.418179 | E28: 35.901041 | F28: 37.268285 | G28: 38.501257
A29: Tax Rate | C29: =$B$14 -> 0.25 | D29: =$B$14 -> 0.25 | E29: =$B$14 -> 0.25 | F29: =$B$14 -> 0.25 | G29: =$B$14 -> 0.25
A30: NOPAT | C30: =C28*(1-C29) -> 24.629363 | D30: =D28*(1-D29) -> 25.813634 | E30: =E28*(1-E29) -> 26.92578 | F30: =F28*(1-F29) -> 27.951213 | G30: =G28*(1-G29) -> 28.875943
A31: Depreciation and Other non-cash items | C31: {=Process_Pro_Forma!L27:P27} -> 43.785535 | D31: 45.890905 | E31: 47.868054 | F31: 49.691046 | G31: 51.335009
A32: Change in NWC | C32: {=Process_Pro_Forma!L36:P36} -> 2.7365959 | D32: 2.8681815 | E32: 2.9917534 | F32: 3.1056904 | G32: 3.2084381
A33: Capital expenditure | C33: {=Process_Pro_Forma!L42:P42} -> 8.2097878 | D33: 8.6045446 | E33: 8.9752602 | F33: 9.3170712 | G33: 9.6253142
A34: FCF | C34: =(C30+C31)-(C32+C33) -> 57.468514 | D34: =(D30+D31)-(D32+D33) -> 60.231813 | E34: =(E30+E31)-(E32+E33) -> 62.826821 | F34: =(F30+F31)-(F32+F33) -> 65.219498 | G34: =(G30+G31)-(G32+G33) -> 67.3772
A35: FCF with Terminal Value | C35: {=C34:G34} -> 57.468514 | D35: 60.231813 | E35: 62.826821 | F35: 65.219498 | G35: 67.3772 | H35: =G35*(1+B7) / (B8-B7) -> 1270.328
A36: Present Value | C36: =C35/(1+$B$8)^1 -> 53.503877 | D36: =D35/(1+$B$8)^2 -> 52.207933 | E36: =E35/(1+$B$8)^3 -> 50.700348 | F36: =F35/(1+$B$8)^4 -> 49.000283 | G36: =G35/(1+$B$8)^5 -> 47.129125 | H36: =H35/(1+$B$8)^5 -> 888.5713
A39: Free Cash Flow Projection
A41: Enterprise Value | B41: =SUM(C36:H36) -> 1141.1129
A42: Firm Cash | B42: =DCF_CSCF!B34 -> 41.88
A43: Firm Debt | B43: =DCF_CSCF!B35 -> 319.65
A44: Equity Value | B44: =(B41+B42)-B43 -> 863.34286
A45: Fair Share Price | B45: =B44/B6 -> 21.369873
A46: Recommendation | B46: SELL
A50: Sensitivity Analysis
A51: Terminal Growth Rate vs Discount Rate (CSCF)
B55: Scenario 1: Discount Rate ±10% | C55: WACC | D55: Fair Price
B56: Case | D56: =B45 -> 21.369873
B57: Low | C57: 0.0667 | D57: 25.879714
B58: Base | C58: 0.0741 | D58: 21.369873
B59: High | C59: 0.0815 | D59: 17.945977
B61: Scenario 2: Long-Term Growth ±10% | C61: Long_term g | D61: Fair Price
B62: Case | D62: =B45 -> 21.369873
B63: Low | C63: 0.018 | D63: 20.544172
B64: Base | C64: 0.02 | D64: 21.369873
B65: High | C65: 0.022 | D65: 22.258967
B67: Scenario 3: Inflation ±10% | C67: Inflation Rate | D67: Fair Price
B68: Case | D68: =B45 -> 21.369873
B69: Low | C69: 0.0225 | D69: 21.216502
B70: Base | C70: 0.025 | D70: 21.369873
B71: High | C71: 0.0275 | D71: 21.523944
B73: Scenario 4: Short-Term Revenue Growth ±10% | C73: Short-term g | D73: Fair Price
B74: Case | D74: =B45 -> 21.369873
B75: Low | C75: 0.0478 | D75: 20.72633
B76: Base | C76: 0.0531 | D76: 21.371879
B77: High | C77: 0.0584 | D77: 22.030021
B79: Scenario 5: Industry Tax Rate ±10% | C79: Tax Rate | D79: Fair Price
B80: Case | D80: =B45 -> 21.369873
B81: Low | C81: 0.18 | D81: 22.499688
B82: Base (Industry Tax Rate) | C82: 0.2 | D82: 22.176883
B83: High | C83: 0.22 | D83: 21.854079

Sheet CCA
A1: Input and Assumptions
I2: Cells in YELLOW are input
A3: Last Updated on | B3: =DCF_Pro_Forma!B3 -> 46073
A4: Last Financial Statement Date | B4: ='Balance Sheet'!K18 -> 30-12-2024 | I4: Cells in BEIGE are looked up
A5: Current Market Price | B5: =DCF_Pro_Forma!B5 -> 40.25
A6: # of share outstanding in million | B6: =DCF_Pro_Forma!B6 -> 40.4 | I6: Cells in WHITE are calculated
A7: Comparable Companies | B7: Company 1 | C7: Company 2 | D7: Company 3 | E7: Company 4 | F7: Company 5
A8: Mutiples Ratios at | B8: Colliers International | C8: FirstService Corp | D8: CBRE Group | E8: Jones Lang LaSalle | F8: Real Matters Inc | I8: Cells in RED are output
A9: Total Enterprise Value (TEV)/Revenue | B9: 1.22 | C9: 1.47 | D9: 1.04 | E9: 0.72 | F9: 4.41
A10: TEV/EBITDA | B10: 9.26 | C10: 14.3 | D10: 12.58 | E10: 9.79 | F10: 22.64
A11: P/E | B11: 15.24 | C11: 25.17 | D11: 19.91 | E11: 15 | F11: 33.82
A13: Your Company Information
A14: Revenue | B14: ='Income Statement'!K20 -> 519.73
A15: EBITDA | B15: ='Income Statement'!K46+'Income Statement'!K34+'Income Statement'!K35+'Income Statement'!K36 -> 52.97
A16: Earnings per share | B16: ='Income Statement'!K94 -> 0.29
A18: Investment Criteria
A20: Decision | B20: Difference Between Value and Price
A21: Sell | B21: =ROUND((B46-B5) / B5, 3) -> -0.781 | C21: {=_xlfn.IFS(B21>0.1,"BUY",B21<-0.1,"SELL",TRUE,"HOLD")} -> SELL
A22: Underperform
A23: HOLD
A24: BUY
A25: Strong Buy
A28: Average Multiple
B30: average | C30: median | D30: your company
A31: TEV/Revenue | B31: =AVERAGE(B9:F9) -> 1.772 | C31: =MEDIAN(B9:F9) -> 1.22 | D31: 2.16
A32: TEV/EBITDA | B32: =AVERAGE(B10:F10) -> 13.714 | C32: =MEDIAN(B10:F10) -> 12.58 | D32: 9.32
A33: P/E | B33: =AVERAGE(B11:F11) -> 21.828 | C33: =MEDIAN(B11:F11) -> 19.91 | D33: 17.7
A39: Free Cash Flow Projection
A41: implied by | B41: TEV/Revenue | C41: TEV/EBITDA | D41: Implied Share Price (P/E)
A42: Enterprise Value | B42: =C31*B14 -> 634.0706 | C42: =C32*B15 -> 666.3626
A43: Firm Cash | B43: =DCF_Pro_Forma!B42 -> 41.88 | C43: 42
A44: Firm Debt | B44: =DCF_Pro_Forma!B43 -> 319.65 | C44: 320
A45: Equity Value | B45: =B42+B43-B44 -> 356.3006 | C45: =C42+C43-C44 -> 388.3626
A46: Fair Share Price | B46: =B45/B6 -> 8.8193218 | C46: =C45/B6 -> 9.6129356 | D46: =C33*B16 -> 5.7739
A47: Recommendation | B47: SELL | C47: SELL | D47: SELL
